Workbook

Sheet 1850 Not Stated Clean
A1: Line Number | B1: Dwelling Number | C1: Family Number | D1: Given Name | E1: Surname | F1: Age | G1: Birth Date | H1: Gender | I1: Race | J1: Occupation | K1: Industry | L1: Value of Real Estate | M1: Birth Place | N1: Married within the Year | O1: Attended School | P1: Cannot Read, Write | Q1: Condition
A2: 1 | B2: 1 | C2: 1 | D2: Sherman | E2: Reynolds | F2: 34 | G2: 1816 | H2: Male | I2: White | J2: Merchant | L2: 10160 | M2: New York
A3: 2 | B3: 1 | C3: 1 | D3: Martha | E3: Reynolds | F3: 22 | G3: 1828 | H3: Female | I3: White | M3: Illinois
A4: 3 | B4: 1 | C4: 1 | D4: Albert B | E4: Reynolds | F4: 2 | G4: 1848 | H4: Male | I4: White | M4: Texas
A5: 4 | B5: 2 | C5: 2 | D5: Sherman A | E5: Reynolds | F5: 5/12 | G5: 1850 | H5: Male | I5: White | M5: Texas
A6: 5 | B6: 2 | C6: 2 | D6: H M | E6: Lawhon | F6: 45 | G6: 1805 | H6: Male | I6: White | J6: Farmer | K6: Agriculture | L6: 300 | M6: North Carolina
A7: 6 | B7: 2 | C7: 2 | D7: Anna | E7: Lawhon | F7: 44 | G7: 1806 | H7: Female | I7: White | M7: Georgia
A8: 7 | B8: 2 | C8: 2 | D8: Frances | E8: Lawhon | F8: 23 | G8: 1827 | H8: Female | I8: White | M8: Alabama
A9: 8 | B9: 2 | C9: 2 | D9: William C | E9: Lawhon | F9: 21 | G9: 1829 | H9: Male | I9: White | J9: Farmhand | K9: Agriculture | M9: Tennessee
A10: 9 | B10: 2 | C10: 2 | D10: E M | E10: Lawhon | F10: 17 | G10: 1833 | H10: Female | I10: White | M10: Alabama
A11: 10 | B11: 2 | C11: 2 | D11: S | E11: Lawhon | F11: 14 | G11: 1836 | H11: Female | I11: White | M11: Alabama
A12: 11 | B12: 2 | C12: 2 | D12: D | E12: Lawhon | F12: 13 | G12: 1837 | H12: Male | I12: White | M12: Alabama
A13: 12 | B13: 2 | C13: 2 | D13: M A | E13: Lawhon | F13: 9 | G13: 1841 | H13: Female | I13: White | M13: Alabama
A14: 13 | B14: 2 | C14: 2 | D14: John W | E14: Lawhon | F14: 5 | G14: 1845 | H14: Male | I14: White | M14: Alabama
A15: 14 | B15: 2 | C15: 2 | D15: R L | E15: Lawhon | F15: 2 | G15: 1848 | H15: Female | I15: White | M15: Alabama
A16: 15 | B16: 3 | C16: 3 | D16: James W | E16: Moore | F16: 55 | G16: 1795 | H16: Male | I16: White | J16: Farmer | K16: Agriculture | L16: 4400 | M16: Georgia
A17: 16 | B17: 3 | C17: 3 | D17: M | E17: Moore | F17: 40 | G17: 1810 | H17: Female | I17: White | M17: Tennessee
A18: 17 | B18: 3 | C18: 3 | D18: H | E18: Moore | F18: 22 | G18: 1828 | H18: Male | I18: White | J18: Farmhand | K18: Agriculture | M18: Arkansas
A19: 18 | B19: 3 | C19: 3 | D19: J A | E19: Moore | F19: 20 | G19: 1830 | H19: Male | I19: White | J19: Farmhand | K19: Agriculture | M19: Arkansas
A20: 19 | B20: 3 | C20: 3 | D20: D E | E20: Moore | F20: 17 | G20: 1833 | H20: Male | I20: White | J20: Farmhand | K20: Agriculture | M20: Texas
A21: 20 | B21: 3 | C21: 3 | D21: R C | E21: Moore | F21: 16 | G21: 1834 | H21: Male | I21: White | J21: Farmhand | K21: Agriculture | M21: Texas
A22: 21 | B22: 3 | C22: 3 | D22: E | E22: Moore | F22: 14 | G22: 1836 | H22: Female | I22: White | M22: Texas | O22: Yes
A23: 22 | B23: 3 | C23: 3 | D23: B | E23: Moore | F23: 10 | G23: 1840 | H23: Male | I23: White | M23: Texas
A24: 23 | B24: 3 | C24: 3 | D24: G | E24: Moore | F24: 8 | G24: 1842 | H24: Male | I24: White | M24: Texas
A25: 24 | B25: 3 | C25: 3 | D25: N J | E25: Moore | F25: 7 | G25: 1843 | H25: Female | I25: White | M25: Texas | O25: Yes
A26: 25 | B26: 3 | C26: 3 | D26: A E | E26: Moore | F26: 5 | G26: 1845 | H26: Female | I26: White | M26: Texas
A27: 26 | B27: 3 | C27: 3 | D27: M E | E27: Moore | F27: 4 | G27: 1846 | H27: Female | I27: White | M27: Texas
A28: 27 | B28: 4 | C28: 4 | D28: Joseph | E28: Priest | F28: 32 | G28: 1818 | H28: Male | I28: White | J28: Farmer | K28: Agriculture | M28: Alabama
A29: 28 | B29: 4 | C29: 4 | D29: E | E29: Priest | F29: 28 | G29: 1822 | H29: Female | I29: White | M29: Alabama
A30: 29 | B30: 4 | C30: 4 | D30: George W | E30: Priest | F30: 10 | G30: 1840 | H30: Male | I30: White | M30: Mississippi | O30: Yes
A31: 30 | B31: 4 | C31: 4 | D31: William R | E31: Priest | F31: 8 | G31: 1842 | H31: Male | I31: White | M31: Mississippi
A32: 31 | B32: 4 | C32: 4 | D32: M C | E32: Priest | F32: 6 | G32: 1844 | H32: Female | I32: White | M32: Mississippi
A33: 32 | B33: 4 | C33: 4 | D33: L B | E33: Priest | F33: 4 | G33: 1846 | H33: Male | I33: White | M33: Mississippi
A34: 33 | B34: 4 | C34: 4 | D34: N J | E34: Priest | F34: 2 | G34: 1848 | H34: Female | I34: White | M34: Tennessee
A35: 34 | B35: 5 | C35: 5 | D35: James E | E35: Brady | F35: 40 | G35: 1810 | H35: Male | I35: White | J35: Stone Mason | K35: Construction | M35: New York
A36: 35 | B36: 5 | C36: 5 | D36: M A | E36: Brady | F36: 18 | G36: 1832 | H36: Female | I36: White | M36: Georgia
A37: 36 | B37: 5 | C37: 5 | D37: A L | E37: Brady | F37: 2 | G37: 1848 | H37: Female | I37: White | M37: Texas
A38: 37 | B38: 6 | C38: 6 | D38: Thomas | E38: Mays | F38: 47 | G38: 1803 | H38: Male | I38: White | J38: Farmer | K38: Agriculture | L38: 5000 | M38: Virginia
A39: 38 | B39: 6 | C39: 6 | D39: A | E39: Mays | F39: 32 | G39: 1818 | H39: Female | I39: White | M39: Kentucky
A40: 39 | B40: 6 | C40: 6 | D40: E F | E40: Mays | F40: 12 | G40: 1838 | H40: Female | I40: White | M40: Texas | O40: Yes
A41: 40 | B41: 6 | C41: 6 | D41: M A | E41: Mays | F41: 10 | G41: 1840 | H41: Female | I41: White | M41: Texas | O41: Yes
A42: 41 | B42: 6 | C42: 6 | D42: Thomas F | E42: Mays | F42: 7 | G42: 1843 | H42: Male | I42: White | M42: Texas
A43: 42 | B43: 6 | C43: 6 | D43: Octavia | E43: Mays | F43: 5 | G43: 1845 | H43: Female | I43: White | M43: Texas
A44: 1 | B44: 6 | C44: 6 | D44: Samuel J | E44: Mays | F44: 2 | G44: 1848 | H44: Male | I44: White | M44: Texas
A45: 2 | B45: 7 | C45: 7 | D45: Joel | E45: Cherry | F45: 51 | G45: 1799 | H45: Male | I45: White | J45: Farmer | K45: Agriculture | M45: Tennessee
A46: 3 | B46: 7 | C46: 7 | D46: P | E46: Cherry | F46: 48 | G46: 1802 | H46: Female | I46: White | M46: South Carolina
A47: 4 | B47: 7 | C47: 7 | D47: James | E47: Cherry | F47: 19 | G47: 1831 | H47: Male | I47: White | J47: Farm Hand | K47: Agriculture | M47: Tennessee | P47: Yes
A48: 5 | B48: 7 | C48: 7 | D48: M L | E48: Cherry | F48: 21 | G48: 1829 | H48: Female | I48: White | M48: Tennessee | P48: Yes
A49: 6 | B49: 7 | C49: 7 | D49: N L | E49: Cherry | F49: 17 | G49: 1833 | H49: Female | I49: White | M49: Tennessee
A50: 7 | B50: 7 | C50: 7 | D50: N | E50: Cherry | F50: 14 | G50: 1836 | H50: Male | I50: White | M50: Tennessee
A51: 8 | B51: 7 | C51: 7 | D51: J | E51: Cherry | F51: 12 | G51: 1838 | H51: Male | I51: White | M51: Tennessee
A52: 9 | B52: 7 | C52: 7 | D52: R | E52: Cherry | F52: 10 | G52: 1840 | H52: Male | I52: White | M52: Tennessee
A53: 10 | B53: 8 | C53: 8 | D53: John | E53: Faucet | F53: 34 | G53: 1816 | H53: Male | I53: White | J53: Farmer | K53: Agriculture | L53: 2150 | M53: England
A54: 11 | B54: 8 | C54: 8 | D54: M W T | E54: Faucet | F54: 23 | G54: 1827 | H54: Female | I54: White | M54: Alabama
A55: 12 | B55: 8 | C55: 8 | D55: J.P. | E55: Faucet | F55: 3 | G55: 1847 | H55: Female | I55: White | M55: Texas
A56: 13 | B56: 8 | C56: 8 | D56: William | E56: Faucet | F56: 28 | G56: 1822 | H56: Male | I56: White | J56: Cooper | K56: Miscellaneous Wood Products | M56: Ohio
A57: 14 | B57: 9 | C57: 9 | D57: William A | E57: Hemphill | F57: 32 | G57: 1818 | H57: Male | I57: White | J57: Farmer | K57: Agriculture | L57: 2000 | M57: Georgia
A58: 15 | B58: 9 | C58: 9 | D58: M J | E58: Hemphill | F58: 16 | G58: 1834 | H58: Female | I58: White | M58: Alabama
A59: 16 | B59: 10 | C59: 10 | D59: James | E59: Nickolson | F59: 34 | G59: 1816 | H59: Male | I59: White | J59: Merchant | K59: Not Specified Retail Trade | L59: 3100 | M59: England
A60: 17 | B60: 10 | C60: 10 | D60: R H | E60: Nickolson | F60: 30 | G60: 1820 | H60: Female | I60: White | M60: Tennessee
A61: 18 | B61: 10 | C61: 10 | D61: William | E61: Nickolson | F61: 13 | G61: 1837 | H61: Male | I61: White | M61: New York | O61: Yes
A62: 19 | B62: 10 | C62: 10 | D62: Mary A | E62: Nickolson | F62: 11 | G62: 1839 | H62: Female | I62: White | M62: Texas | O62: Yes
A63: 20 | B63: 10 | C63: 10 | D63: H | E63: Nickolson | F63: 9 | G63: 1841 | H63: Male | I63: White | M63: Texas | O63: Yes
A64: 21 | B64: 10 | C64: 10 | D64: R | E64: Nickolson | F64: 7 | G64: 1843 | H64: Female | I64: White | M64: Texas
A65: 22 | B65: 10 | C65: 10 | D65: Samuel | E65: Nickolson | F65: 1 | G65: 1849 | H65: Male | I65: White | M65: Texas
A66: 23 | B66: 10 | C66: 10 | D66: Charles | E66: Ploger | F66: 26 | G66: 1824 | H66: Male | I66: White | J66: M D | K66: Medical and Other Health Services, Except Hospitals | M66: Germany
A67: 24 | B67: 10 | C67: 10 | D67: M J | E67: Smith | F67: 32 | G67: 1818 | H67: Male | I67: White | J67: Clerk | K67: Not Specified Retail Trade | M67: North Carolina
A68: 25 | B68: 10 | C68: 10 | D68: Philip | E68: Schnyder | F68: 14 | G68: 1836 | H68: Male | I68: White | M68: Germany
A69: 26 | B69: 11 | C69: 11 | D69: Phil | E69: Claiborne | F69: 33 | G69: 1817 | H69: Male | I69: White | J69: Lawyer | K69: Legal Services | L69: 3600 | M69: Virginia
A70: 27 | B70: 11 | C70: 11 | D70: Mary C | E70: Claiborne | F70: 24 | G70: 1826 | H70: Female | I70: White | M70: Missouri
A71: 28 | B71: 11 | C71: 11 | D71: John M | E71: Claiborne | F71: 11 | G71: 1839 | H71: Male | I71: White | M71: Tennessee | O71: Yes
A72: 29 | B72: 11 | C72: 11 | D72: Martha A | E72: Claiborne | F72: 9 | G72: 1841 | H72: Female | I72: White | M72: Tennessee | O72: Yes
A73: 30 | B73: 11 | C73: 11 | D73: Austin | E73: Claiborne | F73: 6 | G73: 1844 | H73: Male | I73: White | M73: Tennessee
A74: 31 | B74: 11 | C74: 11 | D74: Myriam J | E74: Claiborne | F74: 1 | G74: 1849 | H74: Female | I74: White | M74: Texas
A75: 32 | B75: 12 | C75: 12 | D75: William R | E75: Redding | F75: 42 | G75: 1808 | H75: Male | I75: White | L75: 4000 | M75: Tennessee
A76: 33 | B76: 12 | C76: 12 | D76: J M | E76: Redding | F76: 27 | G76: 1823 | H76: Female | I76: White | M76: Tennessee
A77: 34 | B77: 12 | C77: 12 | D77: J W | E77: Redding | F77: 4 | G77: 1846 | H77: Male | I77: White | M77: Texas
A78: 35 | B78: 12 | C78: 12 | D78: William R | E78: Redding | F78: 2 | G78: 1848 | H78: Male | I78: White | M78: Texas
A79: 36 | B79: 12 | C79: 12 | D79: T J | E79: Redding | F79: 2 | G79: 1848 | H79: Female | I79: White | M79: Texas
A80: 37 | B80: 12 | C80: 12 | D80: John | E80: Mitchell | F80: 40 | G80: 1810 | H80: Male | I80: White | J80: None | K80: Non-Industrial Response | M80: Virginia
A81: 38 | B81: 13 | C81: 13 | D81: Chauncey | E81: Johnson | F81: 52 | G81: 1798 | H81: Male | I81: White | J81: Merchant | K81: Not Specified Retail Trade | L81: 22000 | M81: Vermont
A82: 39 | B82: 13 | C82: 13 | D82: E | E82: Johnson | F82: 52 | G82: 1798 | H82: Female | I82: White | M82: Massachusetts
A83: 40 | B83: 13 | C83: 13 | D83: M | E83: Johnson | F83: 21 | G83: 1829 | H83: Female | I83: White | M83: New York
A84: 41 | B84: 13 | C84: 13 | D84: E | E84: Johnson | F84: 16 | G84: 1834 | H84: Female | I84: White | M84: New York | O84: Yes
A85: 42 | B85: 13 | C85: 13 | D85: C | E85: Johnson | F85: 14 | G85: 1836 | H85: Female | I85: White | O85: Yes
A86: 1 | B86: 13 | C86: 14 | D86: Henry S | E86: Phillips | F86: 40 | G86: 1810 | H86: Male | I86: White | J86: Carpenter | K86: Construction | L86: 2880 | M86: Virginia
A87: 2 | B87: 13 | C87: 14 | D87: E | E87: Phillips | F87: 23 | G87: 1827 | H87: Female | I87: White | M87: New York
A88: 3 | B88: 13 | C88: 14 | D88: Julia | E88: Phillips | F88: 6 | G88: 1844 | H88: Female | I88: White | M88: Texas | O88: Yes
A89: 4 | B89: 13 | C89: 14 | D89: Leman | E89: Phillips | F89: 3 | G89: 1847 | H89: Male | I89: White | M89: Texas
A90: 5 | B90: 13 | C90: 14 | D90: J | E90: Leffinger | F90: 34 | G90: 1816 | H90: Male | I90: White | J90: Carpenter | K90: Construction | M90: New York
A91: 6 | B91: 13 | C91: 14 | D91: William | E91: Richardson | F91: 20 | G91: 1830 | H91: Male | I91: White | J91: Carpenter | K91: Construction | M91: New York
A92: 7 | B92: 14 | C92: 15 | D92: John S | E92: Johnson | F92: 25 | G92: 1825 | H92: Male | I92: White | J92: Merchant | K92: Not Specified Retail Trade | L92: 1000 | M92: New York
A93: 8 | B93: 14 | C93: 15 | D93: P | E93: Johnson | F93: 19 | G93: 1831 | H93: Female | I93: White | M93: South Carolina
A94: 9 | B94: 14 | C94: 15 | D94: A | E94: Johnson | F94: 7/12 | G94: 1850 | H94: Male | I94: White | M94: Texas
A95: 10 | B95: 15 | C95: 16 | D95: Westty | E95: Dykes | F95: 38 | G95: 1812 | H95: Male | I95: White | J95: Farmer | K95: Agriculture | L95: 100 | M95: Louisiana
A96: 11 | B96: 15 | C96: 16 | D96: H | E96: Dykes | F96: 37 | G96: 1813 | H96: Female | I96: White | M96: Louisiana
A97: 12 | B97: 15 | C97: 16 | D97: M | E97: Dykes | F97: 13 | G97: 1837 | H97: Female | I97: White | M97: Texas | O97: Yes
A98: 13 | B98: 15 | C98: 16 | D98: Frances | E98: Dykes | F98: 9 | G98: 1841 | H98: Female | I98: White | M98: Texas | O98: Yes
A99: 14 | B99: 15 | C99: 16 | D99: A | E99: Dykes | F99: 7 | G99: 1843 | H99: Female | I99: White | M99: Texas | O99: Yes
A100: 15 | B100: 15 | C100: 16 | D100: E | E100: Dykes | F100: 5 | G100: 1845 | H100: Female | I100: White | M100: Texas
...

Sheet 1850 Not Stated Raw
A1: Line Number | B1: Dwelling Number | C1: Family Number | D1: Given Name | E1: Surname | F1: Residence Age | G1: Birth Date | H1: Gender | I1: Race | J1: Occupation | K1: Industry | L1: Real Estate | M1: Birth Place | N1: Married within the Year | O1: Attended School | P1: Cannot Read, Write | Q1: Condition | R1: Comp.
A2: 1 | B2: 1 | C2: 1 | D2: Sherman | E2: Reynolds | F2: 34 | G2: 1816 | H2: Male | I2: White | J2: Merchant | K2: Not Specified Retail Trade | L2: 10160 | M2: New York | R2: {=SUMPRODUCT(--('1850 Not Stated Clean'!A2:Q2 <> '1850 Not Stated Raw'!A2:Q2))} -> 1
A3: 2 | B3: 1 | C3: 1 | D3: Martha | E3: Reynolds | F3: 22 | G3: 1828 | H3: Female | I3: White | M3: Illinois | R3: {=SUMPRODUCT(--('1850 Not Stated Clean'!A3:Q3 <> '1850 Not Stated Raw'!A3:Q3))} -> 0
A4: 3 | B4: 1 | C4: 1 | D4: Albert B | E4: Reynolds | F4: 2 | G4: 1848 | H4: Male | I4: White | M4: Texas | R4: {=SUMPRODUCT(--('1850 Not Stated Clean'!A4:Q4 <> '1850 Not Stated Raw'!A4:Q4))} -> 0
A5: 4 | B5: 1 | C5: 1 | D5: Sherman A | E5: Reynolds | F5: 0 | G5: 1850 | H5: Male | I5: White | M5: Texas | R5: {=SUMPRODUCT(--('1850 Not Stated Clean'!A5:Q5 <> '1850 Not Stated Raw'!A5:Q5))} -> 3
A6: 5 | B6: 2 | C6: 2 | D6: H M | E6: Lawhon | F6: 45 | G6: 1805 | H6: Male | I6: White | J6: Farmer | K6: Agriculture | L6: 300 | M6: North Carolina | R6: {=SUMPRODUCT(--('1850 Not Stated Clean'!A6:Q6 <> '1850 Not Stated Raw'!A6:Q6))} -> 0
A7: 6 | B7: 2 | C7: 2 | D7: Anna | E7: Lawhon | F7: 44 | G7: 1806 | H7: Female | I7: White | M7: Georgia | R7: {=SUMPRODUCT(--('1850 Not Stated Clean'!A7:Q7 <> '1850 Not Stated Raw'!A7:Q7))} -> 0
A8: 7 | B8: 2 | C8: 2 | D8: Frances | E8: Lawhon | F8: 23 | G8: 1827 | H8: Female | I8: White | M8: Alabama | R8: {=SUMPRODUCT(--('1850 Not Stated Clean'!A8:Q8 <> '1850 Not Stated Raw'!A8:Q8))} -> 0
A9: 8 | B9: 2 | C9: 2 | D9: William C | E9: Lawhon | F9: 21 | G9: 1829 | H9: Male | I9: White | J9: Farmhand | K9: Agriculture | M9: Tennessee | R9: {=SUMPRODUCT(--('1850 Not Stated Clean'!A9:Q9 <> '1850 Not Stated Raw'!A9:Q9))} -> 0
A10: 9 | B10: 2 | C10: 2 | D10: E M | E10: Lawhon | F10: 17 | G10: 1833 | H10: Female | I10: White | M10: Alabama | R10: {=SUMPRODUCT(--('1850 Not Stated Clean'!A10:Q10 <> '1850 Not Stated Raw'!A10:Q10))} -> 0
A11: 10 | B11: 2 | C11: 2 | D11: S | E11: Lawhon | F11: 14 | G11: 1836 | H11: Female | I11: White | M11: Alabama | R11: {=SUMPRODUCT(--('1850 Not Stated Clean'!A11:Q11 <> '1850 Not Stated Raw'!A11:Q11))} -> 0
A12: 11 | B12: 2 | C12: 2 | D12: D W | E12: Lawhon | F12: 13 | G12: 1837 | H12: Male | I12: White | M12: Alabama | R12: {=SUMPRODUCT(--('1850 Not Stated Clean'!A12:Q12 <> '1850 Not Stated Raw'!A12:Q12))} -> 1
A13: 12 | B13: 2 | C13: 2 | D13: M A | E13: Lawhon | F13: 9 | G13: 1841 | H13: Female | I13: White | M13: Alabama | R13: {=SUMPRODUCT(--('1850 Not Stated Clean'!A13:Q13 <> '1850 Not Stated Raw'!A13:Q13))} -> 1
A14: 13 | B14: 2 | C14: 2 | D14: John W | E14: Lawhon | F14: 5 | G14: 1845 | H14: Male | I14: White | M14: Alabama | R14: {=SUMPRODUCT(--('1850 Not Stated Clean'!A14:Q14 <> '1850 Not Stated Raw'!A14:Q14))} -> 0
A15: 14 | B15: 2 | C15: 2 | D15: R L | E15: Lawhon | F15: 2 | G15: 1848 | H15: Female | I15: White | M15: Alabama | R15: {=SUMPRODUCT(--('1850 Not Stated Clean'!A15:Q15 <> '1850 Not Stated Raw'!A15:Q15))} -> 0
A16: 15 | B16: 3 | C16: 3 | D16: James W | E16: Moore | F16: 55 | G16: 1795 | H16: Male | I16: White | J16: Farmer | K16: Agriculture | L16: 4400 | M16: Georgia | R16: {=SUMPRODUCT(--('1850 Not Stated Clean'!A16:Q16 <> '1850 Not Stated Raw'!A16:Q16))} -> 0
A17: 16 | B17: 3 | C17: 3 | D17: M | E17: Moore | F17: 40 | G17: 1810 | H17: Female | I17: White | M17: Tennessee | R17: {=SUMPRODUCT(--('1850 Not Stated Clean'!A17:Q17 <> '1850 Not Stated Raw'!A17:Q17))} -> 0
A18: 17 | B18: 3 | C18: 3 | D18: H | E18: Moore | F18: 22 | G18: 1828 | H18: Male | I18: White | J18: Farmhand | K18: Agriculture | M18: Arkansas | R18: {=SUMPRODUCT(--('1850 Not Stated Clean'!A18:Q18 <> '1850 Not Stated Raw'!A18:Q18))} -> 0
A19: 18 | B19: 3 | C19: 3 | D19: J A | E19: Moore | F19: 20 | G19: 1830 | H19: Male | I19: White | J19: Farmhand | K19: Agriculture | M19: Arkansas | R19: {=SUMPRODUCT(--('1850 Not Stated Clean'!A19:Q19 <> '1850 Not Stated Raw'!A19:Q19))} -> 1
A20: 19 | B20: 3 | C20: 3 | D20: D E | E20: Moore | F20: 17 | G20: 1833 | H20: Male | I20: White | J20: Farmhand | K20: Agriculture | M20: Texas | R20: {=SUMPRODUCT(--('1850 Not Stated Clean'!A20:Q20 <> '1850 Not Stated Raw'!A20:Q20))} -> 0
A21: 20 | B21: 3 | C21: 3 | D21: R C | E21: Moore | F21: 16 | G21: 1834 | H21: Male | I21: White | J21: Farmhand | K21: Agriculture | M21: Texas | R21: {=SUMPRODUCT(--('1850 Not Stated Clean'!A21:Q21 <> '1850 Not Stated Raw'!A21:Q21))} -> 1
A22: 21 | B22: 3 | C22: 3 | D22: E | E22: Moore | F22: 14 | G22: 1836 | H22: Female | I22: White | M22: Texas | O22: Yes | R22: {=SUMPRODUCT(--('1850 Not Stated Clean'!A22:Q22 <> '1850 Not Stated Raw'!A22:Q22))} -> 0
A23: 22 | B23: 3 | C23: 3 | D23: B | E23: Moore | F23: 10 | G23: 1840 | H23: Male | I23: White | M23: Texas | R23: {=SUMPRODUCT(--('1850 Not Stated Clean'!A23:Q23 <> '1850 Not Stated Raw'!A23:Q23))} -> 0
A24: 23 | B24: 3 | C24: 3 | D24: G | E24: Moore | F24: 8 | G24: 1842 | H24: Male | I24: White | M24: Texas | R24: {=SUMPRODUCT(--('1850 Not Stated Clean'!A24:Q24 <> '1850 Not Stated Raw'!A24:Q24))} -> 0
A25: 24 | B25: 3 | C25: 3 | D25: N J | E25: Moore | F25: 7 | G25: 1843 | H25: Female | I25: White | M25: Texas | O25: Yes | R25: {=SUMPRODUCT(--('1850 Not Stated Clean'!A25:Q25 <> '1850 Not Stated Raw'!A25:Q25))} -> 1
A26: 25 | B26: 3 | C26: 3 | D26: A E | E26: Moore | F26: 5 | G26: 1845 | H26: Female | I26: White | M26: Texas | R26: {=SUMPRODUCT(--('1850 Not Stated Clean'!A26:Q26 <> '1850 Not Stated Raw'!A26:Q26))} -> 0
A27: 26 | B27: 3 | C27: 3 | D27: M E | E27: Moore | F27: 4 | G27: 1846 | H27: Female | I27: White | M27: Texas | R27: {=SUMPRODUCT(--('1850 Not Stated Clean'!A27:Q27 <> '1850 Not Stated Raw'!A27:Q27))} -> 1
A28: 27 | B28: 4 | C28: 4 | D28: Joseph | E28: Priest | F28: 32 | G28: 1818 | H28: Male | I28: White | J28: Farmer | K28: Agriculture | M28: Alabama | R28: {=SUMPRODUCT(--('1850 Not Stated Clean'!A28:Q28 <> '1850 Not Stated Raw'!A28:Q28))} -> 0
A29: 28 | B29: 4 | C29: 4 | D29: E | E29: Priest | F29: 28 | G29: 1822 | H29: Female | I29: White | M29: Alabama | R29: {=SUMPRODUCT(--('1850 Not Stated Clean'!A29:Q29 <> '1850 Not Stated Raw'!A29:Q29))} -> 0
A30: 29 | B30: 4 | C30: 4 | D30: George W | E30: Priest | F30: 10 | G30: 1840 | H30: Male | I30: White | M30: Mississippi | O30: Yes | R30: {=SUMPRODUCT(--('1850 Not Stated Clean'!A30:Q30 <> '1850 Not Stated Raw'!A30:Q30))} -> 0
A31: 30 | B31: 4 | C31: 4 | D31: William R | E31: Priest | F31: 8 | G31: 1842 | H31: Male | I31: White | M31: Mississippi | R31: {=SUMPRODUCT(--('1850 Not Stated Clean'!A31:Q31 <> '1850 Not Stated Raw'!A31:Q31))} -> 0
A32: 31 | B32: 4 | C32: 4 | D32: M C | E32: Priest | F32: 6 | G32: 1844 | H32: Female | I32: White | M32: Mississippi | R32: {=SUMPRODUCT(--('1850 Not Stated Clean'!A32:Q32 <> '1850 Not Stated Raw'!A32:Q32))} -> 0
A33: 32 | B33: 4 | C33: 4 | D33: L B | E33: Priest | F33: 4 | G33: 1846 | H33: Male | I33: White | M33: Mississippi | R33: {=SUMPRODUCT(--('1850 Not Stated Clean'!A33:Q33 <> '1850 Not Stated Raw'!A33:Q33))} -> 0
A34: 33 | B34: 4 | C34: 4 | D34: N J | E34: Priest | F34: 2 | G34: 1848 | H34: Female | I34: White | M34: Tennessee | R34: {=SUMPRODUCT(--('1850 Not Stated Clean'!A34:Q34 <> '1850 Not Stated Raw'!A34:Q34))} -> 1
A35: 34 | B35: 5 | C35: 5 | D35: James E | E35: Brady | F35: 40 | G35: 1810 | H35: Male | I35: White | J35: Stone Mason | K35: Construction | M35: New York | R35: {=SUMPRODUCT(--('1850 Not Stated Clean'!A35:Q35 <> '1850 Not Stated Raw'!A35:Q35))} -> 0
A36: 35 | B36: 5 | C36: 5 | D36: M A | E36: Brady | F36: 18 | G36: 1832 | H36: Female | I36: White | M36: Georgia | R36: {=SUMPRODUCT(--('1850 Not Stated Clean'!A36:Q36 <> '1850 Not Stated Raw'!A36:Q36))} -> 1
A37: 36 | B37: 5 | C37: 5 | D37: A L | E37: Brady | F37: 2 | G37: 1848 | H37: Female | I37: White | M37: Texas | R37: {=SUMPRODUCT(--('1850 Not Stated Clean'!A37:Q37 <> '1850 Not Stated Raw'!A37:Q37))} -> 0
A38: 37 | B38: 6 | C38: 6 | D38: Thomas | E38: Mays | F38: 47 | G38: 1803 | H38: Male | I38: White | J38: Farmer | K38: Agriculture | L38: 5000 | M38: Virginia | R38: {=SUMPRODUCT(--('1850 Not Stated Clean'!A38:Q38 <> '1850 Not Stated Raw'!A38:Q38))} -> 0
A39: 38 | B39: 6 | C39: 6 | D39: A | E39: Mays | F39: 32 | G39: 1818 | H39: Female | I39: White | M39: Kent | R39: {=SUMPRODUCT(--('1850 Not Stated Clean'!A39:Q39 <> '1850 Not Stated Raw'!A39:Q39))} -> 1
A40: 39 | B40: 6 | C40: 6 | D40: E F | E40: Mays | F40: 12 | G40: 1838 | H40: Female | I40: White | M40: Texas | O40: Yes | R40: {=SUMPRODUCT(--('1850 Not Stated Clean'!A40:Q40 <> '1850 Not Stated Raw'!A40:Q40))} -> 0
A41: 40 | B41: 6 | C41: 6 | D41: M A | E41: Mays | F41: 10 | G41: 1840 | H41: Female | I41: White | M41: Texas | O41: Yes | R41: {=SUMPRODUCT(--('1850 Not Stated Clean'!A41:Q41 <> '1850 Not Stated Raw'!A41:Q41))} -> 1
A42: 41 | B42: 6 | C42: 6 | D42: Thomas F | E42: Mays | F42: 7 | G42: 1843 | H42: Male | I42: White | M42: Texas | R42: {=SUMPRODUCT(--('1850 Not Stated Clean'!A42:Q42 <> '1850 Not Stated Raw'!A42:Q42))} -> 0
A43: 42 | B43: 6 | C43: 6 | D43: Octavia | E43: Mays | F43: 5 | G43: 1845 | H43: Female | I43: White | M43: Texas | R43: {=SUMPRODUCT(--('1850 Not Stated Clean'!A43:Q43 <> '1850 Not Stated Raw'!A43:Q43))} -> 0
A44: 1 | B44: 6 | C44: 6 | D44: Samuel J | E44: Mays | F44: 2 | G44: 1848 | H44: Male | I44: White | M44: Texas | R44: {=SUMPRODUCT(--('1850 Not Stated Clean'!A44:Q44 <> '1850 Not Stated Raw'!A44:Q44))} -> 0
A45: 2 | B45: 7 | C45: 7 | D45: Joel | E45: Cherry | F45: 51 | G45: 1799 | H45: Male | I45: White | J45: Farmer | K45: Agriculture | M45: Tennessee | R45: {=SUMPRODUCT(--('1850 Not Stated Clean'!A45:Q45 <> '1850 Not Stated Raw'!A45:Q45))} -> 0
A46: 3 | B46: 7 | C46: 7 | D46: P | E46: Cherry | F46: 48 | G46: 1802 | H46: Female | I46: White | M46: South Carolina | R46: {=SUMPRODUCT(--('1850 Not Stated Clean'!A46:Q46 <> '1850 Not Stated Raw'!A46:Q46))} -> 0
A47: 4 | B47: 7 | C47: 7 | D47: James | E47: Cherry | F47: 19 | G47: 1831 | H47: Male | I47: White | J47: Farm Hand | K47: Agriculture | M47: Tennessee | P47: Yes | R47: {=SUMPRODUCT(--('1850 Not Stated Clean'!A47:Q47 <> '1850 Not Stated Raw'!A47:Q47))} -> 0
A48: 5 | B48: 7 | C48: 7 | D48: M L | E48: Cherry | F48: 21 | G48: 1829 | H48: Female | I48: White | M48: Tennessee | P48: Yes | R48: {=SUMPRODUCT(--('1850 Not Stated Clean'!A48:Q48 <> '1850 Not Stated Raw'!A48:Q48))} -> 1
A49: 6 | B49: 7 | C49: 7 | D49: N L | E49: Cherry | F49: 17 | G49: 1833 | H49: Female | I49: White | M49: Tennessee | R49: {=SUMPRODUCT(--('1850 Not Stated Clean'!A49:Q49 <> '1850 Not Stated Raw'!A49:Q49))} -> 0
A50: 7 | B50: 7 | C50: 7 | D50: N | E50: Cherry | F50: 14 | G50: 1836 | H50: Male | I50: White | M50: Tennessee | R50: {=SUMPRODUCT(--('1850 Not Stated Clean'!A50:Q50 <> '1850 Not Stated Raw'!A50:Q50))} -> 0
A51: 8 | B51: 7 | C51: 7 | D51: J | E51: Cherry | F51: 12 | G51: 1838 | H51: Male | I51: White | M51: Tennessee | R51: {=SUMPRODUCT(--('1850 Not Stated Clean'!A51:Q51 <> '1850 Not Stated Raw'!A51:Q51))} -> 0
A52: 9 | B52: 7 | C52: 7 | D52: R | E52: Cherry | F52: 10 | G52: 1840 | H52: Male | I52: White | M52: Tennessee | R52: {=SUMPRODUCT(--('1850 Not Stated Clean'!A52:Q52 <> '1850 Not Stated Raw'!A52:Q52))} -> 0
A53: 10 | B53: 8 | C53: 8 | D53: John | E53: Fancet | F53: 34 | G53: 1816 | H53: Male | I53: White | J53: Farmer | K53: Agriculture | L53: 2150 | M53: England | R53: {=SUMPRODUCT(--('1850 Not Stated Clean'!A53:Q53 <> '1850 Not Stated Raw'!A53:Q53))} -> 1
A54: 11 | B54: 8 | C54: 8 | D54: M W T | E54: Fancet | F54: 23 | G54: 1827 | H54: Female | I54: White | M54: Alabama | R54: {=SUMPRODUCT(--('1850 Not Stated Clean'!A54:Q54 <> '1850 Not Stated Raw'!A54:Q54))} -> 1
A55: 12 | B55: 8 | C55: 8 | D55: J P | E55: Fancet | F55: 3 | G55: 1847 | H55: Female | I55: White | M55: Texas | R55: {=SUMPRODUCT(--('1850 Not Stated Clean'!A55:Q55 <> '1850 Not Stated Raw'!A55:Q55))} -> 2
A56: 13 | B56: 8 | C56: 8 | D56: William | E56: Fancet | F56: 28 | G56: 1822 | H56: Male | I56: White | J56: Cooper | K56: Miscellaneous Wood Products | M56: Ohio | R56: {=SUMPRODUCT(--('1850 Not Stated Clean'!A56:Q56 <> '1850 Not Stated Raw'!A56:Q56))} -> 1
A57: 14 | B57: 9 | C57: 9 | D57: William A | E57: Hemphill | F57: 32 | G57: 1818 | H57: Male | I57: White | J57: Farmer | K57: Agriculture | L57: 2000 | M57: Georgia | R57: {=SUMPRODUCT(--('1850 Not Stated Clean'!A57:Q57 <> '1850 Not Stated Raw'!A57:Q57))} -> 0
A58: 15 | B58: 9 | C58: 9 | D58: M J | E58: Hemphill | F58: 16 | G58: 1834 | H58: Female | I58: White | M58: Alabama | R58: {=SUMPRODUCT(--('1850 Not Stated Clean'!A58:Q58 <> '1850 Not Stated Raw'!A58:Q58))} -> 0
A59: 16 | B59: 10 | C59: 10 | D59: James | E59: Nickolson | F59: 34 | G59: 1816 | H59: Male | I59: White | J59: Merchant | K59: Not Specified Retail Trade | L59: 3100 | M59: England | R59: {=SUMPRODUCT(--('1850 Not Stated Clean'!A59:Q59 <> '1850 Not Stated Raw'!A59:Q59))} -> 0
A60: 17 | B60: 10 | C60: 10 | D60: R H | E60: Nickolson | F60: 30 | G60: 1820 | H60: Female | I60: White | M60: Tennessee | R60: {=SUMPRODUCT(--('1850 Not Stated Clean'!A60:Q60 <> '1850 Not Stated Raw'!A60:Q60))} -> 0
A61: 18 | B61: 10 | C61: 10 | D61: William | E61: Nickolson | F61: 13 | G61: 1837 | H61: Male | I61: White | M61: New York | O61: Yes | R61: {=SUMPRODUCT(--('1850 Not Stated Clean'!A61:Q61 <> '1850 Not Stated Raw'!A61:Q61))} -> 0
A62: 19 | B62: 10 | C62: 10 | D62: Mary A | E62: Nickolson | F62: 11 | G62: 1839 | H62: Female | I62: White | M62: Texas | O62: Yes | R62: {=SUMPRODUCT(--('1850 Not Stated Clean'!A62:Q62 <> '1850 Not Stated Raw'!A62:Q62))} -> 0
A63: 20 | B63: 10 | C63: 10 | D63: H | E63: Nickolson | F63: 9 | G63: 1841 | H63: Male | I63: White | M63: Texas | R63: {=SUMPRODUCT(--('1850 Not Stated Clean'!A63:Q63 <> '1850 Not Stated Raw'!A63:Q63))} -> 1
A64: 21 | B64: 10 | C64: 10 | D64: R | E64: Nickolson | F64: 7 | G64: 1843 | H64: Female | I64: White | M64: Texas | R64: {=SUMPRODUCT(--('1850 Not Stated Clean'!A64:Q64 <> '1850 Not Stated Raw'!A64:Q64))} -> 0
A65: 22 | B65: 10 | C65: 10 | D65: Samuel | E65: Nickolson | F65: 1 | G65: 1849 | H65: Male | I65: White | M65: Texas | R65: {=SUMPRODUCT(--('1850 Not Stated Clean'!A65:Q65 <> '1850 Not Stated Raw'!A65:Q65))} -> 0
A66: 23 | B66: 10 | C66: 10 | D66: Charles | E66: Ploger | F66: 26 | G66: 1824 | H66: Male | I66: White | J66: Md | K66: Medical and Other Health Services, Except Hospitals | M66: Germany | R66: {=SUMPRODUCT(--('1850 Not Stated Clean'!A66:Q66 <> '1850 Not Stated Raw'!A66:Q66))} -> 1
A67: 24 | B67: 10 | C67: 10 | D67: M J | E67: Smith | F67: 32 | G67: 1818 | H67: Male | I67: White | J67: Clerk | K67: Not Specified Retail Trade | M67: North Carolina | R67: {=SUMPRODUCT(--('1850 Not Stated Clean'!A67:Q67 <> '1850 Not Stated Raw'!A67:Q67))} -> 0
A68: 25 | B68: 10 | C68: 10 | D68: Philip | E68: Schnyder | F68: 14 | G68: 1836 | H68: Male | I68: White | M68: Germany | R68: {=SUMPRODUCT(--('1850 Not Stated Clean'!A68:Q68 <> '1850 Not Stated Raw'!A68:Q68))} -> 0
A69: 26 | B69: 11 | C69: 11 | D69: Phil | E69: Claiborne | F69: 33 | G69: 1817 | H69: Male | I69: White | J69: Lawyer | K69: Legal Services | L69: 3600 | M69: Virginia | R69: {=SUMPRODUCT(--('1850 Not Stated Clean'!A69:Q69 <> '1850 Not Stated Raw'!A69:Q69))} -> 0
A70: 27 | B70: 11 | C70: 11 | D70: Mary C | E70: Claiborne | F70: 24 | G70: 1826 | H70: Female | I70: White | M70: Missouri | R70: {=SUMPRODUCT(--('1850 Not Stated Clean'!A70:Q70 <> '1850 Not Stated Raw'!A70:Q70))} -> 0
A71: 28 | B71: 11 | C71: 11 | D71: John M | E71: Claiborne | F71: 11 | G71: 1839 | H71: Male | I71: White | M71: Tennessee | O71: Yes | R71: {=SUMPRODUCT(--('1850 Not Stated Clean'!A71:Q71 <> '1850 Not Stated Raw'!A71:Q71))} -> 0
A72: 29 | B72: 11 | C72: 11 | D72: Martha A | E72: Claiborne | F72: 9 | G72: 1841 | H72: Female | I72: White | M72: Tennessee | O72: Yes | R72: {=SUMPRODUCT(--('1850 Not Stated Clean'!A72:Q72 <> '1850 Not Stated Raw'!A72:Q72))} -> 0
A73: 30 | B73: 11 | C73: 11 | D73: Austin | E73: Claiborne | F73: 6 | G73: 1844 | H73: Male | I73: White | M73: Tennessee | R73: {=SUMPRODUCT(--('1850 Not Stated Clean'!A73:Q73 <> '1850 Not Stated Raw'!A73:Q73))} -> 0
A74: 31 | B74: 11 | C74: 11 | D74: Myriam J | E74: Claiborne | F74: 1 | G74: 1849 | H74: Female | I74: White | M74: Texas | R74: {=SUMPRODUCT(--('1850 Not Stated Clean'!A74:Q74 <> '1850 Not Stated Raw'!A74:Q74))} -> 0
A75: 32 | B75: 12 | C75: 12 | D75: William R | E75: Redding | F75: 42 | G75: 1808 | H75: Male | I75: White | L75: 4000 | M75: Tennessee | R75: {=SUMPRODUCT(--('1850 Not Stated Clean'!A75:Q75 <> '1850 Not Stated Raw'!A75:Q75))} -> 0
A76: 33 | B76: 12 | C76: 12 | D76: J M | E76: Redding | F76: 27 | G76: 1823 | H76: Female | I76: White | M76: Tennessee | R76: {=SUMPRODUCT(--('1850 Not Stated Clean'!A76:Q76 <> '1850 Not Stated Raw'!A76:Q76))} -> 0
A77: 34 | B77: 12 | C77: 12 | D77: J W | E77: Redding | F77: 4 | G77: 1846 | H77: Male | I77: White | M77: Texas | R77: {=SUMPRODUCT(--('1850 Not Stated Clean'!A77:Q77 <> '1850 Not Stated Raw'!A77:Q77))} -> 0
A78: 35 | B78: 12 | C78: 12 | D78: William R | E78: Redding | F78: 2 | G78: 1848 | H78: Male | I78: White | M78: Texas | R78: {=SUMPRODUCT(--('1850 Not Stated Clean'!A78:Q78 <> '1850 Not Stated Raw'!A78:Q78))} -> 1
A79: 36 | B79: 12 | C79: 12 | D79: T J | E79: Redding | F79: 2 | G79: 1848 | H79: Female | I79: White | M79: Texas | R79: {=SUMPRODUCT(--('1850 Not Stated Clean'!A79:Q79 <> '1850 Not Stated Raw'!A79:Q79))} -> 0
A80: 37 | B80: 12 | C80: 12 | D80: John | E80: Mitchell | F80: 40 | G80: 1810 | H80: Female | I80: White | J80: None | K80: Non-Industrial Response | M80: Virginia | R80: {=SUMPRODUCT(--('1850 Not Stated Clean'!A80:Q80 <> '1850 Not Stated Raw'!A80:Q80))} -> 1
A81: 38 | B81: 13 | C81: 13 | D81: Chauncey | E81: Johnson | F81: 52 | G81: 1798 | H81: Male | I81: White | J81: Merchant | K81: Not Specified Retail Trade | L81: 22000 | M81: Vermont | R81: {=SUMPRODUCT(--('1850 Not Stated Clean'!A81:Q81 <> '1850 Not Stated Raw'!A81:Q81))} -> 0
A82: 39 | B82: 13 | C82: 13 | D82: E | E82: Johnson | F82: 52 | G82: 1798 | H82: Female | I82: White | M82: Massachusetts | R82: {=SUMPRODUCT(--('1850 Not Stated Clean'!A82:Q82 <> '1850 Not Stated Raw'!A82:Q82))} -> 0
A83: 40 | B83: 13 | C83: 13 | D83: M | E83: Johnson | F83: 21 | G83: 1829 | H83: Female | I83: White | M83: New York | R83: {=SUMPRODUCT(--('1850 Not Stated Clean'!A83:Q83 <> '1850 Not Stated Raw'!A83:Q83))} -> 0
A84: 41 | B84: 13 | C84: 13 | D84: E | E84: Johnson | F84: 16 | G84: 1834 | H84: Female | I84: White | M84: New York | O84: Yes | R84: {=SUMPRODUCT(--('1850 Not Stated Clean'!A84:Q84 <> '1850 Not Stated Raw'!A84:Q84))} -> 0
A85: 42 | B85: 13 | C85: 13 | D85: C | E85: Johnson | F85: 14 | G85: 1836 | H85: Female | I85: White | R85: {=SUMPRODUCT(--('1850 Not Stated Clean'!A85:Q85 <> '1850 Not Stated Raw'!A85:Q85))} -> 1
A86: 1 | B86: 13 | C86: 14 | D86: Henry S | E86: Phillips | F86: 40 | G86: 1810 | H86: Male | I86: White | J86: Carpenter | K86: Construction | L86: 2880 | M86: Virginia | R86: {=SUMPRODUCT(--('1850 Not Stated Clean'!A86:Q86 <> '1850 Not Stated Raw'!A86:Q86))} -> 0
A87: 2 | B87: 13 | C87: 14 | D87: E | E87: Phillips | F87: 23 | G87: 1827 | H87: Female | I87: White | M87: New York | R87: {=SUMPRODUCT(--('1850 Not Stated Clean'!A87:Q87 <> '1850 Not Stated Raw'!A87:Q87))} -> 0
A88: 3 | B88: 13 | C88: 14 | D88: Julia | E88: Phillips | F88: 6 | G88: 1844 | H88: Female | I88: White | M88: Texas | O88: Yes | R88: {=SUMPRODUCT(--('1850 Not Stated Clean'!A88:Q88 <> '1850 Not Stated Raw'!A88:Q88))} -> 0
A89: 4 | B89: 13 | C89: 14 | D89: Leman | E89: Phillips | F89: 3 | G89: 1847 | H89: Male | I89: White | M89: Texas | R89: {=SUMPRODUCT(--('1850 Not Stated Clean'!A89:Q89 <> '1850 Not Stated Raw'!A89:Q89))} -> 0
A90: 5 | B90: 13 | C90: 14 | D90: J | E90: Leffinger | F90: 34 | G90: 1816 | H90: Male | I90: White | J90: Carpenter | K90: Construction | M90: New York | R90: {=SUMPRODUCT(--('1850 Not Stated Clean'!A90:Q90 <> '1850 Not Stated Raw'!A90:Q90))} -> 0
A91: 6 | B91: 13 | C91: 14 | D91: William | E91: Richardson | F91: 20 | G91: 1830 | H91: Male | I91: White | J91: Carpenter | K91: Construction | M91: New York | R91: {=SUMPRODUCT(--('1850 Not Stated Clean'!A91:Q91 <> '1850 Not Stated Raw'!A91:Q91))} -> 0
A92: 7 | B92: 14 | C92: 15 | D92: John S | E92: Johnson | F92: 25 | G92: 1825 | H92: Male | I92: White | J92: Merchant | K92: Not Specified Retail Trade | L92: 1000 | M92: New York | R92: {=SUMPRODUCT(--('1850 Not Stated Clean'!A92:Q92 <> '1850 Not Stated Raw'!A92:Q92))} -> 0
A93: 8 | B93: 14 | C93: 15 | D93: P | E93: Johnson | F93: 19 | G93: 1831 | H93: Female | I93: White | M93: South Carolina | R93: {=SUMPRODUCT(--('1850 Not Stated Clean'!A93:Q93 <> '1850 Not Stated Raw'!A93:Q93))} -> 0
A94: 9 | B94: 14 | C94: 15 | D94: A | E94: Johnson | F94: 0 | G94: 1850 | H94: Male | I94: White | M94: Texas | R94: {=SUMPRODUCT(--('1850 Not Stated Clean'!A94:Q94 <> '1850 Not Stated Raw'!A94:Q94))} -> 1
A95: 10 | B95: 15 | C95: 16 | D95: Westty | E95: Dykes | F95: 38 | G95: 1812 | H95: Male | I95: White | J95: Farmer | K95: Agriculture | L95: 100 | M95: Louisiana | R95: {=SUMPRODUCT(--('1850 Not Stated Clean'!A95:Q95 <> '1850 Not Stated Raw'!A95:Q95))} -> 0
A96: 11 | B96: 15 | C96: 16 | D96: H | E96: Dykes | F96: 37 | G96: 1813 | H96: Female | I96: White | M96: Louisiana | R96: {=SUMPRODUCT(--('1850 Not Stated Clean'!A96:Q96 <> '1850 Not Stated Raw'!A96:Q96))} -> 0
A97: 12 | B97: 15 | C97: 16 | D97: M | E97: Dykes | F97: 13 | G97: 1837 | H97: Female | I97: White | M97: Texas | O97: Yes | R97: {=SUMPRODUCT(--('1850 Not Stated Clean'!A97:Q97 <> '1850 Not Stated Raw'!A97:Q97))} -> 0
A98: 13 | B98: 15 | C98: 16 | D98: Frances | E98: Dykes | F98: 9 | G98: 1841 | H98: Female | I98: White | M98: Texas | O98: Yes | R98: {=SUMPRODUCT(--('1850 Not Stated Clean'!A98:Q98 <> '1850 Not Stated Raw'!A98:Q98))} -> 0
A99: 14 | B99: 15 | C99: 16 | D99: A | E99: Dykes | F99: 7 | G99: 1843 | H99: Female | I99: White | M99: Texas | O99: Yes | R99: {=SUMPRODUCT(--('1850 Not Stated Clean'!A99:Q99 <> '1850 Not Stated Raw'!A99:Q99))} -> 0
A100: 15 | B100: 15 | C100: 16 | D100: E | E100: Dykes | F100: 5 | G100: 1845 | H100: Female | I100: White | M100: Texas | R100: {=SUMPRODUCT(--('1850 Not Stated Clean'!A100:Q100 <> '1850 Not Stated Raw'!A100:Q100))} -> 0
...

Sheet 1860 Bastrop Clean
A1: Dwelling Number | B1: Family Number | C1: Given Name | D1: Surname | E1: Age | F1: Birth Year | G1: Gender | H1: Race | I1: Occupation | J1: Real Estate Value | K1: Personal Estate Value | L1: Birth Place | M1: Married Within Year | N1: Attended School | O1: Cannot Read, Write | P1: Disability Condition
A2: 1 | B2: 1 | C2: James | D2: Nicholson | E2: 45 | F2: 1815 | G2: Male | H2: White | I2: Hotel Keeper | J2: 4000 | K2: 2000 | L2: England
A3: 1 | B3: 1 | C3: Rebecca M H | D3: Nicholson | E3: 46 | F3: 1814 | G3: Female | H3: White | J3: 1000 | L3: Tennessee
A4: 1 | B4: 1 | C4: Samuel G | D4: Nicholson | E4: 11 | F4: 1849 | G4: Male | H4: White | L4: Texas | N4: Y
A5: 1 | B5: 1 | C5: James N | D5: Nicholson | E5: 7 | F5: 1853 | G5: Male | H5: White | L5: Texas | N5: Y
A6: 1 | B6: 1 | C6: Rubell N | D6: Nicholson | E6: 5 | F6: 1855 | G6: Female | H6: White | L6: Texas
A7: 1 | B7: 1 | C7: Samuel | D7: Halker | E7: 29 | F7: 1831 | G7: Male | H7: White | I7: Drugest | K7: 2000 | L7: Georgia
A8: 1 | B8: 1 | C8: John M | D8: Webster | E8: 25 | F8: 1835 | G8: Male | H8: White | I8: Clerk | K8: 400 | L8: North Carolina
A9: 1 | B9: 1 | C9: S H | D9: Chercher | E9: 29 | F9: 1831 | G9: Male | H9: White | I9: Carpenter | L9: North Carolina
A10: 1 | B10: 1 | C10: Cornelius | D10: Philips | E10: 54 | F10: 1806 | G10: Male | H10: White | I10: Carpenter | L10: Virginia
A11: 1 | B11: 1 | C11: James B | D11: Cowan | E11: 34 | F11: 1826 | G11: Male | H11: White | I11: Brickmason | K11: 100 | L11: Virginia
A12: 1 | B12: 1 | C12: S C | D12: Wilkins | E12: 26 | F12: 1834 | G12: Male | H12: White | I12: Clerk | J12: 80 | K12: 1530 | L12: Kentucky
A13: 1 | B13: 1 | C13: John | D13: Smith | E13: 38 | F13: 1822 | G13: Male | H13: White | I13: Laborer | L13: Ireland
A14: 1 | B14: 1 | C14: John T | D14: Stanley | E14: 33 | F14: 1827 | G14: Male | H14: White | I14: Proff Searger | K14: 500 | L14: Maine
A15: 1 | B15: 1 | C15: J | D15: Rosenfield | E15: 22 | F15: 1838 | G15: Male | H15: White | I15: Clerk | K15: 9000 | L15: Texas
A16: 2 | B16: 1 | C16: H | D16: McLester | E16: 33 | F16: 1827 | G16: Male | H16: White | I16: Sawyer | K16: 400 | L16: Georgia
A17: 2 | B17: 1 | C17: S | D17: Elsworth | E17: 47 | F17: 1813 | G17: Male | H17: White | I17: Stage Driver | L17: New York
A18: 2 | B18: 1 | C18: R F | D18: Cambell | E18: 23 | F18: 1837 | G18: Male | H18: White | I18: Farmer | J18: 400 | K18: 2000 | L18: Tennessee
A19: 2 | B19: 1 | C19: H | D19: Mc Fowlard | E19: 30 | F19: 1830 | G19: Male | H19: White | I19: Stage Driver | L19: Pennsylvania
A20: 2 | B20: 1 | C20: C A | D20: Banes | E20: 32 | F20: 1828 | G20: Male | H20: White | I20: Stage Driver | L20: Tennessee
A21: 2 | B21: 1 | C21: A | D21: Hews | E21: 24 | F21: 1836 | G21: Male | H21: White | I21: Student M D | K21: 400 | L21: Ohio
A22: 3 | B22: 1 | C22: K | D22: Keslus | E22: 23 | F22: 1837 | G22: Male | H22: White | I22: Taylor | K22: 700 | L22: Saxony
A23: 3 | B23: 1 | C23: Elizabeth | D23: Barden | E23: 24 | F23: 1836 | G23: Female | H23: White | I23: Servant | L23: Texas | O23: Y
A24: 3 | B24: 1 | C24: Emma | D24: Barden | E24: 4 | F24: 1856 | G24: Female | H24: White | L24: Texas
A25: 4 | B25: 2 | C25: Charles | D25: Gnote | E25: 40 | F25: 1820 | G25: Male | H25: White | I25: Minister | K25: 4000 | L25: Germany
A26: 4 | B26: 2 | C26: Mary | D26: Gnote | E26: 40 | F26: 1820 | G26: Female | H26: White | I26: Laborer | L26: Germany
A27: 4 | B27: 2 | C27: Frits | D27: Gnote | E27: 20 | F27: 1840 | G27: Male | H27: White | L27: Germany
A28: 4 | B28: 2 | C28: Nana | D28: Gnote | E28: 5 | F28: 1855 | G28: Female | H28: White | L28: Texas
A29: 4 | B29: 2 | C29: Henry | D29: Gnote | G29: Male | H29: White | L29: Texas
A30: 5 | B30: 3 | C30: J M | D30: Hill | E30: 52 | F30: 1808 | G30: Female | H30: White | I30: Widow | J30: 500 | K30: 100 | L30: Maryland
A31: 5 | B31: 3 | C31: Thos J | D31: Hill | G31: Male | H31: White | L31: Missouri | N31: Y
A32: 6 | B32: 4 | C32: R T P | D32: Allen | E32: 46 | F32: 1814 | G32: Male | H32: White | I32: Proff Engineer | J32: 7000 | K32: 6000 | L32: Maryland
A33: 6 | B33: 4 | C33: Julia A | D33: Allen | E33: 40 | F33: 1820 | G33: Female | H33: White | L33: Tennessee
A34: 6 | B34: 4 | C34: G Howard A | D34: Allen | G34: Male | H34: White | L34: Kentucky | N34: Y
A35: 7 | B35: 5 | C35: Sam H | D35: Sims | E35: 43 | F35: 1817 | G35: Male | H35: White | I35: Master Miller | J35: 14000 | K35: 14650 | L35: Maryland
A36: 7 | B36: 5 | C36: Tulia J | D36: Sims | E36: 38 | F36: 1822 | G36: Female | H36: White | L36: Tennessee
A37: 7 | B37: 5 | C37: J W T | D37: Sims | E37: 20 | F37: 1840 | G37: Male | H37: White | I37: Clerk | L37: Texas
A38: 7 | B38: 5 | C38: J H | D38: Bruce | E38: 1 | F38: 1859 | G38: Female | H38: White | L38: Texas
A39: 7 | B39: 5 | C39: Nancy E | D39: Sims | G39: Female | H39: White | L39: Texas | N39: Y
A40: 7 | B40: 5 | C40: James O | D40: Sims | E40: 12 | F40: 1848 | G40: Male | H40: White | L40: Texas | N40: Y
A41: 7 | B41: 5 | C41: Ira J | D41: Sims | E41: 10 | F41: 1850 | G41: Female | H41: White | L41: Texas | N41: Y
A42: 7 | B42: 5 | C42: Stasca | D42: Sims | E42: 8 | F42: 1852 | G42: Female | H42: White | L42: Texas | N42: Y
A43: 7 | B43: 5 | C43: Lola W | D43: Sims | E43: 1 | F43: 1859 | G43: Female | H43: White | L43: Texas
A44: 7 | B44: 5 | C44: R D | D44: Allen | E44: 24 | F44: 1836 | G44: Male | H44: White | I44: Proff Math | J44: 500 | K44: 2000 | L44: District of Columbia
A45: 7 | B45: 5 | C45: Launa A | D45: Allen | E45: 18 | F45: 1842 | G45: Female | H45: White | L45: Texas
A46: 7 | B46: 5 | C46: Eola J | D46: Allen | E46: 45728 | F46: 1859 | G46: Female | H46: White | L46: Texas
A47: 8 | B47: 6 | C47: Henny | D47: Cnochron | E47: 51 | F47: 1809 | G47: Male | H47: White | I47: Merchant | J47: 15000 | K47: 8000 | L47: New York
A48: 8 | B48: 6 | C48: Mary | D48: Crochron | E48: 43 | F48: 1817 | G48: Female | H48: White | L48: England
A49: 8 | B49: 6 | C49: William | D49: Nicholson | E49: 20 | F49: 1840 | G49: Male | H49: White | I49: Clerk | L49: New York
A50: 8 | B50: 6 | C50: Mary A | D50: Nicholson | E50: 17 | F50: 1843 | G50: Female | H50: White | L50: Texas
A51: 8 | B51: 6 | C51: Ruth T | D51: Nicholson | E51: 12 | F51: 1848 | G51: Female | H51: White | L51: Texas | N51: Y
A52: 9 | B52: 7 | C52: John S | D52: Johnson | E52: 35 | F52: 1825 | G52: Male | H52: White | I52: Merchant | J52: 8000 | K52: 25000 | L52: New York
A53: 9 | B53: 7 | C53: Permitia | D53: Johnson | E53: 26 | F53: 1834 | G53: Female | H53: White | L53: South Carolina
A54: 9 | B54: 7 | C54: Alonzo | D54: Johnson | E54: 10 | F54: 1850 | G54: Male | H54: White | L54: Texas | N54: Y
A55: 9 | B55: 7 | C55: Benjamin | D55: Johnson | E55: 8 | F55: 1852 | G55: Male | H55: White | L55: Texas | N55: Y
A56: 9 | B56: 7 | C56: Samuel | D56: Johnson | E56: 4 | F56: 1856 | G56: Male | H56: White | L56: Texas
A57: 9 | B57: 7 | C57: Charles | D57: Johnson | E57: 45820 | F57: 1859 | G57: Male | H57: White | L57: Texas
A58: 9 | B58: 7 | C58: G B | D58: Cope | E58: 27 | F58: 1833 | G58: Male | H58: White | I58: Clerk | K58: 700 | L58: Tennessee
A59: 10 | B59: 8 | C59: William A | D59: Smith | E59: 52 | F59: 1808 | G59: Male | H59: White | I59: Teacher | J59: 700 | K59: 5000 | L59: Kentucky
A60: 10 | B60: 8 | C60: A H | D60: Smith | E60: 52 | F60: 1808 | G60: Female | H60: White | L60: Kentucky
A61: 10 | B61: 8 | C61: William C | D61: Smith | F61: 1845 | G61: Male | H61: White | L61: Kentucky | N61: Y
A62: 10 | B62: 8 | C62: L H | D62: Smith | E62: 10 | F62: 1850 | G62: Male | H62: White | L62: Kentucky | N62: Y
A63: 10 | B63: 8 | C63: Anna R | D63: Smith | E63: 8 | F63: 1852 | G63: Female | H63: White | L63: Kentucky | N63: Y
A64: 10 | B64: 8 | C64: James A | D64: Smith | E64: 5 | F64: 1855 | G64: Male | H64: White | L64: Texas | N64: Y
A65: 11 | B65: 9 | C65: A W | D65: Anms | E65: 30 | F65: 1830 | G65: Male | H65: White | I65: Shoemaker | K65: 200 | L65: Georgia
A66: 11 | B66: 9 | C66: N A | D66: Anms | E66: 23 | F66: 1837 | G66: Female | H66: White | L66: Georgia
A67: 12 | B67: 10 | C67: Sacop | D67: Leweris | E67: 36 | F67: 1824 | G67: Male | H67: White | I67: Shoemaker | L67: Pennsylvania | M67: Y
A68: 12 | B68: 10 | C68: Hannah | D68: Lewers | E68: 18 | F68: 1842 | G68: Female | H68: White | L68: Germany | M68: Y
A69: 13 | B69: 10 | C69: Mark | D69: Bernie | E69: 46 | F69: 1814 | G69: Male | H69: White | I69: Sadler | K69: 200 | L69: Portugal
A70: 14 | B70: 11 | C70: R G | D70: Rice | E70: 46 | F70: 1814 | G70: Male | H70: White | I70: Master Sadler | J70: 1000 | K70: 500 | L70: Virginia
A71: 14 | B71: 11 | C71: Martha | D71: Rice | E71: 46 | F71: 1814 | G71: Female | H71: White | L71: Kentucky
A72: 14 | B72: 11 | C72: Sula P | D72: Rice | E72: 16 | F72: 1844 | G72: Female | H72: White | L72: Alabama
A73: 14 | B73: 11 | C73: Robert G | D73: Rice | E73: 13 | F73: 1847 | G73: Male | H73: White | L73: Texas | N73: Y
A74: 14 | B74: 11 | C74: Correlius B | D74: Rice | E74: 11 | F74: 1849 | G74: Female | H74: White | L74: Texas | N74: Y
A75: 14 | B75: 11 | C75: John W | D75: Rice | E75: 8 | F75: 1852 | G75: Male | H75: White | L75: Texas | N75: Y
A76: 14 | B76: 11 | C76: Rebecca | D76: Rice | E76: 6 | F76: 1854 | G76: Female | H76: White | L76: Texas | N76: Y
A77: 14 | B77: 11 | C77: A J | D77: Batts | E77: 29 | F77: 1831 | G77: Male | H77: White | I77: Saddler | K77: 400 | L77: Virginia
A78: 15 | B78: 11 | C78: Charles | D78: Briger | E78: 25 | F78: 1835 | G78: Male | H78: White | I78: Taylor | K78: 200 | L78: Prussia
A79: 16 | B79: 12 | C79: Nelson | D79: Burch | E79: 48 | F79: 1812 | G79: Male | H79: White | I79: Merchant | J79: 15000 | K79: 25000 | L79: New York
A80: 16 | B80: 12 | C80: Elizabeth | D80: Burch | E80: 32 | F80: 1828 | G80: Female | H80: White | L80: New York
A81: 17 | B81: 13 | C81: Stephen C | D81: Nolen | E81: 49 | F81: 1811 | G81: Male | H81: White | I81: Farmer | J81: 500 | K81: 2500 | L81: Tennessee
A82: 17 | B82: 13 | C82: Mary A | D82: Nolen | E82: 41 | F82: 1819 | G82: Female | H82: White | L82: Tennessee
A83: 17 | B83: 13 | C83: Venginia | D83: Nolen | E83: 22 | F83: 1838 | G83: Female | H83: White | L83: Tennessee
A84: 17 | B84: 13 | C84: Mary T | D84: Nolen | E84: 20 | F84: 1840 | G84: Female | H84: White | L84: Tennessee
A85: 17 | B85: 13 | C85: Alexandra | D85: Nolen | E85: 14 | F85: 1846 | G85: Male | H85: White | L85: Mississippi | N85: Y
A86: 17 | B86: 13 | C86: John | D86: Nolen | E86: 12 | F86: 1848 | G86: Male | H86: White | L86: Mississippi | N86: Y
A87: 17 | B87: 13 | C87: Willmath | D87: Nolen | E87: 10 | F87: 1850 | G87: Female | H87: White | L87: Texas | N87: Y
A88: 17 | B88: 13 | C88: Turner | D88: Nolen | E88: 8 | F88: 1852 | G88: Male | H88: White | L88: Texas
A89: 17 | B89: 13 | C89: William | D89: Nolen | E89: 4 | F89: 1856 | G89: Male | H89: White | L89: Texas
A90: 17 | B90: 13 | C90: Anna | D90: Nolen | E90: 1 | F90: 1859 | G90: Female | H90: White | L90: Texas
A91: 17 | B91: 13 | C91: Ada | D91: Nolen | E91: 1 | F91: 1859 | G91: Female | H91: White | L91: Texas
A92: 18 | B92: 14 | C92: G | D92: Friedberger | E92: 20 | F92: 1840 | G92: Male | H92: White | I92: Merchant | J92: 3500 | K92: 12000 | L92: Germany
A93: 19 | B93: 15 | C93: A S | D93: Rose | E93: 34 | F93: 1826 | G93: Male | H93: White | I93: Carriage Maker | J93: 3000 | K93: 1500 | L93: New York
A94: 19 | B94: 15 | C94: Jane | D94: Rose | E94: 41 | F94: 1819 | G94: Female | H94: White | L94: New York
A95: 19 | B95: 15 | C95: Joshua | D95: Rose | E95: 14 | F95: 1846 | G95: Male | H95: White | L95: New Jersey | N95: Y
A96: 19 | B96: 15 | C96: Charles | D96: Rose | E96: 12 | F96: 1848 | G96: Male | H96: White | L96: New York | N96: Y
A97: 19 | B97: 15 | C97: Jane | D97: Rose | E97: 8 | F97: 1852 | G97: Female | H97: White | L97: New York | N97: Y
A98: 19 | B98: 15 | C98: Chester | D98: Rose | E98: 6 | F98: 1854 | G98: Male | H98: White | L98: Alla | N98: Y
A99: 20 | B99: 15 | C99: Jenny | D99: Gordier | G99: Male | H99: White | I99: Carriage Maker | J99: 1500 | L99: Alla
A100: 20 | B100: 15 | C100: Ellen | D100: Gordier | E100: 21 | F100: 1839 | G100: Female | H100: White | L100: New York
...

Sheet 1860 Bastrop Raw
A1: Dwelling Number | B1: Family Number | C1: Given Name | D1: Surname | E1: Age | F1: Birth Year | G1: Gender | H1: Race | I1: Occupation | J1: Real Estate Value | K1: Personal Estate Value | L1: Birth Place | M1: Married Within Year | N1: Attended School | O1: Cannot Read, Write | P1: Disability Condition | Q1: Comp.
A2: 1 | B2: 1 | C2: Tamer | D2: Nicholson | E2: 45 | F2: 1815 | G2: Male | H2: White | I2: Hotel Keeper | J2: 4000 | K2: 2000 | L2: England | Q2: {=SUMPRODUCT(--('1860 Bastrop Clean'!A2:P2 <> '1860 Bastrop Raw'!A2:P2))} -> 1
A3: 1 | B3: 1 | C3: Rebecca M H | D3: Nicholson | E3: 46 | F3: 1814 | G3: Female | H3: White | J3: 1000 | L3: Tennessee | Q3: {=SUMPRODUCT(--('1860 Bastrop Clean'!A3:P3 <> '1860 Bastrop Raw'!A3:P3))} -> 0
A4: 1 | B4: 1 | C4: Samuel G | D4: Nicholson | E4: 11 | F4: 1849 | G4: Male | H4: White | L4: Texas | N4: Y | Q4: {=SUMPRODUCT(--('1860 Bastrop Clean'!A4:P4 <> '1860 Bastrop Raw'!A4:P4))} -> 0
A5: 1 | B5: 1 | C5: James N | D5: Nicholson | E5: 7 | F5: 1853 | G5: Male | H5: White | L5: Texas | N5: Y | Q5: {=SUMPRODUCT(--('1860 Bastrop Clean'!A5:P5 <> '1860 Bastrop Raw'!A5:P5))} -> 0
A6: 1 | B6: 1 | C6: Rubell N | D6: Nicholson | E6: 5 | F6: 1855 | G6: Female | H6: White | L6: Texas | Q6: {=SUMPRODUCT(--('1860 Bastrop Clean'!A6:P6 <> '1860 Bastrop Raw'!A6:P6))} -> 0
A7: 1 | B7: 1 | C7: Samuel | D7: Halker | E7: 29 | F7: 1831 | G7: Male | H7: White | I7: Drugest | K7: 2000 | L7: Georgia | Q7: {=SUMPRODUCT(--('1860 Bastrop Clean'!A7:P7 <> '1860 Bastrop Raw'!A7:P7))} -> 0
A8: 1 | B8: 1 | C8: John M | D8: Webster | E8: 25 | F8: 1835 | G8: Male | H8: White | I8: Clerk | K8: 400 | L8: North Carolina | Q8: {=SUMPRODUCT(--('1860 Bastrop Clean'!A8:P8 <> '1860 Bastrop Raw'!A8:P8))} -> 0
A9: 1 | B9: 1 | C9: S H | D9: Chercher | E9: 29 | F9: 1831 | G9: Male | H9: White | I9: Carpenter | L9: North Carolina | Q9: {=SUMPRODUCT(--('1860 Bastrop Clean'!A9:P9 <> '1860 Bastrop Raw'!A9:P9))} -> 0
A10: 1 | B10: 1 | C10: Cornelius | D10: Philips | E10: 54 | F10: 1806 | G10: Male | H10: White | I10: Carpenter | L10: Virginia | Q10: {=SUMPRODUCT(--('1860 Bastrop Clean'!A10:P10 <> '1860 Bastrop Raw'!A10:P10))} -> 0
A11: 1 | B11: 1 | C11: James B | D11: Cowan | E11: 34 | F11: 1826 | G11: Male | H11: White | I11: Brickmason | K11: 100 | L11: Virginia | Q11: {=SUMPRODUCT(--('1860 Bastrop Clean'!A11:P11 <> '1860 Bastrop Raw'!A11:P11))} -> 0
A12: 1 | B12: 1 | C12: S C | D12: Wilkins | E12: 26 | F12: 1834 | G12: Male | H12: White | I12: Clerk | J12: 80 | K12: 1530 | L12: Kentucky | Q12: {=SUMPRODUCT(--('1860 Bastrop Clean'!A12:P12 <> '1860 Bastrop Raw'!A12:P12))} -> 0
A13: 1 | B13: 1 | C13: John | D13: Smith | E13: 38 | F13: 1822 | G13: Male | H13: White | I13: Laborer | L13: Ireland | Q13: {=SUMPRODUCT(--('1860 Bastrop Clean'!A13:P13 <> '1860 Bastrop Raw'!A13:P13))} -> 0
A14: 1 | B14: 1 | C14: John T | D14: Stanley | E14: 33 | F14: 1827 | G14: Male | H14: White | I14: Proff Searger | K14: 500 | L14: Maine | Q14: {=SUMPRODUCT(--('1860 Bastrop Clean'!A14:P14 <> '1860 Bastrop Raw'!A14:P14))} -> 0
A15: 1 | B15: 1 | C15: J | D15: Rosenfield | E15: 22 | F15: 1838 | G15: Male | H15: White | I15: Clerk | K15: 9000 | L15: Texas | Q15: {=SUMPRODUCT(--('1860 Bastrop Clean'!A15:P15 <> '1860 Bastrop Raw'!A15:P15))} -> 0
A16: 2 | B16: 1 | C16: H | D16: McLester | E16: 33 | F16: 1827 | G16: Male | H16: White | I16: Sawyer | K16: 400 | L16: Georgia | Q16: {=SUMPRODUCT(--('1860 Bastrop Clean'!A16:P16 <> '1860 Bastrop Raw'!A16:P16))} -> 0
A17: 2 | B17: 1 | C17: S | D17: Elsworth | E17: 47 | F17: 1813 | G17: Male | H17: White | I17: Stage Driver | L17: New York | Q17: {=SUMPRODUCT(--('1860 Bastrop Clean'!A17:P17 <> '1860 Bastrop Raw'!A17:P17))} -> 0
A18: 2 | B18: 1 | C18: R F | D18: Cambell | E18: 23 | F18: 1837 | G18: Male | H18: White | I18: Farmer | J18: 400 | K18: 2000 | L18: Tennessee | Q18: {=SUMPRODUCT(--('1860 Bastrop Clean'!A18:P18 <> '1860 Bastrop Raw'!A18:P18))} -> 0
A19: 2 | B19: 1 | C19: H | D19: Mc Fowlard | E19: 30 | F19: 1830 | G19: Male | H19: White | I19: Stage Driver | L19: Pennsylvania | Q19: {=SUMPRODUCT(--('1860 Bastrop Clean'!A19:P19 <> '1860 Bastrop Raw'!A19:P19))} -> 0
A20: 2 | B20: 1 | C20: C A | D20: Banes | E20: 32 | F20: 1828 | G20: Male | H20: White | I20: Stage Driver | L20: Tennessee | Q20: {=SUMPRODUCT(--('1860 Bastrop Clean'!A20:P20 <> '1860 Bastrop Raw'!A20:P20))} -> 0
A21: 2 | B21: 1 | C21: A | D21: Hews | E21: 24 | F21: 1836 | G21: Male | H21: White | I21: Student M D | K21: 400 | L21: Ohio | Q21: {=SUMPRODUCT(--('1860 Bastrop Clean'!A21:P21 <> '1860 Bastrop Raw'!A21:P21))} -> 0
A22: 3 | B22: 1 | C22: K | D22: Keslus | E22: 23 | F22: 1837 | G22: Male | H22: White | I22: Taylor | K22: 700 | L22: Saxony | Q22: {=SUMPRODUCT(--('1860 Bastrop Clean'!A22:P22 <> '1860 Bastrop Raw'!A22:P22))} -> 0
A23: 3 | B23: 1 | C23: Elizabeth | D23: Barden | E23: 24 | F23: 1836 | G23: Female | H23: White | I23: Servant | L23: Texas | O23: Y | Q23: {=SUMPRODUCT(--('1860 Bastrop Clean'!A23:P23 <> '1860 Bastrop Raw'!A23:P23))} -> 0
A24: 3 | B24: 1 | C24: Emma | D24: Barden | E24: 4 | F24: 1856 | G24: Female | H24: White | L24: Texas | Q24: {=SUMPRODUCT(--('1860 Bastrop Clean'!A24:P24 <> '1860 Bastrop Raw'!A24:P24))} -> 0
A25: 4 | B25: 2 | C25: Charles | D25: Gnote | E25: 40 | F25: 1820 | G25: Male | H25: White | I25: Minister | K25: 4000 | L25: Germany | Q25: {=SUMPRODUCT(--('1860 Bastrop Clean'!A25:P25 <> '1860 Bastrop Raw'!A25:P25))} -> 0
A26: 4 | B26: 2 | C26: Mary | D26: Gnote | E26: 40 | F26: 1820 | G26: Female | H26: White | I26: Laborer | L26: Germany | Q26: {=SUMPRODUCT(--('1860 Bastrop Clean'!A26:P26 <> '1860 Bastrop Raw'!A26:P26))} -> 0
A27: 4 | B27: 2 | C27: Frits | D27: Gnote | E27: 20 | F27: 1840 | G27: Male | H27: White | L27: Germany | Q27: {=SUMPRODUCT(--('1860 Bastrop Clean'!A27:P27 <> '1860 Bastrop Raw'!A27:P27))} -> 0
A28: 4 | B28: 2 | C28: Nana | D28: Gnote | E28: 5 | F28: 1855 | G28: Female | H28: White | L28: Texas | Q28: {=SUMPRODUCT(--('1860 Bastrop Clean'!A28:P28 <> '1860 Bastrop Raw'!A28:P28))} -> 0
A29: 4 | B29: 2 | C29: Henry | D29: Gnote | G29: Male | H29: White | L29: Texas | Q29: {=SUMPRODUCT(--('1860 Bastrop Clean'!A29:P29 <> '1860 Bastrop Raw'!A29:P29))} -> 0
A30: 5 | B30: 3 | C30: J M | D30: Hill | E30: 52 | F30: 1808 | G30: Female | H30: White | I30: Widow | J30: 500 | K30: 100 | L30: Maryland | Q30: {=SUMPRODUCT(--('1860 Bastrop Clean'!A30:P30 <> '1860 Bastrop Raw'!A30:P30))} -> 0
A31: 5 | B31: 3 | C31: Thos J | D31: Hill | G31: Male | H31: White | L31: Missouri | N31: Y | Q31: {=SUMPRODUCT(--('1860 Bastrop Clean'!A31:P31 <> '1860 Bastrop Raw'!A31:P31))} -> 0
A32: 6 | B32: 4 | C32: R T P | D32: Allen | E32: 46 | F32: 1814 | G32: Male | H32: White | I32: Proff Engineer | J32: 7000 | K32: 6000 | L32: Maryland | Q32: {=SUMPRODUCT(--('1860 Bastrop Clean'!A32:P32 <> '1860 Bastrop Raw'!A32:P32))} -> 0
A33: 6 | B33: 4 | C33: Julia A | D33: Allen | E33: 40 | F33: 1820 | G33: Female | H33: White | L33: Tennessee | Q33: {=SUMPRODUCT(--('1860 Bastrop Clean'!A33:P33 <> '1860 Bastrop Raw'!A33:P33))} -> 0
A34: 6 | B34: 4 | C34: G Howard A | D34: Allen | G34: Male | H34: White | L34: Kentucky | N34: Y | Q34: {=SUMPRODUCT(--('1860 Bastrop Clean'!A34:P34 <> '1860 Bastrop Raw'!A34:P34))} -> 0
A35: 7 | B35: 5 | C35: Sam H | D35: Sims | E35: 43 | F35: 1817 | G35: Male | H35: White | I35: Master Miller | J35: 14000 | K35: 14650 | L35: Maryland | Q35: {=SUMPRODUCT(--('1860 Bastrop Clean'!A35:P35 <> '1860 Bastrop Raw'!A35:P35))} -> 0
A36: 7 | B36: 5 | C36: Tulia J | D36: Sims | E36: 38 | F36: 1822 | G36: Female | H36: White | L36: Tennessee | Q36: {=SUMPRODUCT(--('1860 Bastrop Clean'!A36:P36 <> '1860 Bastrop Raw'!A36:P36))} -> 0
A37: 7 | B37: 5 | C37: J W T | D37: Sims | E37: 20 | F37: 1840 | G37: Male | H37: White | I37: Clerk | L37: Texas | Q37: {=SUMPRODUCT(--('1860 Bastrop Clean'!A37:P37 <> '1860 Bastrop Raw'!A37:P37))} -> 0
A38: 7 | B38: 5 | C38: J H | D38: Bruce | E38: 1 | F38: 1859 | G38: Female | H38: White | L38: Texas | Q38: {=SUMPRODUCT(--('1860 Bastrop Clean'!A38:P38 <> '1860 Bastrop Raw'!A38:P38))} -> 0
A39: 7 | B39: 5 | C39: Nancy E | D39: Sims | G39: Female | H39: White | L39: Texas | N39: Y | Q39: {=SUMPRODUCT(--('1860 Bastrop Clean'!A39:P39 <> '1860 Bastrop Raw'!A39:P39))} -> 0
A40: 7 | B40: 5 | C40: James O | D40: Sims | E40: 12 | F40: 1848 | G40: Male | H40: White | L40: Texas | N40: Y | Q40: {=SUMPRODUCT(--('1860 Bastrop Clean'!A40:P40 <> '1860 Bastrop Raw'!A40:P40))} -> 0
A41: 7 | B41: 5 | C41: Ira J | D41: Sims | E41: 10 | F41: 1850 | G41: Female | H41: White | L41: Texas | N41: Y | Q41: {=SUMPRODUCT(--('1860 Bastrop Clean'!A41:P41 <> '1860 Bastrop Raw'!A41:P41))} -> 0
A42: 7 | B42: 5 | C42: Stasca | D42: Sims | E42: 8 | F42: 1852 | G42: Female | H42: White | L42: Texas | N42: Y | Q42: {=SUMPRODUCT(--('1860 Bastrop Clean'!A42:P42 <> '1860 Bastrop Raw'!A42:P42))} -> 0
A43: 7 | B43: 5 | C43: Lola W | D43: Sims | E43: 1 | F43: 1859 | G43: Female | H43: White | L43: Texas | Q43: {=SUMPRODUCT(--('1860 Bastrop Clean'!A43:P43 <> '1860 Bastrop Raw'!A43:P43))} -> 0
A44: 7 | B44: 5 | C44: R D | D44: Allen | E44: 24 | F44: 1836 | G44: Male | H44: White | I44: Proff Math | J44: 500 | K44: 2000 | L44: District of Columbia | Q44: {=SUMPRODUCT(--('1860 Bastrop Clean'!A44:P44 <> '1860 Bastrop Raw'!A44:P44))} -> 0
A45: 7 | B45: 5 | C45: Launa A | D45: Allen | E45: 18 | F45: 1842 | G45: Female | H45: White | L45: Texas | Q45: {=SUMPRODUCT(--('1860 Bastrop Clean'!A45:P45 <> '1860 Bastrop Raw'!A45:P45))} -> 0
A46: 7 | B46: 5 | C46: Eola J | D46: Allen | E46: 45728 | F46: 1859 | G46: Female | H46: White | L46: Texas | Q46: {=SUMPRODUCT(--('1860 Bastrop Clean'!A46:P46 <> '1860 Bastrop Raw'!A46:P46))} -> 0
A47: 8 | B47: 6 | C47: Henny | D47: Cnochron | E47: 51 | F47: 1809 | G47: Male | H47: White | I47: Merchant | J47: 15000 | K47: 8000 | L47: New York | Q47: {=SUMPRODUCT(--('1860 Bastrop Clean'!A47:P47 <> '1860 Bastrop Raw'!A47:P47))} -> 0
A48: 8 | B48: 6 | C48: Mary | D48: Crochron | E48: 43 | F48: 1817 | G48: Female | H48: White | L48: England | Q48: {=SUMPRODUCT(--('1860 Bastrop Clean'!A48:P48 <> '1860 Bastrop Raw'!A48:P48))} -> 0
A49: 8 | B49: 6 | C49: William | D49: Nicholson | E49: 20 | F49: 1840 | G49: Male | H49: White | I49: Clerk | L49: New York | Q49: {=SUMPRODUCT(--('1860 Bastrop Clean'!A49:P49 <> '1860 Bastrop Raw'!A49:P49))} -> 0
A50: 8 | B50: 6 | C50: Mary A | D50: Nicholson | E50: 17 | F50: 1843 | G50: Female | H50: White | L50: Texas | Q50: {=SUMPRODUCT(--('1860 Bastrop Clean'!A50:P50 <> '1860 Bastrop Raw'!A50:P50))} -> 0
A51: 8 | B51: 6 | C51: Ruth T | D51: Nicholson | E51: 12 | F51: 1848 | G51: Female | H51: White | L51: Texas | N51: Y | Q51: {=SUMPRODUCT(--('1860 Bastrop Clean'!A51:P51 <> '1860 Bastrop Raw'!A51:P51))} -> 0
A52: 9 | B52: 7 | C52: John S | D52: Johnson | E52: 35 | F52: 1825 | G52: Male | H52: White | I52: Merchant | J52: 8000 | K52: 25000 | L52: New York | Q52: {=SUMPRODUCT(--('1860 Bastrop Clean'!A52:P52 <> '1860 Bastrop Raw'!A52:P52))} -> 0
A53: 9 | B53: 7 | C53: Permitia | D53: Johnson | E53: 26 | F53: 1834 | G53: Female | H53: White | L53: South Carolina | Q53: {=SUMPRODUCT(--('1860 Bastrop Clean'!A53:P53 <> '1860 Bastrop Raw'!A53:P53))} -> 0
A54: 9 | B54: 7 | C54: Alonzo | D54: Johnson | E54: 10 | F54: 1850 | G54: Male | H54: White | L54: Texas | N54: Y | Q54: {=SUMPRODUCT(--('1860 Bastrop Clean'!A54:P54 <> '1860 Bastrop Raw'!A54:P54))} -> 0
A55: 9 | B55: 7 | C55: Benjamin | D55: Johnson | E55: 8 | F55: 1852 | G55: Male | H55: White | L55: Texas | N55: Y | Q55: {=SUMPRODUCT(--('1860 Bastrop Clean'!A55:P55 <> '1860 Bastrop Raw'!A55:P55))} -> 0
A56: 9 | B56: 7 | C56: Samuel | D56: Johnson | E56: 4 | F56: 1856 | G56: Male | H56: White | L56: Texas | Q56: {=SUMPRODUCT(--('1860 Bastrop Clean'!A56:P56 <> '1860 Bastrop Raw'!A56:P56))} -> 0
A57: 9 | B57: 7 | C57: Charles | D57: Johnson | E57: 45820 | F57: 1859 | G57: Male | H57: White | L57: Texas | Q57: {=SUMPRODUCT(--('1860 Bastrop Clean'!A57:P57 <> '1860 Bastrop Raw'!A57:P57))} -> 0
A58: 9 | B58: 7 | C58: G B | D58: Cope | E58: 27 | F58: 1833 | G58: Male | H58: White | I58: Clerk | K58: 700 | L58: Tennessee | Q58: {=SUMPRODUCT(--('1860 Bastrop Clean'!A58:P58 <> '1860 Bastrop Raw'!A58:P58))} -> 0
A59: 10 | B59: 8 | C59: William A | D59: Smith | E59: 52 | F59: 1808 | G59: Male | H59: White | I59: Teacher | J59: 700 | K59: 5000 | L59: Kentucky | Q59: {=SUMPRODUCT(--('1860 Bastrop Clean'!A59:P59 <> '1860 Bastrop Raw'!A59:P59))} -> 0
A60: 10 | B60: 8 | C60: A H | D60: Smith | E60: 52 | F60: 1808 | G60: Female | H60: White | L60: Kentucky | Q60: {=SUMPRODUCT(--('1860 Bastrop Clean'!A60:P60 <> '1860 Bastrop Raw'!A60:P60))} -> 0
A61: 10 | B61: 8 | C61: William C | D61: Smith | F61: 1845 | G61: Male | H61: White | L61: Kentucky | N61: Y | Q61: {=SUMPRODUCT(--('1860 Bastrop Clean'!A61:P61 <> '1860 Bastrop Raw'!A61:P61))} -> 0
A62: 10 | B62: 8 | C62: L H | D62: Smith | E62: 10 | F62: 1850 | G62: Male | H62: White | L62: Kentucky | N62: Y | Q62: {=SUMPRODUCT(--('1860 Bastrop Clean'!A62:P62 <> '1860 Bastrop Raw'!A62:P62))} -> 0
A63: 10 | B63: 8 | C63: Anna R | D63: Smith | E63: 8 | F63: 1852 | G63: Female | H63: White | L63: Kentucky | N63: Y | Q63: {=SUMPRODUCT(--('1860 Bastrop Clean'!A63:P63 <> '1860 Bastrop Raw'!A63:P63))} -> 0
A64: 10 | B64: 8 | C64: James A | D64: Smith | E64: 5 | F64: 1855 | G64: Male | H64: White | L64: Texas | N64: Y | Q64: {=SUMPRODUCT(--('1860 Bastrop Clean'!A64:P64 <> '1860 Bastrop Raw'!A64:P64))} -> 0
A65: 11 | B65: 9 | C65: A W | D65: Anms | E65: 30 | F65: 1830 | G65: Male | H65: White | I65: Shoemaker | K65: 200 | L65: Georgia | Q65: {=SUMPRODUCT(--('1860 Bastrop Clean'!A65:P65 <> '1860 Bastrop Raw'!A65:P65))} -> 0
A66: 11 | B66: 9 | C66: N A | D66: Anmis | E66: 23 | F66: 1837 | G66: Female | H66: White | L66: Georgia | Q66: {=SUMPRODUCT(--('1860 Bastrop Clean'!A66:P66 <> '1860 Bastrop Raw'!A66:P66))} -> 1
A67: 12 | B67: 10 | C67: Sacop | D67: Leweris | E67: 36 | F67: 1824 | G67: Male | H67: White | I67: Shoemaker | L67: Pennsylvania | M67: Y | Q67: {=SUMPRODUCT(--('1860 Bastrop Clean'!A67:P67 <> '1860 Bastrop Raw'!A67:P67))} -> 0
A68: 12 | B68: 10 | C68: Hannah | D68: Lewers | E68: 18 | F68: 1842 | G68: Female | H68: White | L68: Germany | M68: Y | Q68: {=SUMPRODUCT(--('1860 Bastrop Clean'!A68:P68 <> '1860 Bastrop Raw'!A68:P68))} -> 0
A69: 13 | B69: 10 | C69: Mark | D69: Bernie | E69: 46 | F69: 1814 | G69: Male | H69: White | I69: Sadler | K69: 200 | L69: Portugal | Q69: {=SUMPRODUCT(--('1860 Bastrop Clean'!A69:P69 <> '1860 Bastrop Raw'!A69:P69))} -> 0
A70: 14 | B70: 11 | C70: R G | D70: Rice | E70: 46 | F70: 1814 | G70: Male | H70: White | I70: Master Sadler | J70: 1000 | K70: 500 | L70: Virginia | Q70: {=SUMPRODUCT(--('1860 Bastrop Clean'!A70:P70 <> '1860 Bastrop Raw'!A70:P70))} -> 0
A71: 14 | B71: 11 | C71: Martha | D71: Rice | E71: 46 | F71: 1814 | G71: Female | H71: White | L71: Kentucky | Q71: {=SUMPRODUCT(--('1860 Bastrop Clean'!A71:P71 <> '1860 Bastrop Raw'!A71:P71))} -> 0
A72: 14 | B72: 11 | C72: Sula P | D72: Rice | E72: 16 | F72: 1844 | G72: Female | H72: White | L72: Alabama | Q72: {=SUMPRODUCT(--('1860 Bastrop Clean'!A72:P72 <> '1860 Bastrop Raw'!A72:P72))} -> 0
A73: 14 | B73: 11 | C73: Robert G | D73: Rice | E73: 13 | F73: 1847 | G73: Male | H73: White | L73: Texas | N73: Y | Q73: {=SUMPRODUCT(--('1860 Bastrop Clean'!A73:P73 <> '1860 Bastrop Raw'!A73:P73))} -> 0
A74: 14 | B74: 11 | C74: Correlius B | D74: Rice | E74: 11 | F74: 1849 | G74: Female | H74: White | L74: Texas | N74: Y | Q74: {=SUMPRODUCT(--('1860 Bastrop Clean'!A74:P74 <> '1860 Bastrop Raw'!A74:P74))} -> 0
A75: 14 | B75: 11 | C75: John W | D75: Rice | E75: 8 | F75: 1852 | G75: Male | H75: White | L75: Texas | N75: Y | Q75: {=SUMPRODUCT(--('1860 Bastrop Clean'!A75:P75 <> '1860 Bastrop Raw'!A75:P75))} -> 0
A76: 14 | B76: 11 | C76: Rebecca | D76: Rice | E76: 6 | F76: 1854 | G76: Female | H76: White | L76: Texas | N76: Y | Q76: {=SUMPRODUCT(--('1860 Bastrop Clean'!A76:P76 <> '1860 Bastrop Raw'!A76:P76))} -> 0
A77: 14 | B77: 11 | C77: A J | D77: Batts | E77: 29 | F77: 1831 | G77: Male | H77: White | I77: Saddler | K77: 400 | L77: Virginia | Q77: {=SUMPRODUCT(--('1860 Bastrop Clean'!A77:P77 <> '1860 Bastrop Raw'!A77:P77))} -> 0
A78: 15 | B78: 11 | C78: Charles | D78: Briger | E78: 25 | F78: 1835 | G78: Male | H78: White | I78: Taylor | K78: 200 | L78: Prussia | Q78: {=SUMPRODUCT(--('1860 Bastrop Clean'!A78:P78 <> '1860 Bastrop Raw'!A78:P78))} -> 0
A79: 16 | B79: 12 | C79: Nelson | D79: Burch | E79: 48 | F79: 1812 | G79: Male | H79: White | I79: Merchant | J79: 15000 | K79: 25000 | L79: New York | Q79: {=SUMPRODUCT(--('1860 Bastrop Clean'!A79:P79 <> '1860 Bastrop Raw'!A79:P79))} -> 0
A80: 16 | B80: 12 | C80: Elizabeth | D80: Burch | E80: 32 | F80: 1828 | G80: Female | H80: White | L80: New York | Q80: {=SUMPRODUCT(--('1860 Bastrop Clean'!A80:P80 <> '1860 Bastrop Raw'!A80:P80))} -> 0
A81: 17 | B81: 13 | C81: Stephen C | D81: Nolen | E81: 49 | F81: 1811 | G81: Male | H81: White | I81: Farmer | J81: 500 | K81: 2500 | L81: Tennessee | Q81: {=SUMPRODUCT(--('1860 Bastrop Clean'!A81:P81 <> '1860 Bastrop Raw'!A81:P81))} -> 0
A82: 17 | B82: 13 | C82: Mary A | D82: Nolen | E82: 41 | F82: 1819 | G82: Female | H82: White | L82: Tennessee | Q82: {=SUMPRODUCT(--('1860 Bastrop Clean'!A82:P82 <> '1860 Bastrop Raw'!A82:P82))} -> 0
A83: 17 | B83: 13 | C83: Venginia | D83: Nolen | E83: 22 | F83: 1838 | G83: Female | H83: White | L83: Tennessee | Q83: {=SUMPRODUCT(--('1860 Bastrop Clean'!A83:P83 <> '1860 Bastrop Raw'!A83:P83))} -> 0
A84: 17 | B84: 13 | C84: Mary T | D84: Nolen | E84: 20 | F84: 1840 | G84: Female | H84: White | L84: Tennessee | Q84: {=SUMPRODUCT(--('1860 Bastrop Clean'!A84:P84 <> '1860 Bastrop Raw'!A84:P84))} -> 0
A85: 17 | B85: 13 | C85: Alexandra | D85: Nolen | E85: 14 | F85: 1846 | G85: Male | H85: White | L85: Mississippi | N85: Y | Q85: {=SUMPRODUCT(--('1860 Bastrop Clean'!A85:P85 <> '1860 Bastrop Raw'!A85:P85))} -> 0
A86: 17 | B86: 13 | C86: John | D86: Nolen | E86: 12 | F86: 1848 | G86: Male | H86: White | L86: Mississippi | N86: Y | Q86: {=SUMPRODUCT(--('1860 Bastrop Clean'!A86:P86 <> '1860 Bastrop Raw'!A86:P86))} -> 0
A87: 17 | B87: 13 | C87: Willmath | D87: Nolen | E87: 10 | F87: 1850 | G87: Female | H87: White | L87: Texas | N87: Y | Q87: {=SUMPRODUCT(--('1860 Bastrop Clean'!A87:P87 <> '1860 Bastrop Raw'!A87:P87))} -> 0
A88: 17 | B88: 13 | C88: Turner | D88: Nolen | E88: 8 | F88: 1852 | G88: Male | H88: White | L88: Texas | Q88: {=SUMPRODUCT(--('1860 Bastrop Clean'!A88:P88 <> '1860 Bastrop Raw'!A88:P88))} -> 0
A89: 17 | B89: 13 | C89: William | D89: Nolen | E89: 4 | F89: 1856 | G89: Male | H89: White | L89: Texas | Q89: {=SUMPRODUCT(--('1860 Bastrop Clean'!A89:P89 <> '1860 Bastrop Raw'!A89:P89))} -> 0
A90: 17 | B90: 13 | C90: Anna | D90: Nolen | E90: 1 | F90: 1859 | G90: Female | H90: White | L90: Texas | Q90: {=SUMPRODUCT(--('1860 Bastrop Clean'!A90:P90 <> '1860 Bastrop Raw'!A90:P90))} -> 0
A91: 17 | B91: 13 | C91: Ada | D91: Nolen | E91: 1 | F91: 1859 | G91: Female | H91: White | L91: Texas | Q91: {=SUMPRODUCT(--('1860 Bastrop Clean'!A91:P91 <> '1860 Bastrop Raw'!A91:P91))} -> 0
A92: 18 | B92: 14 | C92: G | D92: Friedberger | E92: 20 | F92: 1840 | G92: Male | H92: White | I92: Merchant | J92: 3500 | K92: 12000 | L92: Germany | Q92: {=SUMPRODUCT(--('1860 Bastrop Clean'!A92:P92 <> '1860 Bastrop Raw'!A92:P92))} -> 0
A93: 19 | B93: 15 | C93: A S | D93: Rose | E93: 34 | F93: 1826 | G93: Male | H93: White | I93: Carriage Maker | J93: 3000 | K93: 1500 | L93: New York | Q93: {=SUMPRODUCT(--('1860 Bastrop Clean'!A93:P93 <> '1860 Bastrop Raw'!A93:P93))} -> 0
A94: 19 | B94: 15 | C94: Jane | D94: Rose | E94: 41 | F94: 1819 | G94: Female | H94: White | L94: New York | Q94: {=SUMPRODUCT(--('1860 Bastrop Clean'!A94:P94 <> '1860 Bastrop Raw'!A94:P94))} -> 0
A95: 19 | B95: 15 | C95: Joshua | D95: Rose | E95: 14 | F95: 1846 | G95: Male | H95: White | L95: New Jersey | N95: Y | Q95: {=SUMPRODUCT(--('1860 Bastrop Clean'!A95:P95 <> '1860 Bastrop Raw'!A95:P95))} -> 0
A96: 19 | B96: 15 | C96: Charles | D96: Rose | E96: 12 | F96: 1848 | G96: Male | H96: White | L96: New York | N96: Y | Q96: {=SUMPRODUCT(--('1860 Bastrop Clean'!A96:P96 <> '1860 Bastrop Raw'!A96:P96))} -> 0
A97: 19 | B97: 15 | C97: Jane | D97: Rose | E97: 8 | F97: 1852 | G97: Female | H97: White | L97: New York | N97: Y | Q97: {=SUMPRODUCT(--('1860 Bastrop Clean'!A97:P97 <> '1860 Bastrop Raw'!A97:P97))} -> 0
A98: 19 | B98: 15 | C98: Chester | D98: Rose | E98: 6 | F98: 1854 | G98: Male | H98: White | L98: Alla | N98: Y | Q98: {=SUMPRODUCT(--('1860 Bastrop Clean'!A98:P98 <> '1860 Bastrop Raw'!A98:P98))} -> 0
A99: 20 | B99: 15 | C99: Jenny | D99: Gordier | G99: Male | H99: White | I99: Carriage Maker | J99: 1500 | L99: Alla | Q99: {=SUMPRODUCT(--('1860 Bastrop Clean'!A99:P99 <> '1860 Bastrop Raw'!A99:P99))} -> 0
A100: 20 | B100: 15 | C100: Ellen | D100: Gordier | E100: 21 | F100: 1839 | G100: Female | H100: White | L100: New York | Q100: {=SUMPRODUCT(--('1860 Bastrop Clean'!A100:P100 <> '1860 Bastrop Raw'!A100:P100))} -> 0
...

Sheet 1870 Bastrop Clean
A1: Line Number | B1: Dwelling Number | C1: Family Number | D1: Surname | E1: Given Name | F1: Age | G1: Birth Year | H1: Gender | I1: Race | J1: Occupation | K1: Real Estate Value | L1: Personal Estate Value | M1: Birthplace | N1: Father of Foreign Birth | O1: Mother of Foreign Birth | P1: Birth Month | Q1: Marriage Month | R1: Attended School | S1: Cannot Read | T1: Cannot Write | U1: Condition | V1: Male Citizen Over 21 | W1: Denied Voting Rights
A2: 1 | B2: 1 | C2: 1 | D2: Schaefer | E2: Cho | F2: 54 | G2: 1816 | H2: Male | I2: White | J2: Farmer | K2: 1000 | L2: 300 | M2: Bavaria / Bayern | N2: Yes | O2: Yes | V2: Yes
A3: =A2+1 -> 2 | B3: 1 | C3: 1 | D3: Schaefer | E3: Barbara | F3: 54 | G3: 1816 | H3: Female | I3: White | J3: Keeping House | M3: Bavaria / Bayern | N3: Yes | O3: Yes
A4: =A3+1 -> 3 | B4: 1 | C4: 1 | D4: Schaefer | E4: Andreas | F4: 24 | G4: 1846 | H4: Male | I4: White | J4: Farm Laborer | M4: Texas | N4: Yes | O4: Yes | V4: Yes
A5: =A4+1 -> 4 | B5: 1 | C5: 2 | D5: Geis | E5: Christian | F5: 26 | G5: 1844 | H5: Male | I5: White | J5: Farmer | K5: 600 | L5: 200 | M5: Nassau | N5: Yes | O5: Yes | V5: Yes
A6: =A5+1 -> 5 | B6: 1 | C6: 2 | D6: Geis | E6: Barbara | F6: 27 | G6: 1843 | H6: Female | I6: White | J6: Keeping House | M6: Bavaria / Bayern | N6: Yes | O6: Yes
A7: =A6+1 -> 6 | B7: 1 | C7: 2 | D7: Geis | E7: Helene | F7: 7 | G7: 1863 | H7: Female | I7: White | M7: Texas | N7: Yes | O7: Yes
A8: =A7+1 -> 7 | B8: 1 | C8: 2 | D8: Geis | E8: Henry | F8: 2 | G8: 1868 | H8: Male | I8: White | M8: Texas | N8: Yes | O8: Yes
A9: =A8+1 -> 8 | B9: 2 | C9: 3 | D9: Schefsky | E9: C R V | F9: 40 | G9: 1830 | H9: Male | I9: White | J9: Teacher & DU Sea | K9: 1000 | L9: 400 | M9: Hannover / Hanover | N9: Yes | O9: Yes | V9: Yes
A10: =A9+1 -> 9 | B10: 2 | C10: 3 | D10: Schefsky | E10: Johanna | F10: 51 | G10: 1819 | H10: Female | I10: White | J10: Keeping House | M10: Holstein | N10: Yes | O10: Yes
A11: =A10+1 -> 10 | B11: 3 | C11: 4 | D11: Wertsner | E11: Chas | F11: 40 | G11: 1830 | H11: Male | I11: White | J11: Merchant & Post M | K11: 1500 | L11: 2000 | M11: Saxonia | N11: Yes | O11: Yes | V11: Yes
A12: =A11+1 -> 11 | B12: 3 | C12: 4 | D12: Wertsner | E12: Franziska | F12: 31 | G12: 1839 | H12: Female | I12: White | J12: Keeping House | M12: Bohemia | N12: Yes | O12: Yes
A13: =A12+1 -> 12 | B13: 3 | C13: 4 | D13: Wertsner | E13: Oskar | F13: 11 | G13: 1859 | H13: Male | I13: White | J13: Farmer | M13: Texas | N13: Yes | O13: Yes | R13: Yes
A14: =A13+1 -> 13 | B14: 3 | C14: 4 | D14: Wertsner | E14: Selma | F14: 7 | G14: 1863 | H14: Female | I14: White | M14: Texas | N14: Yes | O14: Yes
A15: =A14+1 -> 14 | B15: 3 | C15: 4 | D15: Wertsner | E15: Pauline | F15: 5 | G15: 1865 | H15: Female | I15: White | M15: Texas | N15: Yes | O15: Yes
A16: =A15+1 -> 15 | B16: 3 | C16: 4 | D16: Wertsner | E16: Elisabeth | F16: 1 | G16: 1869 | H16: Female | I16: White | M16: Texas | N16: Yes | O16: Yes
A17: =A16+1 -> 16 | B17: 3 | C17: 4a | D17: Hanke | E17: Anna | F17: 19 | G17: 1851 | H17: Female | I17: White | J17: Domestic Servant | M17: Prussia | N17: Yes | O17: Yes
A18: =A17+1 -> 17 | B18: 3 | C18: 4b | D18: Hopler | E18: John | F18: 53 | G18: 1817 | H18: Male | I18: White | J18: Domestic Servant | M18: Mecklenburg | N18: Yes | O18: Yes | V18: Yes
A19: =A18+1 -> 18 | B19: 3 | C19: 4c | D19: Woehl | E19: Joseph | F19: 16 | G19: 1854 | H19: Male | I19: White | J19: Clerk In Store | M19: Texas | N19: Yes | O19: Yes
A20: =A19+1 -> 19 | B20: 4 | C20: 5 | D20: Glockner | E20: Moritz | F20: 57 | G20: 1813 | H20: Male | I20: White | J20: Baker & Mercha | K20: 2000 | L20: 1000 | M20: Bohemia | N20: Yes | O20: Yes | V20: Yes
A21: =A20+1 -> 20 | B21: 4 | C21: 5 | D21: Glockner | E21: Solovia | F21: 34 | G21: 1836 | H21: Female | I21: White | J21: Keeping House | M21: Bohemia | N21: Yes | O21: Yes
A22: =A21+1 -> 21 | B22: 4 | C22: 5 | D22: Glockner | E22: Salonia | F22: 13 | G22: 1857 | H22: Female | I22: White | M22: Texas | N22: Yes | O22: Yes | R22: Yes
A23: =A22+1 -> 22 | B23: 4 | C23: 5 | D23: Glockner | E23: Joseph | F23: 10 | G23: 1860 | H23: Male | I23: White | M23: Texas | N23: Yes | O23: Yes | R23: Yes
A24: =A23+1 -> 23 | B24: 4 | C24: 5 | D24: Glockner | E24: Tracy | F24: 8 | G24: 1862 | H24: Male | I24: White | M24: Texas | N24: Yes | O24: Yes | R24: Yes
A25: =A24+1 -> 24 | B25: 4 | C25: 5 | D25: Glockner | E25: Anton | F25: 1 | G25: 1869 | H25: Male | I25: White | M25: Texas | N25: Yes | O25: Yes
A26: =A25+1 -> 25 | B26: 4 | C26: 5 | D26: Glockner | E26: William | F26: 45820 | G26: 1870 | H26: Male | I26: White | M26: Texas | N26: Yes | O26: Yes | P26: Feb
A27: =A26+1 -> 26 | B27: 5 | C27: 6 | D27: Spifer | E27: George | F27: 24 | G27: 1846 | H27: Male | I27: White | J27: Sadler & Harness | K27: 500 | M27: Hesse-Darmstadt / Hessen-Darmstadt | N27: Yes | O27: Yes | V27: Yes
A28: =A27+1 -> 27 | B28: 5 | C28: 6 | D28: Spifer | E28: Antonia | F28: 20 | G28: 1850 | H28: Female | I28: White | J28: Keeping House | M28: Bohemia | N28: Yes | O28: Yes
A29: =A28+1 -> 28 | B29: 5 | C29: 6a | D29: Stelzig | E29: Anton | F29: 20 | G29: 1850 | H29: Male | I29: White | J29: Apprent To Saw | M29: Bohemia | N29: Yes | O29: Yes
A30: =A29+1 -> 29 | B30: 6 | C30: 7 | D30: Coppel | E30: Henry | F30: 30 | G30: 1840 | H30: Male | I30: White | J30: Merchant In Retail | K30: 600 | L30: 2000 | M30: Hesse-Darmstadt / Hessen-Darmstadt | N30: Yes | O30: Yes | V30: Yes
A31: =A30+1 -> 30 | B31: 6 | C31: 7 | D31: Coppel | E31: Caroline | F31: 24 | G31: 1846 | H31: Female | I31: White | J31: Keeping House | M31: Hesse-Darmstadt / Hessen-Darmstadt | N31: Yes | O31: Yes
A32: =A31+1 -> 31 | B32: 6 | C32: 7 | D32: Coppel | E32: Jacob | F32: 26 | G32: 1844 | H32: Male | I32: White | J32: Merchant In Retail | M32: Hesse-Darmstadt / Hessen-Darmstadt | N32: Yes | O32: Yes | V32: Yes
A33: =A32+1 -> 32 | B33: 7 | C33: 8 | D33: Spittler | E33: N M | F33: 37 | G33: 1833 | H33: Male | I33: White | J33: Farmer & Dik Co | K33: 1500 | L33: 500 | M33: Indiana | N33: Yes | V33: Yes
A34: =A33+1 -> 33 | B34: 7 | C34: 8 | D34: Spittler | E34: Sarah | F34: 33 | G34: 1837 | H34: Female | I34: White | J34: Keeping House | M34: Texas
A35: =A34+1 -> 34 | B35: 7 | C35: 8 | D35: Spittler | E35: Jos M | F35: 11 | G35: 1859 | H35: Male | I35: White | M35: Texas | R35: Yes
A36: =A35+1 -> 35 | B36: 7 | C36: 8 | D36: Spittler | E36: Florence | F36: 9 | G36: 1861 | H36: Female | I36: White | M36: Texas | R36: Yes
A37: =A36+1 -> 36 | B37: 7 | C37: 8 | D37: Spittler | E37: Allen | F37: 6 | G37: 1864 | H37: Male | I37: White | M37: Texas
A38: =A37+1 -> 37 | B38: 7 | C38: 8 | D38: Spittler | E38: W M | F38: 2 | G38: 1868 | H38: Male | I38: White | M38: Texas
A39: =A38+1 -> 38 | B39: 7 | C39: 8a | D39: Sneed | E39: Cyntah | F39: 35 | G39: 1835 | H39: Female | I39: Black | J39: Domestic Servant | M39: Georgia | S39: Yes | T39: Yes | U39: B-.
A40: =A39+1 -> 39 | B40: 7 | C40: 8b | D40: Wilkins | E40: Haney | F40: 53 | G40: 1817 | H40: Female | I40: Black | J40: Farm Laborer | M40: Alabama | S40: Yes | T40: Yes | U40: B-.
A41: 40 | B41: 7 | C41: 8b | D41: Wilkins | E41: Thom | F41: 9 | G41: 1861 | H41: Male | I41: Black | M41: Texas
A42: 1 | B42: 8 | C42: 9 | D42: Rein | E42: George B | F42: 49 | G42: 1821 | H42: Male | I42: White | J42: Baker & Farmer | K42: 600 | L42: 400 | M42: Hesse-Kassel / Hessen-Kassel / Electorate of Hesse / Kurhessen | N42: Yes | O42: Yes | V42: Yes
A43: =A42+1 -> 2 | B43: 8 | C43: 9 | D43: Rein | E43: Therese | F43: 43 | G43: 1827 | H43: Female | I43: White | J43: Keeping House | M43: Prussia | N43: Yes | O43: Yes
A44: =A43+1 -> 3 | B44: 8 | C44: 9 | D44: Rein | E44: Julia | F44: 14 | G44: 1856 | H44: Female | I44: White | M44: Texas | N44: Yes | O44: Yes | R44: Yes
A45: =A44+1 -> 4 | B45: 8 | C45: 9 | D45: Rein | E45: Helena | F45: 12 | G45: 1858 | H45: Female | I45: White | M45: Texas | N45: Yes | O45: Yes | R45: Yes
A46: =A45+1 -> 5 | B46: 8 | C46: 9 | D46: Rein | E46: Emma | F46: 10 | G46: 1860 | H46: Female | I46: White | M46: Texas | N46: Yes | O46: Yes | R46: Yes
A47: =A46+1 -> 6 | B47: 8 | C47: 9 | D47: Rein | E47: John | F47: 8 | G47: 1862 | H47: Male | I47: White | M47: Texas | N47: Yes | O47: Yes | R47: Yes
A48: =A47+1 -> 7 | B48: 8 | C48: 9 | D48: Rein | E48: Therese | F48: 6 | G48: 1864 | H48: Female | I48: White | M48: Texas | N48: Yes | O48: Yes
A49: =A48+1 -> 8 | B49: 8 | C49: 9 | D49: Rein | E49: Bertha | F49: 4 | G49: 1866 | H49: Female | I49: White | M49: Texas | N49: Yes | O49: Yes
A50: =A49+1 -> 9 | B50: 9 | C50: 10 | D50: Gillmoore | E50: M | F50: 45 | G50: 1825 | H50: Male | I50: Black | J50: Blacksmith | K50: 600 | M50: Tennessee | S50: Yes | T50: Yes | U50: B. | V50: Yes
A51: =A50+1 -> 10 | B51: 9 | C51: 10 | D51: Gillmoore | E51: Anna | F51: 42 | G51: 1828 | H51: Female | I51: Mulatto | J51: Keeping House | M51: Kentucky | T51: Yes | U51: B-.
A52: =A51+1 -> 11 | B52: 9 | C52: 10 | D52: Anderson | E52: Maria | F52: 16 | G52: 1854 | H52: Female | I52: Mulatto | M52: Kentucky | R52: Yes
A53: =A52+1 -> 12 | B53: 9 | C53: 10b | D53: Williams | E53: Rob | F53: 24 | G53: 1846 | H53: Male | I53: Mulatto | J53: Day Labourer | M53: Texas | S53: Yes | T53: Yes | U53: B.
A54: =A53+1 -> 13 | B54: 10 | C54: 11 | D54: Krause | E54: Ward | F54: 45 | G54: 1825 | H54: Male | I54: White | J54: Wheelwright | K54: 800 | M54: Hesse-Kassel / Hessen-Kassel / Electorate of Hesse / Kurhessen | N54: Yes | O54: Yes | V54: Yes
A55: =A54+1 -> 14 | B55: 10 | C55: 11 | D55: Krause | E55: Anna | F55: 30 | G55: 1840 | H55: Female | I55: White | J55: Keeping House | M55: Bohemia | N55: Yes | O55: Yes
A56: =A55+1 -> 15 | B56: 10 | C56: 11 | D56: Krause | E56: Lisette | F56: 7 | G56: 1863 | H56: Female | I56: White | M56: Texas
A57: =A56+1 -> 16 | B57: 10 | C57: 11 | D57: Krause | E57: Sarah | F57: 5 | G57: 1865 | H57: Female | I57: White | M57: Texas
A58: =A57+1 -> 17 | B58: 10 | C58: 11 | D58: Krause | E58: Otto | F58: 4 | G58: 1866 | H58: Male | I58: White | M58: Texas
A59: =A58+1 -> 18 | B59: 10 | C59: 11 | D59: Schneider | E59: Helene | F59: 16 | G59: 1854 | H59: Female | I59: White | J59: Milliner | M59: Bohemia | N59: Yes | O59: Yes
A60: =A59+1 -> 19 | B60: 10 | C60: 11 | D60: Emmert | E60: Garland | F60: 16 | G60: 1854 | H60: Male | I60: White | J60: Apprent To Wheelw | M60: Hesse-Darmstadt / Hessen-Darmstadt | N60: Yes | O60: Yes
A61: =A60+1 -> 20 | B61: 11 | C61: 12 | D61: Prokop | E61: B | F61: 39 | G61: 1831 | H61: Male | I61: White | J61: Watchmaker | K61: 800 | L61: 200 | M61: Bohemia | N61: Yes | O61: Yes | S61: Yes | V61: Yes
A62: =A61+1 -> 21 | B62: 11 | C62: 12 | D62: Prokop | E62: Celestine | F62: 13 | G62: 1857 | H62: Female | I62: White | M62: Texas | N62: Yes | O62: Yes
A63: =A62+1 -> 22 | B63: 11 | C63: 12 | D63: Prokop | E63: Emil | F63: 11 | G63: 1859 | H63: Male | I63: White | M63: Texas | N63: Yes | O63: Yes
A64: =A63+1 -> 23 | B64: 12 | C64: 13 | D64: Fehr | E64: William | F64: 27 | G64: 1843 | H64: Male | I64: White | J64: Cabinet Maker | K64: 300 | M64: Holstein | N64: Yes | O64: Yes | V64: Yes
A65: =A64+1 -> 24 | B65: 12 | C65: 13 | D65: Buchmeier | E65: Chas | F65: 28 | G65: 1842 | H65: Male | I65: White | J65: Cabinet Maker | M65: Baden | N65: Yes | O65: Yes
A66: =A65+1 -> 25 | B66: 13 | C66: 14 | D66: Marr | E66: Hugh | F66: 47 | G66: 1823 | H66: Male | I66: White | J66: Builder | K66: 1000 | M66: New York | N66: Yes | O66: Yes | V66: Yes
A67: =A66+1 -> 26 | B67: 13 | C67: 14 | D67: Marr | E67: Mary L | F67: 30 | G67: 1840 | H67: Female | I67: White | J67: Keeping House | K67: 600 | M67: Texas | N67: Yes
A68: =A67+1 -> 27 | B68: 13 | C68: 14 | D68: Marr | E68: Cyrus H | F68: 17 | G68: 1853 | H68: Male | I68: White | J68: At Home | M68: Mississippi
A69: =A68+1 -> 28 | B69: 13 | C69: 14 | D69: Marr | E69: Georgina | F69: 15 | G69: 1855 | H69: Female | I69: White | M69: Texas | R69: Yes
A70: =A69+1 -> 29 | B70: 13 | C70: 14 | D70: Marr | E70: Sam W | F70: 13 | G70: 1857 | H70: Male | I70: White | M70: Texas | R70: Yes
A71: =A70+1 -> 30 | B71: 13 | C71: 14 | D71: Marr | E71: Georg T | F71: 9 | G71: 1861 | H71: Male | I71: White | M71: Texas
A72: =A71+1 -> 31 | B72: 13 | C72: 14 | D72: Marr | E72: Anna | F72: 6 | G72: 1864 | H72: Female | I72: White | M72: Texas
A73: =A72+1 -> 32 | B73: 13 | C73: 14 | D73: Morrais | E73: Alice | F73: 22 | G73: 1848 | H73: Female | I73: White | J73: At Home | M73: Texas
A74: =A73+1 -> 33 | B74: 14 | C74: 15 | D74: Shepperth | E74: Fan | F74: 60 | G74: 1810 | H74: Male | I74: White | J74: Machinist Carp | K74: 800 | M74: Kentucky | V74: Yes
A75: =A74+1 -> 34 | B75: 14 | C75: 15 | D75: Sanders | E75: Lotte | F75: 35 | G75: 1835 | H75: Female | I75: Black | J75: Keeping House | M75: Alabama | S75: Yes | T75: Yes | U75: B-.
A76: =A75+1 -> 35 | B76: 14 | C76: 15 | D76: Hargrave | E76: Lotte | F76: 12 | G76: 1858 | H76: Female | I76: Mulatto | M76: Louisiana | R76: Yes
A77: =A76+1 -> 36 | B77: 15 | C77: 16 | D77: Brieger | E77: Charls | F77: 33 | G77: 1837 | H77: Male | I77: White | J77: Taylor | M77: Prussia | N77: Yes | O77: Yes | V77: Yes
A78: =A77+1 -> 37 | B78: 15 | C78: 16 | D78: Brieger | E78: Maria | F78: 25 | G78: 1845 | H78: Female | I78: White | J78: Keeping House | M78: Nassau | N78: Yes | O78: Yes
A79: =A78+1 -> 38 | B79: 15 | C79: 16 | D79: Brieger | E79: Charles | F79: 7 | G79: 1863 | H79: Male | I79: White | M79: Texas | N79: Yes | O79: Yes | R79: Yes
A80: =A79+1 -> 39 | B80: 15 | C80: 16 | D80: Brieger | E80: Willy | F80: 3 | G80: 1867 | H80: Male | I80: White | M80: Texas | N80: Yes | O80: Yes
A81: =A80+1 -> 40 | B81: 15 | C81: 16 | D81: Brieger | E81: Alberta | F81: 1 | G81: 1869 | H81: Male | I81: White | M81: Texas | N81: Yes | O81: Yes
A82: 1 | B82: 16 | C82: 17 | D82: Austin | E82: Caroline | F82: 45 | G82: 1825 | H82: Female | I82: White | J82: Keeping House | M82: Poland | N82: Yes | O82: Yes
A83: =A82+1 -> 2 | B83: 16 | C83: 17 | D83: Austin | E83: Amalia | F83: 16 | G83: 1854 | H83: Female | I83: White | M83: Poland | N83: Yes | O83: Yes
A84: =A83+1 -> 3 | B84: 16 | C84: 17 | D84: Bothe | E84: Julius | F84: 18 | G84: 1852 | H84: Male | I84: White | J84: Clerk In Grocery | M84: Poland | N84: Yes | O84: Yes
A85: =A84+1 -> 4 | B85: 16 | C85: 17 | D85: Bothe | E85: Bertha | F85: 11 | G85: 1859 | H85: Female | I85: White | M85: Poland | R85: Yes
A86: =A85+1 -> 5 | B86: 16 | C86: 17 | D86: Bothe | E86: Warda | F86: 9 | G86: 1861 | H86: Female | I86: White | M86: Poland | R86: Yes
A87: =A86+1 -> 6 | B87: 16 | C87: 18 | D87: Kleinert | E87: Charl | F87: 47 | G87: 1823 | H87: Male | I87: White | J87: Merchant & Wheelwright | K87: 1600 | M87: Poland | N87: Yes | O87: Yes | V87: Yes
A88: =A87+1 -> 7 | B88: 16 | C88: 18 | D88: Kleinert | E88: Maria | F88: 42 | G88: 1828 | H88: Female | I88: White | J88: Keeping House | M88: Prussia | N88: Yes | O88: Yes
A89: =A88+1 -> 8 | B89: 16 | C89: 18 | D89: Kleinert | E89: Maria | F89: 13 | G89: 1857 | H89: Female | I89: White | M89: Texas | R89: Yes
A90: =A89+1 -> 9 | B90: 16 | C90: 18 | D90: Kleinert | E90: Alexand | F90: 8 | G90: 1862 | H90: Male | I90: White | M90: Texas | R90: Yes
A91: =A90+1 -> 10 | B91: 17 | C91: 19 | D91: Starcke | E91: Richd | F91: 43 | G91: 1827 | H91: Male | I91: White | J91: Physician Domed | K91: 1000 | L91: 600 | M91: Prussia | N91: Yes | O91: Yes | V91: Yes
A92: =A91+1 -> 11 | B92: 17 | C92: 19 | D92: Starcke | E92: Auguste | F92: 42 | G92: 1828 | H92: Female | I92: White | J92: Keeping House | M92: Prussia | N92: Yes | O92: Yes
A93: =A92+1 -> 12 | B93: 17 | C93: 19 | D93: Starcke | E93: Max | F93: 14 | G93: 1856 | H93: Male | I93: White | M93: Texas | N93: Yes | O93: Yes | R93: Yes
A94: =A93+1 -> 13 | B94: 17 | C94: 19 | D94: Starcke | E94: Richard | F94: 12 | G94: 1858 | H94: Male | I94: White | M94: Texas | N94: Yes | O94: Yes | R94: Yes
A95: =A94+1 -> 14 | B95: 17 | C95: 19 | D95: Starcke | E95: Georg | F95: 10 | G95: 1860 | H95: Male | I95: White | M95: Texas | N95: Yes | O95: Yes | R95: Yes
A96: =A95+1 -> 15 | B96: 17 | C96: 19 | D96: Starcke | E96: Elisabeth | F96: 8 | G96: 1862 | H96: Female | I96: White | M96: Texas | N96: Yes | O96: Yes | R96: Yes | S96: Yes
A97: =A96+1 -> 16 | B97: 17 | C97: 19 | D97: Starcke | E97: Helene | F97: 6 | G97: 1864 | H97: Female | I97: White | M97: Texas | N97: Yes | O97: Yes
A98: =A97+1 -> 17 | B98: 17 | C98: 19 | D98: Starcke | E98: Egen | F98: 4 | G98: 1866 | H98: Male | I98: White | M98: Texas | N98: Yes | O98: Yes
A99: =A98+1 -> 18 | B99: 17 | C99: 19a | D99: Futtalow | E99: Lizzie | F99: 16 | G99: 1854 | H99: Female | I99: White | J99: Domest Servant | M99: Kentucky
A100: =A99+1 -> 19 | B100: 17 | C100: 20 | D100: Harke | E100: Christ | F100: 77 | G100: 1793 | H100: Female | I100: White | J100: Keeping House | M100: Prussia | N100: Yes | O100: Yes
...

Sheet 1870 Bastrop Raw
A1: Line Number | B1: Dwelling Number | C1: Family Number | D1: Surname | E1: Given Name | F1: Age | G1: Birth Year | H1: Gender | I1: Race | J1: Occupation | K1: Real Estate Value | L1: Personal Estate Value | M1: Birthplace | N1: Father of Foreign Birth | O1: Mother of Foreign Birth | P1: Birth Month | Q1: Marriage Month | R1: Attended School | S1: Cannot Read | T1: Cannot Write | U1: Condition | V1: Male Citizen Over 21 | W1: Denied Voting Rights
A2: 8 | B2: 2 | C2: 3 | D2: Schefsky | E2: C R V | F2: 40 | G2: 1830 | H2: Male | I2: White | J2: Teacher & DU Sea | K2: 1000 | L2: 400 | M2: Hannover / Hanover | N2: Yes | O2: Yes | V2: Yes | X2: {=SUMPRODUCT(--(INDEX('1870 Bastrop Clean'!A:W, MATCH(A2 & "|" & B2,'1870 Bastrop Clean'!A:A & "|" & '1870 Bastrop Clean'!B:B, 0), 0) <> '1870 Bastrop Raw'!A2:W2))} -> 0
A3: 9 | B3: 2 | C3: 3 | D3: Schefsky | E3: Johanna | F3: 51 | G3: 1819 | H3: Female | I3: White | J3: Keeping House | M3: Holstein | N3: Yes | O3: Yes | X3: {=SUMPRODUCT(--(INDEX('1870 Bastrop Clean'!A:W, MATCH(A3 & "|" & B3,'1870 Bastrop Clean'!A:A & "|" & '1870 Bastrop Clean'!B:B, 0), 0) <> '1870 Bastrop Raw'!A3:W3))} -> 0
A4: 29 | B4: 6 | C4: 7 | D4: Coppel | E4: Henry | F4: 30 | G4: 1840 | H4: Male | I4: White | J4: Merchant In Retail | K4: 600 | L4: 2000 | M4: Hesse-Darmstadt / Hessen-Darmstadt | N4: Yes | O4: Yes | V4: Yes | X4: {=SUMPRODUCT(--(INDEX('1870 Bastrop Clean'!A:W, MATCH(A4 & "|" & B4,'1870 Bastrop Clean'!A:A & "|" & '1870 Bastrop Clean'!B:B, 0), 0) <> '1870 Bastrop Raw'!A4:W4))} -> 0
A5: 30 | B5: 6 | C5: 7 | D5: Coppel | E5: Caroline | F5: 24 | G5: 1846 | H5: Female | I5: White | J5: Keeping House | M5: Hesse-Darmstadt / Hessen-Darmstadt | N5: Yes | O5: Yes | X5: {=SUMPRODUCT(--(INDEX('1870 Bastrop Clean'!A:W, MATCH(A5 & "|" & B5,'1870 Bastrop Clean'!A:A & "|" & '1870 Bastrop Clean'!B:B, 0), 0) <> '1870 Bastrop Raw'!A5:W5))} -> 0
A6: 31 | B6: 6 | C6: 7 | D6: Coppel | E6: Jacob | F6: 26 | G6: 1844 | H6: Male | I6: White | J6: Merchant In Retail | M6: Hesse-Darmstadt / Hessen-Darmstadt | N6: Yes | O6: Yes | V6: Yes | X6: {=SUMPRODUCT(--(INDEX('1870 Bastrop Clean'!A:W, MATCH(A6 & "|" & B6,'1870 Bastrop Clean'!A:A & "|" & '1870 Bastrop Clean'!B:B, 0), 0) <> '1870 Bastrop Raw'!A6:W6))} -> 0
A7: 1 | B7: 1 | C7: 1 | D7: Schaefer | E7: Cho | F7: 54 | G7: 1816 | H7: Male | I7: White | J7: Farmer | K7: 1000 | L7: 300 | M7: Bavaria / Bayern | N7: Yes | O7: Yes | V7: Yes | X7: {=SUMPRODUCT(--(INDEX('1870 Bastrop Clean'!A:W, MATCH(A7 & "|" & B7,'1870 Bastrop Clean'!A:A & "|" & '1870 Bastrop Clean'!B:B, 0), 0) <> '1870 Bastrop Raw'!A7:W7))} -> 0
A8: 2 | B8: 1 | C8: 1 | D8: Schaefer | E8: Barbara | F8: 54 | G8: 1816 | H8: Female | I8: White | J8: Keeping House | M8: Bavaria / Bayern | N8: Yes | O8: Yes | X8: {=SUMPRODUCT(--(INDEX('1870 Bastrop Clean'!A:W, MATCH(A8 & "|" & B8,'1870 Bastrop Clean'!A:A & "|" & '1870 Bastrop Clean'!B:B, 0), 0) <> '1870 Bastrop Raw'!A8:W8))} -> 0
A9: 3 | B9: 1 | C9: 1 | D9: Schaefer | E9: Andreas | F9: 24 | G9: 1846 | H9: Male | I9: White | J9: Farm Laborer | M9: Texas | N9: Yes | O9: Yes | V9: Yes | X9: {=SUMPRODUCT(--(INDEX('1870 Bastrop Clean'!A:W, MATCH(A9 & "|" & B9,'1870 Bastrop Clean'!A:A & "|" & '1870 Bastrop Clean'!B:B, 0), 0) <> '1870 Bastrop Raw'!A9:W9))} -> 0
A10: 4 | B10: 1 | C10: 2 | D10: Geis | E10: Christian | F10: 26 | G10: 1844 | H10: Male | I10: White | J10: Farmer | K10: 600 | L10: 200 | M10: Nassau | N10: Yes | O10: Yes | V10: Yes | X10: {=SUMPRODUCT(--(INDEX('1870 Bastrop Clean'!A:W, MATCH(A10 & "|" & B10,'1870 Bastrop Clean'!A:A & "|" & '1870 Bastrop Clean'!B:B, 0), 0) <> '1870 Bastrop Raw'!A10:W10))} -> 0
A11: 5 | B11: 1 | C11: 2 | D11: Geis | E11: Barbara | F11: 27 | G11: 1843 | H11: Female | I11: White | J11: Keeping House | M11: Bavaria / Bayern | N11: Yes | O11: Yes | X11: {=SUMPRODUCT(--(INDEX('1870 Bastrop Clean'!A:W, MATCH(A11 & "|" & B11,'1870 Bastrop Clean'!A:A & "|" & '1870 Bastrop Clean'!B:B, 0), 0) <> '1870 Bastrop Raw'!A11:W11))} -> 0
A12: 6 | B12: 1 | C12: 2 | D12: Geis | E12: Helene | F12: 7 | G12: 1863 | H12: Female | I12: White | M12: Texas | N12: Yes | O12: Yes | X12: {=SUMPRODUCT(--(INDEX('1870 Bastrop Clean'!A:W, MATCH(A12 & "|" & B12,'1870 Bastrop Clean'!A:A & "|" & '1870 Bastrop Clean'!B:B, 0), 0) <> '1870 Bastrop Raw'!A12:W12))} -> 0
A13: 7 | B13: 1 | C13: 2 | D13: Geis | E13: Henry | F13: 2 | G13: 1868 | H13: Male | I13: White | M13: Texas | N13: Yes | O13: Yes | X13: {=SUMPRODUCT(--(INDEX('1870 Bastrop Clean'!A:W, MATCH(A13 & "|" & B13,'1870 Bastrop Clean'!A:A & "|" & '1870 Bastrop Clean'!B:B, 0), 0) <> '1870 Bastrop Raw'!A13:W13))} -> 0
A14: 10 | B14: 3 | C14: 4 | D14: Wertsner | E14: Chas | F14: 40 | G14: 1830 | H14: Male | I14: White | J14: Merchant & Post M | K14: 1500 | L14: 2000 | M14: Saxonia | N14: Yes | O14: Yes | V14: Yes | X14: {=SUMPRODUCT(--(INDEX('1870 Bastrop Clean'!A:W, MATCH(A14 & "|" & B14,'1870 Bastrop Clean'!A:A & "|" & '1870 Bastrop Clean'!B:B, 0), 0) <> '1870 Bastrop Raw'!A14:W14))} -> 0
A15: 11 | B15: 3 | C15: 4 | D15: Wertsner | E15: Franziska | F15: 31 | G15: 1839 | H15: Female | I15: White | J15: Keeping House | M15: Bohemia | N15: Yes | O15: Yes | X15: {=SUMPRODUCT(--(INDEX('1870 Bastrop Clean'!A:W, MATCH(A15 & "|" & B15,'1870 Bastrop Clean'!A:A & "|" & '1870 Bastrop Clean'!B:B, 0), 0) <> '1870 Bastrop Raw'!A15:W15))} -> 0
A16: 12 | B16: 3 | C16: 4 | D16: Wertsner | E16: Oskar | F16: 11 | G16: 1859 | H16: Male | I16: White | J16: Farmer | M16: Texas | N16: Yes | O16: Yes | R16: Yes | X16: {=SUMPRODUCT(--(INDEX('1870 Bastrop Clean'!A:W, MATCH(A16 & "|" & B16,'1870 Bastrop Clean'!A:A & "|" & '1870 Bastrop Clean'!B:B, 0), 0) <> '1870 Bastrop Raw'!A16:W16))} -> 0
A17: 13 | B17: 3 | C17: 4 | D17: Wertsner | E17: Selma | F17: 7 | G17: 1863 | H17: Female | I17: White | M17: Texas | N17: Yes | O17: Yes | X17: {=SUMPRODUCT(--(INDEX('1870 Bastrop Clean'!A:W, MATCH(A17 & "|" & B17,'1870 Bastrop Clean'!A:A & "|" & '1870 Bastrop Clean'!B:B, 0), 0) <> '1870 Bastrop Raw'!A17:W17))} -> 0
A18: 14 | B18: 3 | C18: 4 | D18: Wertsner | E18: Pauline | F18: 5 | G18: 1865 | H18: Female | I18: White | M18: Texas | N18: Yes | O18: Yes | X18: {=SUMPRODUCT(--(INDEX('1870 Bastrop Clean'!A:W, MATCH(A18 & "|" & B18,'1870 Bastrop Clean'!A:A & "|" & '1870 Bastrop Clean'!B:B, 0), 0) <> '1870 Bastrop Raw'!A18:W18))} -> 0
A19: 15 | B19: 3 | C19: 4 | D19: Wertsner | E19: Elisabeth | H19: Female | I19: White | M19: Texas | N19: Yes | O19: Yes | X19: {=SUMPRODUCT(--(INDEX('1870 Bastrop Clean'!A:W, MATCH(A19 & "|" & B19,'1870 Bastrop Clean'!A:A & "|" & '1870 Bastrop Clean'!B:B, 0), 0) <> '1870 Bastrop Raw'!A19:W19))} -> 2
A20: 16 | B20: 3 | C20: 4 | D20: Hanke | E20: Anna | F20: 19 | G20: 1851 | H20: Female | I20: White | J20: Domestic Servant | M20: Prussia | N20: Yes | O20: Yes | X20: {=SUMPRODUCT(--(INDEX('1870 Bastrop Clean'!A:W, MATCH(A20 & "|" & B20,'1870 Bastrop Clean'!A:A & "|" & '1870 Bastrop Clean'!B:B, 0), 0) <> '1870 Bastrop Raw'!A20:W20))} -> 1
A21: 17 | B21: 3 | C21: 4 | D21: Hopler | E21: John | F21: 53 | G21: 1817 | H21: Male | I21: White | J21: Domestic Servant | M21: Mecklenburg | N21: Yes | O21: Yes | V21: Yes | X21: {=SUMPRODUCT(--(INDEX('1870 Bastrop Clean'!A:W, MATCH(A21 & "|" & B21,'1870 Bastrop Clean'!A:A & "|" & '1870 Bastrop Clean'!B:B, 0), 0) <> '1870 Bastrop Raw'!A21:W21))} -> 1
A22: 18 | B22: 3 | C22: 4 | D22: Woehl | E22: Joseph | F22: 16 | G22: 1854 | H22: Male | I22: White | J22: Clerk In Store | M22: Texas | N22: Yes | O22: Yes | X22: {=SUMPRODUCT(--(INDEX('1870 Bastrop Clean'!A:W, MATCH(A22 & "|" & B22,'1870 Bastrop Clean'!A:A & "|" & '1870 Bastrop Clean'!B:B, 0), 0) <> '1870 Bastrop Raw'!A22:W22))} -> 1
A23: 19 | B23: 4 | C23: 5 | D23: Glockner | E23: Moritz | F23: 57 | G23: 1813 | H23: Male | I23: White | J23: Baker & Mercha | K23: 2000 | L23: 1000 | M23: Bohemia | N23: Yes | O23: Yes | V23: Yes | X23: {=SUMPRODUCT(--(INDEX('1870 Bastrop Clean'!A:W, MATCH(A23 & "|" & B23,'1870 Bastrop Clean'!A:A & "|" & '1870 Bastrop Clean'!B:B, 0), 0) <> '1870 Bastrop Raw'!A23:W23))} -> 0
A24: 20 | B24: 4 | C24: 5 | D24: Glockner | E24: Solovia | F24: 34 | G24: 1836 | H24: Female | I24: White | J24: Keeping House | M24: Bohemia | N24: Yes | O24: Yes | X24: {=SUMPRODUCT(--(INDEX('1870 Bastrop Clean'!A:W, MATCH(A24 & "|" & B24,'1870 Bastrop Clean'!A:A & "|" & '1870 Bastrop Clean'!B:B, 0), 0) <> '1870 Bastrop Raw'!A24:W24))} -> 0
A25: 21 | B25: 4 | C25: 5 | D25: Glockner | E25: Salonia | F25: 13 | G25: 1857 | H25: Female | I25: White | M25: Texas | N25: Yes | O25: Yes | R25: Yes | X25: {=SUMPRODUCT(--(INDEX('1870 Bastrop Clean'!A:W, MATCH(A25 & "|" & B25,'1870 Bastrop Clean'!A:A & "|" & '1870 Bastrop Clean'!B:B, 0), 0) <> '1870 Bastrop Raw'!A25:W25))} -> 0
A26: 22 | B26: 4 | C26: 5 | D26: Glockner | E26: Joseph | F26: 10 | G26: 1860 | H26: Male | I26: White | M26: Texas | N26: Yes | O26: Yes | R26: Yes | X26: {=SUMPRODUCT(--(INDEX('1870 Bastrop Clean'!A:W, MATCH(A26 & "|" & B26,'1870 Bastrop Clean'!A:A & "|" & '1870 Bastrop Clean'!B:B, 0), 0) <> '1870 Bastrop Raw'!A26:W26))} -> 0
A27: 23 | B27: 4 | C27: 5 | D27: Glockner | E27: Tracy | F27: 8 | G27: 1862 | H27: Male | I27: White | M27: Texas | N27: Yes | O27: Yes | R27: Yes | X27: {=SUMPRODUCT(--(INDEX('1870 Bastrop Clean'!A:W, MATCH(A27 & "|" & B27,'1870 Bastrop Clean'!A:A & "|" & '1870 Bastrop Clean'!B:B, 0), 0) <> '1870 Bastrop Raw'!A27:W27))} -> 0
A28: 24 | B28: 4 | C28: 5 | D28: Glockner | E28: Anton | H28: Male | I28: White | M28: Texas | N28: Yes | O28: Yes | X28: {=SUMPRODUCT(--(INDEX('1870 Bastrop Clean'!A:W, MATCH(A28 & "|" & B28,'1870 Bastrop Clean'!A:A & "|" & '1870 Bastrop Clean'!B:B, 0), 0) <> '1870 Bastrop Raw'!A28:W28))} -> 2
A29: 25 | B29: 4 | C29: 5 | D29: Glockner | E29: William | F29: 45820 | H29: Male | I29: White | M29: Texas | N29: Yes | O29: Yes | P29: Feb | X29: {=SUMPRODUCT(--(INDEX('1870 Bastrop Clean'!A:W, MATCH(A29 & "|" & B29,'1870 Bastrop Clean'!A:A & "|" & '1870 Bastrop Clean'!B:B, 0), 0) <> '1870 Bastrop Raw'!A29:W29))} -> 1
A30: 26 | B30: 5 | C30: 6 | D30: Spifer | E30: George | F30: 24 | G30: 1846 | H30: Male | I30: White | J30: Sadler & Harness | K30: 500 | M30: Hesse-Darmstadt / Hessen-Darmstadt | N30: Yes | O30: Yes | V30: Yes | X30: {=SUMPRODUCT(--(INDEX('1870 Bastrop Clean'!A:W, MATCH(A30 & "|" & B30,'1870 Bastrop Clean'!A:A & "|" & '1870 Bastrop Clean'!B:B, 0), 0) <> '1870 Bastrop Raw'!A30:W30))} -> 0
A31: 27 | B31: 5 | C31: 6 | D31: Spifer | E31: Antonia | H31: Female | I31: White | J31: Keeping House | M31: Bohemia | N31: Yes | O31: Yes | X31: {=SUMPRODUCT(--(INDEX('1870 Bastrop Clean'!A:W, MATCH(A31 & "|" & B31,'1870 Bastrop Clean'!A:A & "|" & '1870 Bastrop Clean'!B:B, 0), 0) <> '1870 Bastrop Raw'!A31:W31))} -> 2
A32: 28 | B32: 5 | C32: 6 | D32: Stelzig | E32: Anton | H32: Male | I32: White | J32: Apprent To Saw | M32: Bohemia | N32: Yes | O32: Yes | X32: {=SUMPRODUCT(--(INDEX('1870 Bastrop Clean'!A:W, MATCH(A32 & "|" & B32,'1870 Bastrop Clean'!A:A & "|" & '1870 Bastrop Clean'!B:B, 0), 0) <> '1870 Bastrop Raw'!A32:W32))} -> 3
A33: 32 | B33: 7 | C33: 8 | D33: Spittler | E33: N M | F33: 37 | G33: 1833 | H33: Male | I33: White | J33: Farmer & Dik Co | K33: 1500 | L33: 500 | M33: Indiana | N33: Yes | V33: Yes | X33: {=SUMPRODUCT(--(INDEX('1870 Bastrop Clean'!A:W, MATCH(A33 & "|" & B33,'1870 Bastrop Clean'!A:A & "|" & '1870 Bastrop Clean'!B:B, 0), 0) <> '1870 Bastrop Raw'!A33:W33))} -> 0
A34: 33 | B34: 7 | C34: 8 | D34: Spittler | E34: Sarah | F34: 33 | G34: 1837 | H34: Female | I34: White | J34: Keeping House | M34: Texas | X34: {=SUMPRODUCT(--(INDEX('1870 Bastrop Clean'!A:W, MATCH(A34 & "|" & B34,'1870 Bastrop Clean'!A:A & "|" & '1870 Bastrop Clean'!B:B, 0), 0) <> '1870 Bastrop Raw'!A34:W34))} -> 0
A35: 34 | B35: 7 | C35: 8 | D35: Spittler | E35: Jos M | F35: 11 | G35: 1859 | H35: Male | I35: White | M35: Texas | R35: Yes | X35: {=SUMPRODUCT(--(INDEX('1870 Bastrop Clean'!A:W, MATCH(A35 & "|" & B35,'1870 Bastrop Clean'!A:A & "|" & '1870 Bastrop Clean'!B:B, 0), 0) <> '1870 Bastrop Raw'!A35:W35))} -> 0
A36: 35 | B36: 7 | C36: 8 | D36: Spittler | E36: Florence | F36: 9 | G36: 1861 | H36: Female | I36: White | M36: Texas | R36: Yes | X36: {=SUMPRODUCT(--(INDEX('1870 Bastrop Clean'!A:W, MATCH(A36 & "|" & B36,'1870 Bastrop Clean'!A:A & "|" & '1870 Bastrop Clean'!B:B, 0), 0) <> '1870 Bastrop Raw'!A36:W36))} -> 0
A37: 36 | B37: 7 | C37: 8 | D37: Spittler | E37: Allen | F37: 6 | G37: 1864 | H37: Male | I37: White | M37: Texas | X37: {=SUMPRODUCT(--(INDEX('1870 Bastrop Clean'!A:W, MATCH(A37 & "|" & B37,'1870 Bastrop Clean'!A:A & "|" & '1870 Bastrop Clean'!B:B, 0), 0) <> '1870 Bastrop Raw'!A37:W37))} -> 0
A38: 37 | B38: 7 | C38: 8 | D38: Spittler | E38: W M | F38: 2 | G38: 1868 | H38: Male | I38: White | M38: Texas | X38: {=SUMPRODUCT(--(INDEX('1870 Bastrop Clean'!A:W, MATCH(A38 & "|" & B38,'1870 Bastrop Clean'!A:A & "|" & '1870 Bastrop Clean'!B:B, 0), 0) <> '1870 Bastrop Raw'!A38:W38))} -> 0
A39: 38 | B39: 7 | C39: 8 | D39: Sneed | E39: Cyntah | F39: 35 | G39: 1835 | H39: Female | I39: Black | J39: Domestic Servant | M39: Georgia | S39: Yes | T39: Yes | X39: {=SUMPRODUCT(--(INDEX('1870 Bastrop Clean'!A:W, MATCH(A39 & "|" & B39,'1870 Bastrop Clean'!A:A & "|" & '1870 Bastrop Clean'!B:B, 0), 0) <> '1870 Bastrop Raw'!A39:W39))} -> 2
A40: 39 | B40: 7 | C40: 8 | D40: Wilkins | E40: Haney | F40: 53 | G40: 1817 | H40: Female | I40: Black | J40: Farm Laborer | M40: Alabama | S40: Yes | T40: Yes | X40: {=SUMPRODUCT(--(INDEX('1870 Bastrop Clean'!A:W, MATCH(A40 & "|" & B40,'1870 Bastrop Clean'!A:A & "|" & '1870 Bastrop Clean'!B:B, 0), 0) <> '1870 Bastrop Raw'!A40:W40))} -> 2
A41: 40 | B41: 7 | C41: 8 | D41: Wilkins | E41: Thom | F41: 9 | G41: 1861 | H41: Female | I41: Black | M41: Texas | X41: {=SUMPRODUCT(--(INDEX('1870 Bastrop Clean'!A:W, MATCH(A41 & "|" & B41,'1870 Bastrop Clean'!A:A & "|" & '1870 Bastrop Clean'!B:B, 0), 0) <> '1870 Bastrop Raw'!A41:W41))} -> 2
A42: 13 | B42: 10 | C42: 11 | D42: Krause | E42: Ward | F42: 45 | G42: 1825 | H42: Male | I42: White | J42: Wheelwright | K42: 800 | M42: Hesse-Kassel / Hessen-Kassel / Electorate of Hesse / Kurhessen | N42: Yes | O42: Yes | V42: Yes | X42: {=SUMPRODUCT(--(INDEX('1870 Bastrop Clean'!A:W, MATCH(A42 & "|" & B42,'1870 Bastrop Clean'!A:A & "|" & '1870 Bastrop Clean'!B:B, 0), 0) <> '1870 Bastrop Raw'!A42:W42))} -> 0
A43: 14 | B43: 10 | C43: 11 | D43: Krause | E43: Anna | F43: 30 | G43: 1840 | H43: Female | I43: White | J43: Keeping House | M43: Bohemia | N43: Yes | O43: Yes | X43: {=SUMPRODUCT(--(INDEX('1870 Bastrop Clean'!A:W, MATCH(A43 & "|" & B43,'1870 Bastrop Clean'!A:A & "|" & '1870 Bastrop Clean'!B:B, 0), 0) <> '1870 Bastrop Raw'!A43:W43))} -> 0
A44: 15 | B44: 10 | C44: 11 | D44: Krause | E44: Lisette | F44: 7 | G44: 1863 | H44: Female | I44: White | M44: Texas | X44: {=SUMPRODUCT(--(INDEX('1870 Bastrop Clean'!A:W, MATCH(A44 & "|" & B44,'1870 Bastrop Clean'!A:A & "|" & '1870 Bastrop Clean'!B:B, 0), 0) <> '1870 Bastrop Raw'!A44:W44))} -> 0
A45: 16 | B45: 10 | C45: 11 | D45: Krause | E45: Sarah | F45: 5 | G45: 1865 | H45: Female | I45: White | M45: Texas | X45: {=SUMPRODUCT(--(INDEX('1870 Bastrop Clean'!A:W, MATCH(A45 & "|" & B45,'1870 Bastrop Clean'!A:A & "|" & '1870 Bastrop Clean'!B:B, 0), 0) <> '1870 Bastrop Raw'!A45:W45))} -> 0
A46: 17 | B46: 10 | C46: 11 | D46: Krause | E46: Otto | F46: 4 | G46: 1866 | H46: Male | I46: White | M46: Texas | X46: {=SUMPRODUCT(--(INDEX('1870 Bastrop Clean'!A:W, MATCH(A46 & "|" & B46,'1870 Bastrop Clean'!A:A & "|" & '1870 Bastrop Clean'!B:B, 0), 0) <> '1870 Bastrop Raw'!A46:W46))} -> 0
A47: 18 | B47: 10 | C47: 11 | D47: Schneider | E47: Helene | F47: 16 | G47: 1854 | H47: Female | I47: White | J47: Milliner | M47: Bohemia | N47: Yes | O47: Yes | X47: {=SUMPRODUCT(--(INDEX('1870 Bastrop Clean'!A:W, MATCH(A47 & "|" & B47,'1870 Bastrop Clean'!A:A & "|" & '1870 Bastrop Clean'!B:B, 0), 0) <> '1870 Bastrop Raw'!A47:W47))} -> 0
A48: 19 | B48: 10 | C48: 11 | D48: Emmert | E48: Garland | F48: 16 | G48: 1854 | H48: Male | I48: White | J48: Apprent To Wheelw | M48: Hesse-Darmstadt / Hessen-Darmstadt | N48: Yes | O48: Yes | X48: {=SUMPRODUCT(--(INDEX('1870 Bastrop Clean'!A:W, MATCH(A48 & "|" & B48,'1870 Bastrop Clean'!A:A & "|" & '1870 Bastrop Clean'!B:B, 0), 0) <> '1870 Bastrop Raw'!A48:W48))} -> 0
A49: 20 | B49: 11 | C49: 12 | D49: Prokop | E49: B | F49: 39 | G49: 1831 | H49: Male | I49: White | J49: Watchmaker | K49: 800 | L49: 200 | M49: Bohemia | N49: Yes | O49: Yes | S49: Yes | V49: Yes | X49: {=SUMPRODUCT(--(INDEX('1870 Bastrop Clean'!A:W, MATCH(A49 & "|" & B49,'1870 Bastrop Clean'!A:A & "|" & '1870 Bastrop Clean'!B:B, 0), 0) <> '1870 Bastrop Raw'!A49:W49))} -> 0
A50: 21 | B50: 11 | C50: 12 | D50: Prokop | E50: Celestine | F50: 13 | G50: 1857 | H50: Female | I50: White | M50: Texas | N50: Yes | O50: Yes | X50: {=SUMPRODUCT(--(INDEX('1870 Bastrop Clean'!A:W, MATCH(A50 & "|" & B50,'1870 Bastrop Clean'!A:A & "|" & '1870 Bastrop Clean'!B:B, 0), 0) <> '1870 Bastrop Raw'!A50:W50))} -> 0
A51: 22 | B51: 11 | C51: 12 | D51: Prokop | E51: Emil | F51: 11 | G51: 1859 | H51: Male | I51: White | M51: Texas | N51: Yes | O51: Yes | X51: {=SUMPRODUCT(--(INDEX('1870 Bastrop Clean'!A:W, MATCH(A51 & "|" & B51,'1870 Bastrop Clean'!A:A & "|" & '1870 Bastrop Clean'!B:B, 0), 0) <> '1870 Bastrop Raw'!A51:W51))} -> 0
A52: 23 | B52: 12 | C52: 13 | D52: Fehr | E52: William | F52: 27 | G52: 1843 | H52: Male | I52: White | J52: Cabinet Maker | K52: 300 | M52: Holstein | N52: Yes | O52: Yes | V52: Yes | X52: {=SUMPRODUCT(--(INDEX('1870 Bastrop Clean'!A:W, MATCH(A52 & "|" & B52,'1870 Bastrop Clean'!A:A & "|" & '1870 Bastrop Clean'!B:B, 0), 0) <> '1870 Bastrop Raw'!A52:W52))} -> 0
A53: 24 | B53: 12 | C53: 13 | D53: Buchmeier | E53: Chas | F53: 28 | G53: 1842 | H53: Male | I53: White | J53: Cabinet Maker | M53: Baden | N53: Yes | O53: Yes | X53: {=SUMPRODUCT(--(INDEX('1870 Bastrop Clean'!A:W, MATCH(A53 & "|" & B53,'1870 Bastrop Clean'!A:A & "|" & '1870 Bastrop Clean'!B:B, 0), 0) <> '1870 Bastrop Raw'!A53:W53))} -> 0
A54: 1 | B54: 8 | C54: 9 | D54: Rein | E54: George B | F54: 49 | G54: 1821 | H54: Male | I54: White | J54: Baker & Farmer | K54: 600 | L54: 400 | M54: Hesse-Kassel / Hessen-Kassel / Electorate of Hesse / Kurhessen | N54: Yes | O54: Yes | V54: Yes | X54: {=SUMPRODUCT(--(INDEX('1870 Bastrop Clean'!A:W, MATCH(A54 & "|" & B54,'1870 Bastrop Clean'!A:A & "|" & '1870 Bastrop Clean'!B:B, 0), 0) <> '1870 Bastrop Raw'!A54:W54))} -> 0
A55: 2 | B55: 8 | C55: 9 | D55: Rein | E55: Therese | F55: 43 | G55: 1827 | H55: Female | I55: White | J55: Keeping House | M55: Prussia | N55: Yes | O55: Yes | X55: {=SUMPRODUCT(--(INDEX('1870 Bastrop Clean'!A:W, MATCH(A55 & "|" & B55,'1870 Bastrop Clean'!A:A & "|" & '1870 Bastrop Clean'!B:B, 0), 0) <> '1870 Bastrop Raw'!A55:W55))} -> 0
A56: 3 | B56: 8 | C56: 9 | D56: Rein | E56: Julia | F56: 14 | G56: 1856 | H56: Female | I56: White | M56: Texas | N56: Yes | O56: Yes | R56: Yes | X56: {=SUMPRODUCT(--(INDEX('1870 Bastrop Clean'!A:W, MATCH(A56 & "|" & B56,'1870 Bastrop Clean'!A:A & "|" & '1870 Bastrop Clean'!B:B, 0), 0) <> '1870 Bastrop Raw'!A56:W56))} -> 0
A57: 4 | B57: 8 | C57: 9 | D57: Rein | E57: Helena | F57: 12 | G57: 1858 | H57: Female | I57: White | M57: Texas | N57: Yes | O57: Yes | R57: Yes | X57: {=SUMPRODUCT(--(INDEX('1870 Bastrop Clean'!A:W, MATCH(A57 & "|" & B57,'1870 Bastrop Clean'!A:A & "|" & '1870 Bastrop Clean'!B:B, 0), 0) <> '1870 Bastrop Raw'!A57:W57))} -> 0
A58: 5 | B58: 8 | C58: 9 | D58: Rein | E58: Emma | F58: 10 | G58: 1860 | H58: Female | I58: White | M58: Texas | N58: Yes | O58: Yes | R58: Yes | X58: {=SUMPRODUCT(--(INDEX('1870 Bastrop Clean'!A:W, MATCH(A58 & "|" & B58,'1870 Bastrop Clean'!A:A & "|" & '1870 Bastrop Clean'!B:B, 0), 0) <> '1870 Bastrop Raw'!A58:W58))} -> 0
A59: 6 | B59: 8 | C59: 9 | D59: Rein | E59: John | F59: 8 | G59: 1862 | H59: Male | I59: White | M59: Texas | N59: Yes | O59: Yes | R59: Yes | X59: {=SUMPRODUCT(--(INDEX('1870 Bastrop Clean'!A:W, MATCH(A59 & "|" & B59,'1870 Bastrop Clean'!A:A & "|" & '1870 Bastrop Clean'!B:B, 0), 0) <> '1870 Bastrop Raw'!A59:W59))} -> 0
A60: 7 | B60: 8 | C60: 9 | D60: Rein | E60: Therese | F60: 6 | G60: 1864 | H60: Female | I60: White | M60: Texas | N60: Yes | O60: Yes | X60: {=SUMPRODUCT(--(INDEX('1870 Bastrop Clean'!A:W, MATCH(A60 & "|" & B60,'1870 Bastrop Clean'!A:A & "|" & '1870 Bastrop Clean'!B:B, 0), 0) <> '1870 Bastrop Raw'!A60:W60))} -> 0
A61: 8 | B61: 8 | C61: 9 | D61: Rein | E61: Bertha | F61: 4 | G61: 1866 | H61: Female | I61: White | M61: Texas | N61: Yes | O61: Yes | X61: {=SUMPRODUCT(--(INDEX('1870 Bastrop Clean'!A:W, MATCH(A61 & "|" & B61,'1870 Bastrop Clean'!A:A & "|" & '1870 Bastrop Clean'!B:B, 0), 0) <> '1870 Bastrop Raw'!A61:W61))} -> 0
A62: 25 | B62: 13 | C62: 14 | D62: Marr | E62: Hugh | F62: 47 | G62: 1823 | H62: Male | I62: White | J62: Builder | K62: 1000 | M62: New York | N62: Yes | O62: Yes | V62: Yes | X62: {=SUMPRODUCT(--(INDEX('1870 Bastrop Clean'!A:W, MATCH(A62 & "|" & B62,'1870 Bastrop Clean'!A:A & "|" & '1870 Bastrop Clean'!B:B, 0), 0) <> '1870 Bastrop Raw'!A62:W62))} -> 0
A63: 26 | B63: 13 | C63: 14 | D63: Marr | E63: Mary L | F63: 30 | G63: 1840 | H63: Female | I63: White | J63: Keeping House | K63: 600 | M63: Texas | N63: Yes | X63: {=SUMPRODUCT(--(INDEX('1870 Bastrop Clean'!A:W, MATCH(A63 & "|" & B63,'1870 Bastrop Clean'!A:A & "|" & '1870 Bastrop Clean'!B:B, 0), 0) <> '1870 Bastrop Raw'!A63:W63))} -> 0
A64: 27 | B64: 13 | C64: 14 | D64: Marr | E64: Cyrus H | F64: 17 | G64: 1853 | H64: Male | I64: White | J64: At Home | M64: Mississippi | X64: {=SUMPRODUCT(--(INDEX('1870 Bastrop Clean'!A:W, MATCH(A64 & "|" & B64,'1870 Bastrop Clean'!A:A & "|" & '1870 Bastrop Clean'!B:B, 0), 0) <> '1870 Bastrop Raw'!A64:W64))} -> 0
A65: 28 | B65: 13 | C65: 14 | D65: Marr | E65: Georgina | F65: 15 | G65: 1855 | H65: Female | I65: White | M65: Texas | R65: Yes | X65: {=SUMPRODUCT(--(INDEX('1870 Bastrop Clean'!A:W, MATCH(A65 & "|" & B65,'1870 Bastrop Clean'!A:A & "|" & '1870 Bastrop Clean'!B:B, 0), 0) <> '1870 Bastrop Raw'!A65:W65))} -> 0
A66: 29 | B66: 13 | C66: 14 | D66: Marr | E66: Sam W | F66: 13 | G66: 1857 | H66: Male | I66: White | M66: Texas | R66: Yes | X66: {=SUMPRODUCT(--(INDEX('1870 Bastrop Clean'!A:W, MATCH(A66 & "|" & B66,'1870 Bastrop Clean'!A:A & "|" & '1870 Bastrop Clean'!B:B, 0), 0) <> '1870 Bastrop Raw'!A66:W66))} -> 0
A67: 30 | B67: 13 | C67: 14 | D67: Marr | E67: Georg T | F67: 9 | G67: 1861 | H67: Male | I67: White | M67: Texas | X67: {=SUMPRODUCT(--(INDEX('1870 Bastrop Clean'!A:W, MATCH(A67 & "|" & B67,'1870 Bastrop Clean'!A:A & "|" & '1870 Bastrop Clean'!B:B, 0), 0) <> '1870 Bastrop Raw'!A67:W67))} -> 0
A68: 31 | B68: 13 | C68: 14 | D68: Marr | E68: Anna | F68: 6 | G68: 1864 | H68: Female | I68: White | M68: Texas | X68: {=SUMPRODUCT(--(INDEX('1870 Bastrop Clean'!A:W, MATCH(A68 & "|" & B68,'1870 Bastrop Clean'!A:A & "|" & '1870 Bastrop Clean'!B:B, 0), 0) <> '1870 Bastrop Raw'!A68:W68))} -> 0
A69: 32 | B69: 13 | C69: 14 | D69: Morrais | E69: Alice | F69: 22 | G69: 1848 | H69: Female | I69: White | J69: At Home | M69: Texas | X69: {=SUMPRODUCT(--(INDEX('1870 Bastrop Clean'!A:W, MATCH(A69 & "|" & B69,'1870 Bastrop Clean'!A:A & "|" & '1870 Bastrop Clean'!B:B, 0), 0) <> '1870 Bastrop Raw'!A69:W69))} -> 0
A70: 33 | B70: 14 | C70: 15 | D70: Shepperth | E70: Fan | F70: 60 | G70: 1810 | H70: Male | I70: White | J70: Machinist Carp | K70: 800 | M70: Kentucky | V70: Yes | X70: {=SUMPRODUCT(--(INDEX('1870 Bastrop Clean'!A:W, MATCH(A70 & "|" & B70,'1870 Bastrop Clean'!A:A & "|" & '1870 Bastrop Clean'!B:B, 0), 0) <> '1870 Bastrop Raw'!A70:W70))} -> 0
A71: 34 | B71: 14 | C71: 15 | D71: Sanders | E71: Lotte | F71: 35 | G71: 1835 | H71: Female | I71: Black | J71: Keeping House | M71: Alabama | S71: Yes | T71: Yes | U71: Blind | X71: {=SUMPRODUCT(--(INDEX('1870 Bastrop Clean'!A:W, MATCH(A71 & "|" & B71,'1870 Bastrop Clean'!A:A & "|" & '1870 Bastrop Clean'!B:B, 0), 0) <> '1870 Bastrop Raw'!A71:W71))} -> 1
A72: 35 | B72: 14 | C72: 15 | D72: Hargrave | E72: Lotte | F72: 12 | G72: 1858 | H72: Female | I72: Mulatto | M72: Louisiana | R72: Yes | X72: {=SUMPRODUCT(--(INDEX('1870 Bastrop Clean'!A:W, MATCH(A72 & "|" & B72,'1870 Bastrop Clean'!A:A & "|" & '1870 Bastrop Clean'!B:B, 0), 0) <> '1870 Bastrop Raw'!A72:W72))} -> 0
A73: 36 | B73: 15 | C73: 16 | D73: Brieger | E73: Charls | F73: 33 | G73: 1837 | H73: Male | I73: White | J73: Taylor | M73: Prussia | N73: Yes | O73: Yes | V73: Yes | X73: {=SUMPRODUCT(--(INDEX('1870 Bastrop Clean'!A:W, MATCH(A73 & "|" & B73,'1870 Bastrop Clean'!A:A & "|" & '1870 Bastrop Clean'!B:B, 0), 0) <> '1870 Bastrop Raw'!A73:W73))} -> 0
A74: 37 | B74: 15 | C74: 16 | D74: Brieger | E74: Maria | F74: 25 | G74: 1845 | H74: Female | I74: White | J74: Keeping House | M74: Nassau | N74: Yes | O74: Yes | X74: {=SUMPRODUCT(--(INDEX('1870 Bastrop Clean'!A:W, MATCH(A74 & "|" & B74,'1870 Bastrop Clean'!A:A & "|" & '1870 Bastrop Clean'!B:B, 0), 0) <> '1870 Bastrop Raw'!A74:W74))} -> 0
A75: 38 | B75: 15 | C75: 16 | D75: Brieger | E75: Charles | F75: 7 | G75: 1863 | H75: Male | I75: White | M75: Texas | N75: Yes | O75: Yes | R75: Yes | X75: {=SUMPRODUCT(--(INDEX('1870 Bastrop Clean'!A:W, MATCH(A75 & "|" & B75,'1870 Bastrop Clean'!A:A & "|" & '1870 Bastrop Clean'!B:B, 0), 0) <> '1870 Bastrop Raw'!A75:W75))} -> 0
A76: 39 | B76: 15 | C76: 16 | D76: Brieger | E76: Willy | F76: 3 | G76: 1867 | H76: Male | I76: White | M76: Texas | N76: Yes | O76: Yes | X76: {=SUMPRODUCT(--(INDEX('1870 Bastrop Clean'!A:W, MATCH(A76 & "|" & B76,'1870 Bastrop Clean'!A:A & "|" & '1870 Bastrop Clean'!B:B, 0), 0) <> '1870 Bastrop Raw'!A76:W76))} -> 0
A77: 40 | B77: 15 | C77: 16 | D77: Brieger | E77: Alberta | H77: Male | I77: White | M77: Texas | N77: Yes | O77: Yes | X77: {=SUMPRODUCT(--(INDEX('1870 Bastrop Clean'!A:W, MATCH(A77 & "|" & B77,'1870 Bastrop Clean'!A:A & "|" & '1870 Bastrop Clean'!B:B, 0), 0) <> '1870 Bastrop Raw'!A77:W77))} -> 2
A78: 9 | B78: 9 | C78: 10 | D78: Gillmoore | E78: M | F78: 45 | G78: 1825 | H78: Male | I78: Black | J78: Blacksmith | K78: 600 | M78: Tennessee | S78: Yes | T78: Yes | U78: Blind | V78: Yes | X78: {=SUMPRODUCT(--(INDEX('1870 Bastrop Clean'!A:W, MATCH(A78 & "|" & B78,'1870 Bastrop Clean'!A:A & "|" & '1870 Bastrop Clean'!B:B, 0), 0) <> '1870 Bastrop Raw'!A78:W78))} -> 1
A79: 10 | B79: 9 | C79: 10 | D79: Gillmoore | E79: Anna | F79: 42 | G79: 1828 | H79: Female | I79: Mulatto | J79: Keeping House | M79: Kentucky | T79: Yes | U79: Blind | X79: {=SUMPRODUCT(--(INDEX('1870 Bastrop Clean'!A:W, MATCH(A79 & "|" & B79,'1870 Bastrop Clean'!A:A & "|" & '1870 Bastrop Clean'!B:B, 0), 0) <> '1870 Bastrop Raw'!A79:W79))} -> 1
A80: 11 | B80: 9 | C80: 10 | D80: Anderson | E80: Maria | F80: 16 | G80: 1854 | H80: Female | I80: Mulatto | M80: Kentucky | R80: Yes | X80: {=SUMPRODUCT(--(INDEX('1870 Bastrop Clean'!A:W, MATCH(A80 & "|" & B80,'1870 Bastrop Clean'!A:A & "|" & '1870 Bastrop Clean'!B:B, 0), 0) <> '1870 Bastrop Raw'!A80:W80))} -> 0
A81: 12 | B81: 9 | C81: 10 | D81: Williams | E81: Rob | F81: 24 | G81: 1846 | H81: Male | I81: Mulatto | J81: Day Labourer | M81: Texas | S81: Yes | T81: Yes | V81: Yes | X81: {=SUMPRODUCT(--(INDEX('1870 Bastrop Clean'!A:W, MATCH(A81 & "|" & B81,'1870 Bastrop Clean'!A:A & "|" & '1870 Bastrop Clean'!B:B, 0), 0) <> '1870 Bastrop Raw'!A81:W81))} -> 3
A82: 11 | B82: 17 | C82: 19 | D82: Starcke | E82: Richd | F82: 43 | G82: 1827 | H82: Male | I82: White | J82: Physician Domed | K82: 1000 | L82: 600 | M82: Prussia | N82: Yes | O82: Yes | V82: Yes | X82: {=SUMPRODUCT(--(INDEX('1870 Bastrop Clean'!A:W, MATCH(A82 & "|" & B82,'1870 Bastrop Clean'!A:A & "|" & '1870 Bastrop Clean'!B:B, 0), 0) <> '1870 Bastrop Raw'!A82:W82))} -> 8
A83: 12 | B83: 17 | C83: 19 | D83: Starcke | E83: Auguste | F83: 42 | G83: 1828 | H83: Female | I83: White | J83: Keeping House | M83: Prussia | N83: Yes | O83: Yes | X83: {=SUMPRODUCT(--(INDEX('1870 Bastrop Clean'!A:W, MATCH(A83 & "|" & B83,'1870 Bastrop Clean'!A:A & "|" & '1870 Bastrop Clean'!B:B, 0), 0) <> '1870 Bastrop Raw'!A83:W83))} -> 7
A84: 13 | B84: 17 | C84: 19 | D84: Starcke | E84: Max | F84: 14 | G84: 1856 | H84: Male | I84: White | M84: Texas | N84: Yes | O84: Yes | R84: Yes | X84: {=SUMPRODUCT(--(INDEX('1870 Bastrop Clean'!A:W, MATCH(A84 & "|" & B84,'1870 Bastrop Clean'!A:A & "|" & '1870 Bastrop Clean'!B:B, 0), 0) <> '1870 Bastrop Raw'!A84:W84))} -> 3
A85: 14 | B85: 17 | C85: 19 | D85: Starcke | E85: Richard | F85: 12 | G85: 1858 | H85: Male | I85: White | M85: Texas | N85: Yes | O85: Yes | R85: Yes | X85: {=SUMPRODUCT(--(INDEX('1870 Bastrop Clean'!A:W, MATCH(A85 & "|" & B85,'1870 Bastrop Clean'!A:A & "|" & '1870 Bastrop Clean'!B:B, 0), 0) <> '1870 Bastrop Raw'!A85:W85))} -> 3
A86: 15 | B86: 17 | C86: 19 | D86: Starcke | E86: Georg | F86: 10 | G86: 1860 | H86: Male | I86: White | M86: Texas | N86: Yes | O86: Yes | R86: Yes | X86: {=SUMPRODUCT(--(INDEX('1870 Bastrop Clean'!A:W, MATCH(A86 & "|" & B86,'1870 Bastrop Clean'!A:A & "|" & '1870 Bastrop Clean'!B:B, 0), 0) <> '1870 Bastrop Raw'!A86:W86))} -> 5
A87: 16 | B87: 17 | C87: 19 | D87: Starcke | E87: Elisabeth | F87: 8 | G87: 1862 | H87: Female | I87: White | M87: Texas | N87: Yes | O87: Yes | R87: Yes | S87: Yes | X87: {=SUMPRODUCT(--(INDEX('1870 Bastrop Clean'!A:W, MATCH(A87 & "|" & B87,'1870 Bastrop Clean'!A:A & "|" & '1870 Bastrop Clean'!B:B, 0), 0) <> '1870 Bastrop Raw'!A87:W87))} -> 5
A88: 17 | B88: 17 | C88: 19 | D88: Starcke | E88: Helene | F88: 6 | G88: 1864 | H88: Female | I88: White | M88: Texas | N88: Yes | O88: Yes | X88: {=SUMPRODUCT(--(INDEX('1870 Bastrop Clean'!A:W, MATCH(A88 & "|" & B88,'1870 Bastrop Clean'!A:A & "|" & '1870 Bastrop Clean'!B:B, 0), 0) <> '1870 Bastrop Raw'!A88:W88))} -> 4
A89: 18 | B89: 17 | C89: 19 | D89: Starcke | E89: Egen | F89: 4 | G89: 1866 | H89: Male | I89: White | M89: Texas | N89: Yes | O89: Yes | X89: {=SUMPRODUCT(--(INDEX('1870 Bastrop Clean'!A:W, MATCH(A89 & "|" & B89,'1870 Bastrop Clean'!A:A & "|" & '1870 Bastrop Clean'!B:B, 0), 0) <> '1870 Bastrop Raw'!A89:W89))} -> 10
A90: 19 | B90: 17 | C90: 19 | D90: Futtalow | E90: Lizzie | F90: 16 | G90: 1854 | H90: Female | I90: White | J90: Domest Servant | M90: Kentucky | X90: {=SUMPRODUCT(--(INDEX('1870 Bastrop Clean'!A:W, MATCH(A90 & "|" & B90,'1870 Bastrop Clean'!A:A & "|" & '1870 Bastrop Clean'!B:B, 0), 0) <> '1870 Bastrop Raw'!A90:W90))} -> 9
A91: 30 | B91: 18 | C91: 22 | D91: Hanke | E91: Florian | F91: 43 | G91: 1827 | H91: Male | I91: White | J91: Carpenter | M91: Prussia | N91: Yes | O91: Yes | X91: {=SUMPRODUCT(--(INDEX('1870 Bastrop Clean'!A:W, MATCH(A91 & "|" & B91,'1870 Bastrop Clean'!A:A & "|" & '1870 Bastrop Clean'!B:B, 0), 0) <> '1870 Bastrop Raw'!A91:W91))} -> 5
A92: 31 | B92: 18 | C92: 22 | D92: Hanke | E92: Veronika | F92: 42 | G92: 1828 | H92: Female | I92: White | J92: Keeping House | M92: Prussia | N92: Yes | O92: Yes | X92: {=SUMPRODUCT(--(INDEX('1870 Bastrop Clean'!A:W, MATCH(A92 & "|" & B92,'1870 Bastrop Clean'!A:A & "|" & '1870 Bastrop Clean'!B:B, 0), 0) <> '1870 Bastrop Raw'!A92:W92))} -> 4
A93: 32 | B93: 18 | C93: 22 | D93: Hanke | E93: Eliza | F93: 14 | G93: 1856 | H93: Female | I93: White | M93: Prussia | N93: Yes | O93: Yes | X93: {=SUMPRODUCT(--(INDEX('1870 Bastrop Clean'!A:W, MATCH(A93 & "|" & B93,'1870 Bastrop Clean'!A:A & "|" & '1870 Bastrop Clean'!B:B, 0), 0) <> '1870 Bastrop Raw'!A93:W93))} -> #N/A
A94: 1 | B94: 16 | C94: 17 | D94: Austin | E94: Andre | F94: 50 | G94: 1820 | H94: Male | I94: White | J94: Merch & Lang Prost | L94: 1300 | M94: France | N94: Yes | O94: Yes | X94: {=SUMPRODUCT(--(INDEX('1870 Bastrop Clean'!A:W, MATCH(A94 & "|" & B94,'1870 Bastrop Clean'!A:A & "|" & '1870 Bastrop Clean'!B:B, 0), 0) <> '1870 Bastrop Raw'!A94:W94))} -> 7
A95: 2 | B95: 16 | C95: 17 | D95: Austin | E95: Caroline | F95: 45 | G95: 1825 | H95: Female | I95: White | J95: Keeping House | M95: Poland | N95: Yes | O95: Yes | X95: {=SUMPRODUCT(--(INDEX('1870 Bastrop Clean'!A:W, MATCH(A95 & "|" & B95,'1870 Bastrop Clean'!A:A & "|" & '1870 Bastrop Clean'!B:B, 0), 0) <> '1870 Bastrop Raw'!A95:W95))} -> 4
A96: 3 | B96: 16 | C96: 17 | D96: Austin | E96: Amalia | F96: 16 | G96: 1854 | H96: Female | I96: White | M96: Poland | N96: Yes | O96: Yes | X96: {=SUMPRODUCT(--(INDEX('1870 Bastrop Clean'!A:W, MATCH(A96 & "|" & B96,'1870 Bastrop Clean'!A:A & "|" & '1870 Bastrop Clean'!B:B, 0), 0) <> '1870 Bastrop Raw'!A96:W96))} -> 6
A97: 4 | B97: 16 | C97: 17 | D97: Bothe | E97: Julius | F97: 18 | G97: 1852 | H97: Male | I97: White | J97: Clerk In Grocery | M97: Poland | N97: Yes | O97: Yes | X97: {=SUMPRODUCT(--(INDEX('1870 Bastrop Clean'!A:W, MATCH(A97 & "|" & B97,'1870 Bastrop Clean'!A:A & "|" & '1870 Bastrop Clean'!B:B, 0), 0) <> '1870 Bastrop Raw'!A97:W97))} -> 8
A98: 5 | B98: 16 | C98: 17 | D98: Bothe | E98: Bertha | F98: 11 | G98: 1859 | H98: Female | I98: White | M98: Poland | R98: Yes | X98: {=SUMPRODUCT(--(INDEX('1870 Bastrop Clean'!A:W, MATCH(A98 & "|" & B98,'1870 Bastrop Clean'!A:A & "|" & '1870 Bastrop Clean'!B:B, 0), 0) <> '1870 Bastrop Raw'!A98:W98))} -> 3
A99: 6 | B99: 16 | C99: 17 | D99: Bothe | E99: Warda | F99: 9 | G99: 1861 | H99: Female | I99: White | M99: Poland | R99: Yes | X99: {=SUMPRODUCT(--(INDEX('1870 Bastrop Clean'!A:W, MATCH(A99 & "|" & B99,'1870 Bastrop Clean'!A:A & "|" & '1870 Bastrop Clean'!B:B, 0), 0) <> '1870 Bastrop Raw'!A99:W99))} -> 12
A100: 7 | B100: 16 | C100: 18 | D100: Kleinert | E100: Charl | F100: 47 | G100: 1823 | H100: Male | I100: White | J100: Merchant & Wheelwright | K100: 1600 | M100: Poland | N100: Yes | O100: Yes | V100: Yes | X100: {=SUMPRODUCT(--(INDEX('1870 Bastrop Clean'!A:W, MATCH(A100 & "|" & B100,'1870 Bastrop Clean'!A:A & "|" & '1870 Bastrop Clean'!B:B, 0), 0) <> '1870 Bastrop Raw'!A100:W100))} -> 8
...

Sheet 1880 Bastrop 0008 Clean
A1: Line Number | B1: Dwelling Number | C1: Street | D1: Surname | E1: Given Name | F1: Race | G1: Gender | H1: Age | I1: Birth Month | J1: Birth Year | K1: Relation to Head of House | L1: Marital Status | M1: Married During Census Year | N1: Occupation | O1: Months Not Employed | P1: Sick | Q1: Blind | R1: Deaf and Dumb | S1: Idiotic | T1: Insane | U1: Maimed, Crippled, or Bedridden | V1: Attended School | W1: Cannot Read | X1: Cannot Write | Y1: Birthplace | Z1: Father's Birthplace | AA1: Mother's Birthplace
A2: 1 | B2: 1 | D2: Wertzner | E2: Charles | F2: White | G2: Male | H2: 57 | J2: Abt 1823 | K2: Self (Head) | L2: Married | N2: Merchant | Y2: Saxony | Z2: Saxony | AA2: Saxony
A3: 2 | B3: 1 | D3: Wertzner | E3: Fransisca | F3: White | G3: Female | H3: 42 | J3: Abt 1838 | K3: Wife | L3: Married | N3: Housekeeper | Y3: Bohemia | Z3: Bohemia | AA3: Bohemia
A4: 3 | B4: 1 | D4: Wertzner | E4: Selma | F4: White | G4: Female | H4: 17 | J4: Abt 1863 | K4: Daughter | L4: Single | Y4: Texas | Z4: Saxony | AA4: Bohemia
A5: 4 | B5: 1 | D5: Wertzner | E5: Pauline | F5: White | G5: Female | H5: 15 | J5: Abt 1865 | K5: Daughter | L5: Single | Y5: Texas | Z5: Saxony | AA5: Bohemia
A6: 5 | B6: 1 | D6: Wertzner | E6: Birtha | F6: White | G6: Female | H6: 11 | J6: Abt 1869 | K6: Daughter | L6: Single | Y6: Texas | Z6: Saxony | AA6: Bohemia
A7: 6 | B7: 1 | D7: Wertzner | E7: Louis | F7: White | G7: Male | H7: 9 | J7: Abt 1871 | K7: Son | L7: Single | Y7: Texas | Z7: Saxony | AA7: Bohemia
A8: 7 | B8: =B2 -> 1 | D8: Wertzner | E8: Juliana | F8: White | G8: Female | H8: 7 | J8: Abt 1873 | K8: Daughter | L8: Single | Y8: Texas | Z8: Saxony | AA8: Bohemia
A9: 8 | B9: =B3 -> 1 | D9: Wertzner | E9: Bruno | F9: White | G9: Male | H9: 5 | J9: Abt 1875 | K9: Son | L9: Single | Y9: Texas | Z9: Saxony | AA9: Bohemia
A10: 9 | B10: =B4 -> 1 | D10: Wertzner | E10: Hugo | F10: White | G10: Male | H10: 1 | J10: Abt 1879 | K10: Son | L10: Single | Y10: Texas | Z10: Saxony | AA10: Bohemia
A11: 10 | B11: =B5 -> 1 | D11: Brandt | E11: H. | F11: White | G11: Male | H11: 18 | J11: Abt 1862 | K11: Boarder | L11: Single | N11: Clerk in post office | Y11: Texas | Z11: Prussia | AA11: Prussia
A12: 11 | B12: =B6 -> 1 | D12: Ploger | E12: Gus | F12: White | G12: Male | H12: 19 | J12: Abt 1861 | K12: Boarder | L12: Single | N12: Clerk in store | Y12: Texas | Z12: Prussia | AA12: Hungary
A13: 12 | B13: =B7 -> 1 | D13: Zandon | E13: William | F13: White | G13: Male | H13: 21 | J13: Abt 1859 | K13: Boarder | L13: Single | N13: Clerk in store | Y13: Prussia | Z13: Prussia | AA13: Prussia
A14: 13 | B14: 2 | D14: Gell | E14: Robert | F14: White | G14: Male | H14: 35 | J14: Abt 1845 | K14: Self (Head) | L14: Married | N14: Merchant | Y14: Tennessee | Z14: Tennessee | AA14: Tennessee
A15: 14 | B15: 2 | D15: Gell | E15: Mary J. | F15: White | G15: Female | H15: 33 | J15: Abt 1847 | K15: Wife | L15: Married | N15: Housekeeper | Y15: England | Z15: England | AA15: England
A16: 15 | B16: 2 | D16: Gell | E16: Edner E. | F16: White | G16: Female | H16: 11 | J16: Abt 1869 | K16: Daughter | L16: Single | V16: Y | Y16: Texas | Z16: Tennessee | AA16: England
A17: 16 | B17: 2 | D17: Gell | E17: Robert L. | F17: White | G17: Male | H17: 8 | J17: Abt 1872 | K17: Son | L17: Single | V17: Y | Y17: Texas | Z17: Tennessee | AA17: England
A18: 17 | B18: 2 | D18: Smutfeld | E18: Olga | F18: White | G18: Female | H18: 14 | J18: Abt 1866 | K18: Servant | L18: Single | N18: Cook | Y18: Germany
A19: 18 | B19: 3 | D19: Vogt | E19: Charles | F19: White | G19: Male | H19: 42 | J19: Abt 1838 | K19: Self (Head) | L19: Married | N19: Gunsmith | Y19: Prussia | Z19: Prussia | AA19: Prussia
A20: 19 | B20: 3 | D20: Vogt | E20: Caroline | F20: White | G20: Female | H20: 32 | J20: Abt 1848 | K20: Wife | L20: Married | N20: Housekeeper | Y20: Bohemia | Z20: Bohemia | AA20: Bohemia
A21: 20 | B21: 3 | D21: Vogt | E21: Paul | F21: White | G21: Male | H21: 12 | J21: Abt 1868 | K21: Son | L21: Single | V21: Y | Y21: Texas | Z21: Prussia | AA21: Bohemia
A22: 21 | B22: 3 | D22: Vogt | E22: Anna | F22: White | G22: Female | H22: 9 | J22: Abt 1871 | K22: Daughter | L22: Single | Y22: Texas | Z22: Prussia | AA22: Bohemia
A23: 22 | B23: 3 | D23: Vogt | E23: Maxmilian | F23: White | G23: Male | H23: 7 | J23: Abt 1873 | K23: Son | L23: Single | Y23: Texas | Z23: Prussia | AA23: Bohemia
A24: 23 | B24: 3 | D24: Vogt | E24: Mary | F24: White | G24: Female | H24: 3 | J24: Abt 1877 | K24: Daughter | L24: Single | Y24: Texas | Z24: Prussia | AA24: Bohemia
A25: 24 | B25: 3 | D25: Vogt | E25: Ida | F25: White | G25: Female | H25: 45759 | I25: Feb | J25: Abt 1880 | K25: Daughter | L25: Single | Y25: Texas | Z25: Prussia | AA25: Bohemia
A26: 25 | B26: 4 | D26: Wiseman | E26: Louis | F26: White | G26: Male | H26: 60 | J26: Abt 1820 | K26: Self (Head) | L26: Married | N26: Watchmaker | Y26: Wurtemburg | Z26: Wurttemberg | AA26: Wurtemburg
A27: 26 | B27: 4 | D27: Wiseman | E27: Sophia | F27: White | G27: Female | H27: 57 | J27: Abt 1823 | K27: Wife | L27: Married | N27: Housekeeper | Y27: Hanover | Z27: Germany | AA27: Germany
A28: 27 | B28: 5 | D28: Pranse | E28: Reinhard | F28: White | G28: Male | H28: 39 | J28: Abt 1841 | K28: Self (Head) | L28: Married | N28: Furniture dealer | Y28: Selasia | Z28: Selasia | AA28: Texas
A29: 28 | B29: 5 | D29: Pranse | E29: Augusta | F29: White | G29: Female | H29: 30 | J29: Abt 1850 | K29: Wife | L29: Married | N29: Housekeeper | Y29: Texas | Z29: Selasia | AA29: Selasia
A30: 29 | B30: 5 | D30: Pranse | E30: Anna | F30: White | G30: Female | H30: 9 | J30: Abt 1871 | K30: Daughter | L30: Single | Y30: Texas | Z30: Selasia | AA30: Texas
A31: 30 | B31: 5 | D31: Pranse | E31: Albert | F31: White | G31: Male | H31: 7 | J31: Abt 1873 | K31: Son | L31: Single | Y31: Texas | Z31: Selasia | AA31: Texas
A32: 31 | B32: 5 | D32: Pranse | E32: Martha | F32: White | G32: Female | H32: 5 | J32: Abt 1875 | K32: Daughter | L32: Single | Y32: Texas | Z32: Selasia | AA32: Texas
A33: 32 | B33: 6 | D33: Walter | E33: William | F33: White | G33: Male | H33: 63 | J33: Abt 1817 | K33: Self (Head) | L33: Married | N33: Grocer and Baker | Y33: Prussia | Z33: Prussia | AA33: Prussia
A34: 33 | B34: 6 | D34: Walter | E34: Joanah | F34: White | G34: Female | H34: 60 | J34: Abt 1820 | K34: Wife | L34: Married | N34: Housekeeper | Y34: Prussia | Z34: Holstein | AA34: Holstein
A35: 34 | B35: 7 | D35: Prokoop | E35: M. A. | F35: White | G35: Male | H35: 47 | J35: Abt 1833 | K35: Self (Head) | L35: Married | N35: Shoemaker | Y35: Bohemia | Z35: Bohemia | AA35: Bohemia
A36: 35 | B36: 7 | D36: Prokoop | E36: Anna M. | F36: White | G36: Female | H36: 48 | J36: Abt 1832 | K36: Wife | L36: Married | N36: Housekeeper | Y36: Bohemia | Z36: Bohemia | AA36: Bohemia
A37: 36 | B37: 7 | D37: Prokoop | E37: Frank | F37: White | G37: Male | H37: 19 | J37: Abt 1861 | K37: Son | L37: Single | N37: Apprentice shoemaker | Y37: Texas | Z37: Bohemia | AA37: Bohemia
A38: 37 | B38: 7 | D38: Prokoop | E38: Emeil | F38: White | G38: Male | H38: 15 | J38: Abt 1865 | K38: Son | L38: Single | Y38: Texas | Z38: Bohemia | AA38: Bohemia
A39: 38 | B39: 8 | D39: Keslus | E39: William M. | F39: White | G39: Male | H39: 46 | J39: Abt 1834 | K39: Self (Head) | L39: Married | N39: Tailor | Y39: Prussia | Z39: Prussia | AA39: Prussia
A40: 39 | B40: 8 | D40: Keslus | E40: Anna | F40: White | G40: Female | H40: 30 | J40: Abt 1850 | K40: Wife | L40: Married | N40: Housekeeper | Y40: Bohemia | Z40: Bohemia | AA40: Bohemia
A41: 40 | B41: 8 | D41: Keslus | E41: William | F41: White | G41: Male | H41: 14 | J41: Abt 1866 | K41: Son | L41: Single | V41: Y | Y41: Texas | Z41: Prussia | AA41: Bohemia
A42: 41 | B42: 8 | D42: Keslus | E42: Hugo | F42: White | G42: Male | H42: 10 | J42: Abt 1870 | K42: Son | L42: Single | V42: Y | Y42: Texas | Z42: Prussia | AA42: Bohemia
A43: 42 | B43: 8 | D43: Keslus | E43: Rudolph | F43: White | G43: Male | H43: 9 | J43: Abt 1871 | K43: Son | L43: Single | Y43: Texas | Z43: Prussia | AA43: Bohemia
A44: 43 | B44: 8 | D44: Keslus | E44: Hellena | F44: White | G44: Female | H44: 4 | J44: Abt 1876 | K44: Daughter | L44: Single | Y44: Texas | Z44: Prussia | AA44: Bohemia
A45: 44 | B45: 8 | D45: Keslus | E45: Hadee | F45: White | G45: Female | H45: 2 | J45: Abt 1878 | K45: Daughter | L45: Single | Y45: Texas | Z45: Prussia | AA45: Bohemia
A46: 45 | B46: 8 | D46: Keslus | E46: Artalia | F46: White | G46: Female | H46: 45789 | J46: Abt 1880 | K46: Daughter | L46: Single | Y46: Texas | Z46: Prussia | AA46: Bohemia
A47: 46 | B47: 9 | D47: Lea | E47: D. C. | F47: White | G47: Male | H47: 39 | J47: Abt 1841 | K47: Self (Head) | L47: Married | N47: Dentist | Y47: Mississippi | AA47: Indiana
A48: 47 | B48: 9 | D48: Lea | E48: Ortalia | F48: White | G48: Female | H48: 20 | J48: Abt 1860 | K48: Wife | L48: Married | N48: Housekeeper | Y48: Texas | Z48: Wurtemburg | AA48: Holland
A49: 48 | B49: 9 | D49: Lea | E49: Maud | F49: White | G49: Female | H49: 45881 | I49: Sep | J49: Abt 1879 | K49: Daughter | L49: Single | Y49: Texas | Z49: Mississippi | AA49: Texas
A50: 1 | B50: 10 | D50: Meller | E50: William | F50: White | G50: Male | H50: 48 | J50: Abt 1832 | K50: Self (Head) | L50: Married | N50: Barber | Y50: Bavaria | Z50: Bavaria | AA50: Bavaria
A51: 2 | B51: 10 | D51: Meller | E51: Hellena | F51: White | G51: Female | H51: 38 | J51: Abt 1842 | K51: Wife | L51: Married | N51: Housekeeper | Y51: Wurtemburg | Z51: Wurtemburg | AA51: Wurtemburg
A52: 3 | B52: 10 | D52: Meller | E52: Antonia | F52: White | G52: Female | H52: 18 | J52: Abt 1862 | K52: Daughter | L52: Single | Y52: Texas | Z52: Bavaria | AA52: Wurtemburg
A53: 4 | B53: 10 | D53: Meller | E53: Anna | F53: White | G53: Female | H53: 16 | J53: Abt 1864 | K53: Daughter | L53: Single | V53: Y | Y53: Texas | Z53: Bavaria | AA53: Wurtemburg
A54: 5 | B54: 10 | D54: Meller | E54: Julia | F54: White | G54: Female | H54: 12 | J54: Abt 1868 | K54: Daughter | L54: Single | V54: Y | Y54: Texas | Z54: Bavaria | AA54: Wurtemburg
A55: 6 | B55: 10 | D55: Meller | E55: Willie | F55: White | G55: Male | H55: 10 | J55: Abt 1870 | K55: Son | L55: Single | V55: Y | Y55: Texas | Z55: Bavaria | AA55: Wurtemburg
A56: 7 | B56: 10 | D56: Meller | E56: George | F56: White | G56: Male | H56: 8 | J56: Abt 1872 | K56: Son | L56: Single | Y56: Texas | Z56: Bavaria | AA56: Wurtemburg
A57: 8 | B57: 10 | D57: Meller | E57: Arnold | F57: White | G57: Male | H57: 3 | J57: Abt 1877 | K57: Son | L57: Single | Y57: Texas | Z57: Bavaria | AA57: Wurtemburg
A58: 9 | B58: 10 | D58: Meller | E58: Fritz | F58: White | G58: Male | H58: 45820 | I58: Oct | J58: Abt 1880 | K58: Son | L58: Single | Y58: Texas | Z58: Bavaria | AA58: Wurtemburg
A59: 10 | B59: 11 | D59: Fuest | E59: L. R. | F59: White | G59: Male | H59: 27 | J59: Abt 1853 | K59: Self (Head) | L59: Married | N59: Merchant | Y59: Texas | Z59: Wurtemburg | AA59: Holland
A60: 11 | B60: 11 | D60: Fuest | E60: Fannie | F60: White | G60: Female | H60: 21 | J60: Abt 1859 | K60: Wife | L60: Married | N60: Housekeeper | Y60: England | Z60: England | AA60: England
A61: 12 | B61: 11 | D61: Fuest | E61: Leo R. | F61: White | G61: Male | H61: 45850 | I61: Oct | J61: Abt 1879 | K61: Son | L61: Single | Y61: Texas | Z61: Texas | AA61: England
A62: 13 | B62: 12 | D62: Nettle | E62: A. | F62: White | G62: Male | H62: 56 | J62: Abt 1824 | K62: Self (Head) | L62: Married | N62: Shoemaker | Y62: Selasia | Z62: Selasia | AA62: Selasia
A63: 14 | B63: 12 | D63: Nettle | E63: Ida | F63: White | G63: Female | H63: 52 | J63: Abt 1828 | K63: Wife | L63: Married | N63: Housekeeper | Y63: Pomeme | Z63: Pomeme | AA63: Pomeme
A64: 15 | B64: 12 | D64: Nettle | E64: Alois | F64: White | G64: Male | H64: 23 | J64: Abt 1857 | K64: Son | L64: Single | N64: Shoemaker | Y64: Texas | Z64: Selasia | AA64: Pomeme
A65: 16 | B65: 12 | D65: Nettle | E65: Ida | F65: White | G65: Female | H65: 21 | J65: Abt 1859 | K65: Daughter | L65: Single | Y65: Texas | Z65: Selasia | AA65: Pomeme
A66: 17 | B66: 12 | D66: Nettle | E66: Alfred | F66: White | G66: Male | H66: 20 | J66: Abt 1860 | K66: Son | L66: Single | N66: Apprentice shoemaker | Y66: Texas | Z66: Selasia | AA66: Pomeme
A67: 18 | B67: 12 | D67: Nettle | E67: Paul | F67: White | G67: Male | H67: 18 | J67: Abt 1862 | K67: Son | L67: Single | N67: Apprentice carpenter | Y67: Texas | Z67: Selasia | AA67: Pomeme
A68: 19 | B68: 12 | D68: Nettle | E68: Joseph | F68: White | G68: Male | H68: 14 | J68: Abt 1866 | K68: Son | L68: Single | V68: Y | Y68: Texas | Z68: Selasia | AA68: Pomeme
A69: 20 | B69: 12 | D69: Nettle | E69: Anna | F69: White | G69: Female | H69: 12 | J69: Abt 1868 | K69: Daughter | L69: Single | V69: Y | Y69: Texas | Z69: Selasia | AA69: Pomeme
A70: 21 | B70: 12 | D70: Nettle | E70: Clara | F70: White | G70: Female | H70: 10 | J70: Abt 1870 | K70: Daughter | L70: Single | V70: Y | Y70: Texas | Z70: Selasia | AA70: Pomeme
A71: 22 | B71: 12 | D71: Nettle | E71: Martha | F71: White | G71: Female | H71: 8 | J71: Abt 1872 | K71: Daughter | L71: Single | Y71: Texas | Z71: Selasia | AA71: Pomeme
A72: 23 | B72: 13 | D72: Lewis | E72: A. S. | F72: White | G72: Male | H72: 25 | J72: Abt 1855 | K72: Self (Head) | L72: Married | N72: Merchant | Y72: Texas | Z72: Poland | AA72: Louisiana
A73: 24 | B73: 13 | D73: Lewis | E73: Birtha | F73: White | G73: Female | H73: 25 | J73: Abt 1855 | K73: Wife | L73: Married | N73: Housekeeper | Y73: Germany
A74: 25 | B74: 13 | D74: Lewis | E74: Lizzie | F74: White | G74: Female | H74: 45881 | I74: Nov | J74: Abt 1879 | K74: Daughter | L74: Single | Y74: Texas | Z74: Texas | AA74: Germany
A75: 26 | B75: 13 | D75: Lewis | E75: F. S. | F75: White | G75: Male | H75: 20 | J75: Abt 1860 | K75: Brother | L75: Single | N75: Merchant | Y75: Texas | Z75: Texas | AA75: Germany
A76: 27 | B76: 13 | D76: Mc David | E76: R. A. | F76: Black | G76: Female | H76: 24 | J76: Abt 1856 | L76: Single | N76: Servant | W76: Y | X76: Y | Y76: Texas
A77: 28 | B77: 13 | D77: Helmann | E77: H. | F77: White | G77: Female | H77: 30 | J77: Abt 1850 | K77: Boarder | L77: Married | Y77: Germany
A78: 29 | B78: 13 | D78: Helmann | E78: L. | F78: White | G78: Male | H78: 44 | J78: Abt 1836 | K78: Boarder | L78: Married | Y78: Germany
A79: 30 | B79: 14 | D79: Shafer | E79: C. W. | F79: White | G79: Male | H79: 32 | J79: Abt 1848 | K79: Self (Head) | L79: Married | N79: Tanner | Y79: Texas | Z79: Germany | AA79: Germany
A80: 31 | B80: 14 | D80: Shafer | E80: Theracia | F80: White | G80: Female | H80: 30 | J80: Abt 1850 | K80: Wife | L80: Married | N80: Housekeeper | Y80: Germany | Z80: Germany | AA80: Germany
A81: 32 | B81: 14 | D81: Shafer | E81: William | F81: White | G81: Male | H81: 6 | J81: Abt 1874 | K81: Son | L81: Single | Y81: Texas | Z81: Texas | AA81: Germany
A82: 33 | B82: 14 | D82: Shafer | E82: Sophia | F82: White | G82: Female | H82: 4 | J82: Abt 1876 | K82: Daughter | L82: Single | Y82: Texas | Z82: Texas | AA82: Germany
A83: 34 | B83: 14 | D83: Shafer | E83: Julia | F83: White | G83: Female | H83: 2 | J83: Abt 1878 | K83: Daughter | L83: Single | Y83: Texas | Z83: Texas | AA83: Germany
A84: 35 | B84: 15 | D84: Birch | E84: Nelson | F84: White | G84: Male | H84: 75 | J84: Abt 1805 | K84: Self (Head) | L84: Married | N84: Merchant | Y84: New York | Z84: Massachusetts | AA84: Massachusetts
A85: 36 | B85: 15 | D85: Birch | E85: E. D. | F85: White | G85: Female | H85: 54 | J85: Abt 1826 | K85: Wife | L85: Married | N85: Housekeeper | Y85: New York | Z85: Massachusetts | AA85: Massachusetts
A86: 37 | B86: 15 | D86: Demauda | E86: R. M. | F86: White | G86: Female | H86: 56 | J86: Abt 1824 | K86: Sister-in-law | L86: Single | Y86: New York | Z86: Massachusetts | AA86: Massachusetts
A87: 38 | B87: 16 | D87: Martin | E87: William | F87: Mulatto | G87: Male | H87: 34 | J87: Abt 1846 | K87: Self (Head) | L87: Married | N87: Blacksmith | Y87: Tennessee | AA87: Tennessee
A88: 39 | B88: 16 | D88: Martin | E88: Elvira | F88: Mulatto | G88: Female | H88: 32 | J88: Abt 1848 | K88: Wife | L88: Married | N88: Housekeeper | Y88: Texas | Z88: Louisiana | AA88: Louisiana
A89: 40 | B89: 16 | D89: Black | E89: Laura | F89: Black | G89: Female | H89: 14 | J89: Abt 1866 | K89: Ward | L89: Single | X89: Y | Y89: Texas
A90: 41 | B90: 16 | D90: Holady | E90: Blanch | F90: Black | G90: Female | H90: 11 | J90: Abt 1869 | K90: Ward | L90: Single | X90: Y | Y90: Texas | Z90: Alabama | AA90: Texas
A91: 42 | B91: 17 | D91: Hancock | E91: Booker | F91: Mulatto | G91: Male | H91: 39 | J91: Abt 1841 | K91: Self (Head) | L91: Married | N91: Blacksmith | Y91: Texas | AA91: Virginia
A92: 43 | B92: 17 | D92: Hancock | E92: Hanale | F92: Black | G92: Female | H92: 34 | J92: Abt 1846 | K92: Wife | L92: Married | N92: Housekeeper | Y92: Alabama | Z92: North Carolina | AA92: Alabama
A93: 44 | B93: 17 | D93: Hancock | E93: Louis | F93: Mulatto | G93: Male | H93: 13 | J93: Abt 1867 | K93: Son | L93: Single | V93: Y | Y93: Texas | Z93: Texas | AA93: Alabama
A94: 45 | B94: 17 | D94: Hancock | E94: Louisa | F94: Mulatto | G94: Female | H94: 11 | J94: Abt 1869 | K94: Daughter | L94: Single | V94: Y | Y94: Texas | Z94: Texas | AA94: Alabama
A95: 46 | B95: 17 | D95: Hancock | E95: Estellar | F95: Mulatto | G95: Male | H95: 8 | J95: Abt 1872 | K95: Son | L95: Single | Y95: Texas | Z95: Texas | AA95: Alabama
A96: 47 | B96: 17 | D96: Hancock | E96: Clarance | F96: Mulatto | G96: Male | H96: 6 | J96: Abt 1874 | K96: Son | L96: Single | Y96: Texas | Z96: Texas | AA96: Alabama
A97: 48 | B97: 17 | D97: Hancock | E97: Ferdenand | F97: Mulatto | G97: Male | H97: 2 | J97: Abt 1878 | K97: Son | L97: Single | Y97: Texas | Z97: Texas | AA97: Alabama
A98: 1 | B98: 18 | D98: Shaffer | E98: Charles | F98: White | G98: Male | H98: 48 | J98: Abt 1832 | K98: Self (Head) | L98: Married | N98: Confectioner | Y98: France | Z98: France | AA98: France
A99: 2 | B99: 18 | D99: Shaffer | E99: Anna | F99: White | G99: Female | H99: 59 | J99: Abt 1821 | K99: Wife | L99: Married | N99: Housekeeper | Y99: Prussia | Z99: Prussia | AA99: Prussia
A100: 3 | B100: 18 | D100: Beacher | E100: Richard | F100: White | G100: Male | H100: 31 | J100: Abt 1849 | K100: Boarder | L100: Single | N100: Clerk in shop | Y100: Prussia | Z100: Prussia | AA100: Prussia
...

Sheet 1880 Bastrop 0008 Raw
A1: Line Number | B1: Dwelling Number | C1: Street | D1: Surname | E1: Given Name | F1: Race | G1: Gender | H1: Age | I1: Birth Month | J1: Birth Year | K1: Relation to Head of House | L1: Marital Status | M1: Married During Census Year | N1: Occupation | O1: Months Not Employed | P1: Sick | Q1: Blind | R1: Deaf and Dumb | S1: Idiotic | T1: Insane | U1: Maimed, Crippled, or Bedridden | V1: Attended School | W1: Cannot Read | X1: Cannot Write | Y1: Birthplace | Z1: Father's Birthplace | AA1: Mother's Birthplace | AC1: Comp.
A2: 1 | B2: 1 | D2: Wertzner | E2: Charles | F2: White | G2: Male | H2: 57 | J2: Abt 1823 | K2: Self (Head) | L2: Married | N2: Merchant | Y2: Saxony | Z2: Saxony | AA2: Saxony | AC2: {=SUMPRODUCT(--(INDEX('1880 Bastrop 0008 Clean'!A:AA, MATCH(A2 & "|" & B2, '1880 Bastrop 0008 Clean'!A:A & "|" & '1880 Bastrop 0008 Clean'!B:B, 0), 0) <> '1880 Bastrop 0008 Raw'!A2:AA2))} -> 0
A3: 2 | B3: 1 | D3: Wertzner | E3: Fransisca | F3: White | G3: Female | H3: 42 | J3: Abt 1838 | K3: Wife | L3: Married | N3: Housekeeper | Y3: Bohemia | Z3: Bohemia | AA3: Bohemia | AC3: {=SUMPRODUCT(--(INDEX('1880 Bastrop 0008 Clean'!A:AA, MATCH(A3 & "|" & B3, '1880 Bastrop 0008 Clean'!A:A & "|" & '1880 Bastrop 0008 Clean'!B:B, 0), 0) <> '1880 Bastrop 0008 Raw'!A3:AA3))} -> 0
A4: 3 | B4: 1 | D4: Wertzner | E4: Selma | F4: White | G4: Female | H4: 17 | J4: Abt 1863 | K4: Daughter | L4: Single | Y4: Texas | Z4: Saxony | AA4: Bohemia | AC4: {=SUMPRODUCT(--(INDEX('1880 Bastrop 0008 Clean'!A:AA, MATCH(A4 & "|" & B4, '1880 Bastrop 0008 Clean'!A:A & "|" & '1880 Bastrop 0008 Clean'!B:B, 0), 0) <> '1880 Bastrop 0008 Raw'!A4:AA4))} -> 0
A5: 4 | B5: 1 | D5: Wertzner | E5: Pauline | F5: White | G5: Female | H5: 15 | J5: Abt 1865 | K5: Daughter | L5: Single | Y5: Texas | Z5: Saxony | AA5: Bohemia | AC5: {=SUMPRODUCT(--(INDEX('1880 Bastrop 0008 Clean'!A:AA, MATCH(A5 & "|" & B5, '1880 Bastrop 0008 Clean'!A:A & "|" & '1880 Bastrop 0008 Clean'!B:B, 0), 0) <> '1880 Bastrop 0008 Raw'!A5:AA5))} -> 0
A6: 5 | B6: 1 | D6: Wertzner | E6: Bertha | F6: White | G6: Female | H6: 11 | J6: Abt 1869 | K6: Daughter | L6: Single | Y6: Texas | Z6: Saxony | AA6: Bohemia | AC6: {=SUMPRODUCT(--(INDEX('1880 Bastrop 0008 Clean'!A:AA, MATCH(A6 & "|" & B6, '1880 Bastrop 0008 Clean'!A:A & "|" & '1880 Bastrop 0008 Clean'!B:B, 0), 0) <> '1880 Bastrop 0008 Raw'!A6:AA6))} -> 1
A7: 6 | B7: 1 | D7: Wertzner | E7: Louis | F7: White | G7: Male | H7: 9 | J7: Abt 1871 | K7: Son | L7: Single | Y7: Texas | Z7: Saxony | AA7: Bohemia | AC7: {=SUMPRODUCT(--(INDEX('1880 Bastrop 0008 Clean'!A:AA, MATCH(A7 & "|" & B7, '1880 Bastrop 0008 Clean'!A:A & "|" & '1880 Bastrop 0008 Clean'!B:B, 0), 0) <> '1880 Bastrop 0008 Raw'!A7:AA7))} -> 0
A8: 7 | B8: 1 | D8: Wertzner | E8: Juliana | F8: White | G8: Female | H8: 7 | J8: Abt 1873 | K8: Daughter | L8: Single | Y8: Texas | Z8: Saxony | AA8: Bohemia | AC8: {=SUMPRODUCT(--(INDEX('1880 Bastrop 0008 Clean'!A:AA, MATCH(A8 & "|" & B8, '1880 Bastrop 0008 Clean'!A:A & "|" & '1880 Bastrop 0008 Clean'!B:B, 0), 0) <> '1880 Bastrop 0008 Raw'!A8:AA8))} -> 0
A9: 8 | B9: 1 | D9: Wertzner | E9: Bruno | F9: White | G9: Male | H9: 5 | J9: Abt 1875 | K9: Son | L9: Single | Y9: Texas | Z9: Saxony | AA9: Bohemia | AC9: {=SUMPRODUCT(--(INDEX('1880 Bastrop 0008 Clean'!A:AA, MATCH(A9 & "|" & B9, '1880 Bastrop 0008 Clean'!A:A & "|" & '1880 Bastrop 0008 Clean'!B:B, 0), 0) <> '1880 Bastrop 0008 Raw'!A9:AA9))} -> 0
A10: 9 | B10: 1 | D10: Wertzner | E10: Hugo | F10: White | G10: Male | H10: 1 | J10: Abt 1879 | K10: Son | L10: Single | Y10: Texas | Z10: Saxony | AA10: Bohemia | AC10: {=SUMPRODUCT(--(INDEX('1880 Bastrop 0008 Clean'!A:AA, MATCH(A10 & "|" & B10, '1880 Bastrop 0008 Clean'!A:A & "|" & '1880 Bastrop 0008 Clean'!B:B, 0), 0) <> '1880 Bastrop 0008 Raw'!A10:AA10))} -> 0
A11: 10 | B11: 1 | D11: Brandt | E11: H. | F11: White | G11: Male | H11: 18 | J11: Abt 1862 | L11: Single | N11: Clerk in post office | Y11: Texas | Z11: Prussia | AA11: Prussia | AC11: {=SUMPRODUCT(--(INDEX('1880 Bastrop 0008 Clean'!A:AA, MATCH(A11 & "|" & B11, '1880 Bastrop 0008 Clean'!A:A & "|" & '1880 Bastrop 0008 Clean'!B:B, 0), 0) <> '1880 Bastrop 0008 Raw'!A11:AA11))} -> 1
A12: 11 | B12: 1 | D12: Ploger | E12: Gus | F12: White | G12: Male | H12: 19 | J12: Abt 1861 | L12: Single | N12: Clerk in store | Y12: Texas | Z12: Prussia | AA12: Hungary | AC12: {=SUMPRODUCT(--(INDEX('1880 Bastrop 0008 Clean'!A:AA, MATCH(A12 & "|" & B12, '1880 Bastrop 0008 Clean'!A:A & "|" & '1880 Bastrop 0008 Clean'!B:B, 0), 0) <> '1880 Bastrop 0008 Raw'!A12:AA12))} -> 1
A13: 12 | B13: 1 | D13: Zandon | E13: William | F13: White | G13: Male | H13: 21 | J13: Abt 1859 | L13: Single | N13: Clerk in store | Y13: Prussia | Z13: Prussia | AA13: Prussia | AC13: {=SUMPRODUCT(--(INDEX('1880 Bastrop 0008 Clean'!A:AA, MATCH(A13 & "|" & B13, '1880 Bastrop 0008 Clean'!A:A & "|" & '1880 Bastrop 0008 Clean'!B:B, 0), 0) <> '1880 Bastrop 0008 Raw'!A13:AA13))} -> 1
A14: 13 | B14: 2 | D14: Gell | E14: Robert | F14: White | G14: Male | H14: 35 | J14: Abt 1845 | K14: Self (Head) | L14: Married | N14: Merchant | Y14: Tennessee | Z14: Tennessee | AA14: Tennessee | AC14: {=SUMPRODUCT(--(INDEX('1880 Bastrop 0008 Clean'!A:AA, MATCH(A14 & "|" & B14, '1880 Bastrop 0008 Clean'!A:A & "|" & '1880 Bastrop 0008 Clean'!B:B, 0), 0) <> '1880 Bastrop 0008 Raw'!A14:AA14))} -> 0
A15: 14 | B15: 2 | D15: Gell | E15: Mary J. | F15: White | G15: Female | H15: 33 | J15: Abt 1847 | K15: Wife | L15: Married | N15: Housekeeper | Y15: England | Z15: England | AA15: England | AC15: {=SUMPRODUCT(--(INDEX('1880 Bastrop 0008 Clean'!A:AA, MATCH(A15 & "|" & B15, '1880 Bastrop 0008 Clean'!A:A & "|" & '1880 Bastrop 0008 Clean'!B:B, 0), 0) <> '1880 Bastrop 0008 Raw'!A15:AA15))} -> 0
A16: 15 | B16: 2 | D16: Gell | E16: Edner E. | F16: White | G16: Female | H16: 11 | J16: Abt 1869 | K16: Daughter | L16: Single | V16: Y | Y16: Texas | Z16: Tennessee | AA16: England | AC16: {=SUMPRODUCT(--(INDEX('1880 Bastrop 0008 Clean'!A:AA, MATCH(A16 & "|" & B16, '1880 Bastrop 0008 Clean'!A:A & "|" & '1880 Bastrop 0008 Clean'!B:B, 0), 0) <> '1880 Bastrop 0008 Raw'!A16:AA16))} -> 0
A17: 16 | B17: 2 | D17: Gell | E17: Robert L. | F17: White | G17: Male | H17: 8 | J17: Abt 1872 | K17: Son | L17: Single | V17: Y | Y17: Texas | Z17: Tennessee | AA17: England | AC17: {=SUMPRODUCT(--(INDEX('1880 Bastrop 0008 Clean'!A:AA, MATCH(A17 & "|" & B17, '1880 Bastrop 0008 Clean'!A:A & "|" & '1880 Bastrop 0008 Clean'!B:B, 0), 0) <> '1880 Bastrop 0008 Raw'!A17:AA17))} -> 0
A18: 17 | B18: 2 | D18: Smutfeld | E18: Olga | F18: White | G18: Female | H18: 14 | J18: Abt 1866 | L18: Single | N18: Cook | Y18: Germany | AC18: {=SUMPRODUCT(--(INDEX('1880 Bastrop 0008 Clean'!A:AA, MATCH(A18 & "|" & B18, '1880 Bastrop 0008 Clean'!A:A & "|" & '1880 Bastrop 0008 Clean'!B:B, 0), 0) <> '1880 Bastrop 0008 Raw'!A18:AA18))} -> 1
A19: 18 | B19: 3 | D19: Vogt | E19: Charles | F19: White | G19: Male | H19: 42 | J19: Abt 1838 | K19: Self (Head) | L19: Married | N19: Gunsmith | Y19: Prussia | Z19: Prussia | AA19: Prussia | AC19: {=SUMPRODUCT(--(INDEX('1880 Bastrop 0008 Clean'!A:AA, MATCH(A19 & "|" & B19, '1880 Bastrop 0008 Clean'!A:A & "|" & '1880 Bastrop 0008 Clean'!B:B, 0), 0) <> '1880 Bastrop 0008 Raw'!A19:AA19))} -> 0
A20: 19 | B20: 3 | D20: Vogt | E20: Caroline | F20: White | G20: Female | H20: 32 | J20: Abt 1848 | K20: Wife | L20: Married | N20: Housekeeper | Y20: Bohemia | Z20: Bohemia | AA20: Bohemia | AC20: {=SUMPRODUCT(--(INDEX('1880 Bastrop 0008 Clean'!A:AA, MATCH(A20 & "|" & B20, '1880 Bastrop 0008 Clean'!A:A & "|" & '1880 Bastrop 0008 Clean'!B:B, 0), 0) <> '1880 Bastrop 0008 Raw'!A20:AA20))} -> 0
A21: 20 | B21: 3 | D21: Vogt | E21: Paul | F21: White | G21: Male | H21: 12 | J21: Abt 1868 | K21: Son | L21: Single | V21: Y | Y21: Texas | Z21: Prussia | AA21: Bohemia | AC21: {=SUMPRODUCT(--(INDEX('1880 Bastrop 0008 Clean'!A:AA, MATCH(A21 & "|" & B21, '1880 Bastrop 0008 Clean'!A:A & "|" & '1880 Bastrop 0008 Clean'!B:B, 0), 0) <> '1880 Bastrop 0008 Raw'!A21:AA21))} -> 0
A22: 21 | B22: 3 | D22: Vogt | E22: Anna | F22: White | G22: Female | H22: 9 | J22: Abt 1871 | K22: Daughter | L22: Single | Y22: Texas | Z22: Prussia | AA22: Bohemia | AC22: {=SUMPRODUCT(--(INDEX('1880 Bastrop 0008 Clean'!A:AA, MATCH(A22 & "|" & B22, '1880 Bastrop 0008 Clean'!A:A & "|" & '1880 Bastrop 0008 Clean'!B:B, 0), 0) <> '1880 Bastrop 0008 Raw'!A22:AA22))} -> 0
A23: 22 | B23: 3 | D23: Vogt | E23: Maxmilian | F23: White | G23: Male | H23: 7 | J23: Abt 1873 | K23: Son | L23: Single | Y23: Texas | Z23: Prussia | AA23: Bohemia | AC23: {=SUMPRODUCT(--(INDEX('1880 Bastrop 0008 Clean'!A:AA, MATCH(A23 & "|" & B23, '1880 Bastrop 0008 Clean'!A:A & "|" & '1880 Bastrop 0008 Clean'!B:B, 0), 0) <> '1880 Bastrop 0008 Raw'!A23:AA23))} -> 0
A24: 23 | B24: 3 | D24: Vogt | E24: Mary | F24: White | G24: Female | H24: 3 | J24: Abt 1877 | K24: Daughter | L24: Single | Y24: Texas | Z24: Prussia | AA24: Bohemia | AC24: {=SUMPRODUCT(--(INDEX('1880 Bastrop 0008 Clean'!A:AA, MATCH(A24 & "|" & B24, '1880 Bastrop 0008 Clean'!A:A & "|" & '1880 Bastrop 0008 Clean'!B:B, 0), 0) <> '1880 Bastrop 0008 Raw'!A24:AA24))} -> 0
A25: 24 | B25: 3 | D25: Vogt | E25: Ida | F25: White | G25: Female | H25: 45759 | I25: Feb | J25: Abt 1880 | K25: Daughter | L25: Single | Y25: Texas | Z25: Prussia | AA25: Bohemia | AC25: {=SUMPRODUCT(--(INDEX('1880 Bastrop 0008 Clean'!A:AA, MATCH(A25 & "|" & B25, '1880 Bastrop 0008 Clean'!A:A & "|" & '1880 Bastrop 0008 Clean'!B:B, 0), 0) <> '1880 Bastrop 0008 Raw'!A25:AA25))} -> 0
A26: 25 | B26: 4 | D26: Wiseman | E26: Louis | F26: White | G26: Male | J26: 1863 | K26: Self (Head) | L26: Married | N26: Watchmaker | Y26: Wurtemburg | Z26: Wurttemberg | AA26: Wurtemburg | AC26: {=SUMPRODUCT(--(INDEX('1880 Bastrop 0008 Clean'!A:AA, MATCH(A26 & "|" & B26, '1880 Bastrop 0008 Clean'!A:A & "|" & '1880 Bastrop 0008 Clean'!B:B, 0), 0) <> '1880 Bastrop 0008 Raw'!A26:AA26))} -> 2
A27: 26 | B27: 4 | D27: Wiseman | E27: Sophia | F27: White | G27: Female | J27: 1863 | K27: Wife | L27: Married | N27: Housekeeper | Y27: Hanover | Z27: Germany | AA27: Germany | AC27: {=SUMPRODUCT(--(INDEX('1880 Bastrop 0008 Clean'!A:AA, MATCH(A27 & "|" & B27, '1880 Bastrop 0008 Clean'!A:A & "|" & '1880 Bastrop 0008 Clean'!B:B, 0), 0) <> '1880 Bastrop 0008 Raw'!A27:AA27))} -> 2
A28: 27 | B28: 5 | D28: Pranse | E28: Reinhard | F28: White | G28: Male | H28: 39 | J28: Abt 1841 | K28: Self (Head) | L28: Married | N28: Furniture dealer | Y28: Selasia | Z28: Selasia | AA28: Texas | AC28: {=SUMPRODUCT(--(INDEX('1880 Bastrop 0008 Clean'!A:AA, MATCH(A28 & "|" & B28, '1880 Bastrop 0008 Clean'!A:A & "|" & '1880 Bastrop 0008 Clean'!B:B, 0), 0) <> '1880 Bastrop 0008 Raw'!A28:AA28))} -> 0
A29: 28 | B29: 5 | D29: Pranse | E29: Augusta | F29: White | G29: Female | H29: 30 | J29: Abt 1850 | K29: Wife | L29: Married | N29: Housekeeper | Y29: Texas | Z29: Selasia | AA29: Selasia | AC29: {=SUMPRODUCT(--(INDEX('1880 Bastrop 0008 Clean'!A:AA, MATCH(A29 & "|" & B29, '1880 Bastrop 0008 Clean'!A:A & "|" & '1880 Bastrop 0008 Clean'!B:B, 0), 0) <> '1880 Bastrop 0008 Raw'!A29:AA29))} -> 0
A30: 29 | B30: 5 | D30: Pranse | E30: Anna | F30: White | G30: Female | H30: 9 | J30: Abt 1871 | K30: Daughter | L30: Single | Y30: Texas | Z30: Selasia | AA30: Texas | AC30: {=SUMPRODUCT(--(INDEX('1880 Bastrop 0008 Clean'!A:AA, MATCH(A30 & "|" & B30, '1880 Bastrop 0008 Clean'!A:A & "|" & '1880 Bastrop 0008 Clean'!B:B, 0), 0) <> '1880 Bastrop 0008 Raw'!A30:AA30))} -> 0
A31: 30 | B31: 5 | D31: Pranse | E31: Albert | F31: White | G31: Male | H31: 7 | J31: Abt 1873 | K31: Son | L31: Single | Y31: Texas | Z31: Selasia | AA31: Texas | AC31: {=SUMPRODUCT(--(INDEX('1880 Bastrop 0008 Clean'!A:AA, MATCH(A31 & "|" & B31, '1880 Bastrop 0008 Clean'!A:A & "|" & '1880 Bastrop 0008 Clean'!B:B, 0), 0) <> '1880 Bastrop 0008 Raw'!A31:AA31))} -> 0
A32: 31 | B32: 5 | D32: Pranse | E32: Martha | F32: White | G32: Female | H32: 5 | J32: Abt 1875 | K32: Daughter | L32: Single | Y32: Texas | Z32: Selasia | AA32: Texas | AC32: {=SUMPRODUCT(--(INDEX('1880 Bastrop 0008 Clean'!A:AA, MATCH(A32 & "|" & B32, '1880 Bastrop 0008 Clean'!A:A & "|" & '1880 Bastrop 0008 Clean'!B:B, 0), 0) <> '1880 Bastrop 0008 Raw'!A32:AA32))} -> 0
A33: 32 | B33: 6 | D33: Walter | E33: William | F33: White | G33: Male | H33: 63 | J33: Abt 1817 | K33: Self (Head) | L33: Married | N33: Grocer and Baker | Y33: Prussia | Z33: Prussia | AA33: Prussia | AC33: {=SUMPRODUCT(--(INDEX('1880 Bastrop 0008 Clean'!A:AA, MATCH(A33 & "|" & B33, '1880 Bastrop 0008 Clean'!A:A & "|" & '1880 Bastrop 0008 Clean'!B:B, 0), 0) <> '1880 Bastrop 0008 Raw'!A33:AA33))} -> 0
A34: 33 | B34: 6 | D34: Walter | E34: Joanah | F34: White | G34: Female | H34: 60 | J34: Abt 1820 | K34: Wife | L34: Married | N34: Housekeeper | Y34: Prussia | Z34: Holstein | AA34: Holstein | AC34: {=SUMPRODUCT(--(INDEX('1880 Bastrop 0008 Clean'!A:AA, MATCH(A34 & "|" & B34, '1880 Bastrop 0008 Clean'!A:A & "|" & '1880 Bastrop 0008 Clean'!B:B, 0), 0) <> '1880 Bastrop 0008 Raw'!A34:AA34))} -> 0
A35: 34 | B35: 7 | D35: Prokoop | E35: M. A. | F35: White | G35: Male | H35: 47 | J35: Abt 1833 | K35: Self (Head) | L35: Married | N35: Shoemaker | Y35: Bohemia | Z35: Bohemia | AA35: Bohemia | AC35: {=SUMPRODUCT(--(INDEX('1880 Bastrop 0008 Clean'!A:AA, MATCH(A35 & "|" & B35, '1880 Bastrop 0008 Clean'!A:A & "|" & '1880 Bastrop 0008 Clean'!B:B, 0), 0) <> '1880 Bastrop 0008 Raw'!A35:AA35))} -> 0
A36: 35 | B36: 7 | D36: Prokoop | E36: Anna M. | F36: White | G36: Female | H36: 48 | J36: Abt 1832 | K36: Wife | L36: Married | N36: Housekeeper | Y36: Bohemia | Z36: Bohemia | AA36: Bohemia | AC36: {=SUMPRODUCT(--(INDEX('1880 Bastrop 0008 Clean'!A:AA, MATCH(A36 & "|" & B36, '1880 Bastrop 0008 Clean'!A:A & "|" & '1880 Bastrop 0008 Clean'!B:B, 0), 0) <> '1880 Bastrop 0008 Raw'!A36:AA36))} -> 0
A37: 36 | B37: 7 | D37: Prokoop | E37: Frank | F37: White | G37: Male | H37: 19 | J37: Abt 1861 | K37: Son | L37: Single | N37: Apprentice shoemaker | Y37: Texas | Z37: Bohemia | AA37: Bohemia | AC37: {=SUMPRODUCT(--(INDEX('1880 Bastrop 0008 Clean'!A:AA, MATCH(A37 & "|" & B37, '1880 Bastrop 0008 Clean'!A:A & "|" & '1880 Bastrop 0008 Clean'!B:B, 0), 0) <> '1880 Bastrop 0008 Raw'!A37:AA37))} -> 0
A38: 37 | B38: 7 | D38: Prokoop | E38: Emeil | F38: White | G38: Male | H38: 15 | J38: Abt 1865 | K38: Son | L38: Single | Y38: Texas | Z38: Bohemia | AA38: Bohemia | AC38: {=SUMPRODUCT(--(INDEX('1880 Bastrop 0008 Clean'!A:AA, MATCH(A38 & "|" & B38, '1880 Bastrop 0008 Clean'!A:A & "|" & '1880 Bastrop 0008 Clean'!B:B, 0), 0) <> '1880 Bastrop 0008 Raw'!A38:AA38))} -> 0
A39: 38 | B39: 8 | D39: Keslus | E39: William M. | F39: White | G39: Male | H39: 46 | J39: Abt 1834 | K39: Self (Head) | L39: Married | N39: Tailor | Y39: Prussia | Z39: Prussia | AA39: Prussia | AC39: {=SUMPRODUCT(--(INDEX('1880 Bastrop 0008 Clean'!A:AA, MATCH(A39 & "|" & B39, '1880 Bastrop 0008 Clean'!A:A & "|" & '1880 Bastrop 0008 Clean'!B:B, 0), 0) <> '1880 Bastrop 0008 Raw'!A39:AA39))} -> 0
A40: 39 | B40: 8 | D40: Keslus | E40: Anna | F40: White | G40: Female | H40: 30 | J40: Abt 1850 | K40: Wife | L40: Married | N40: Housekeeper | Y40: Bohemia | Z40: Bohemia | AA40: Bohemia | AC40: {=SUMPRODUCT(--(INDEX('1880 Bastrop 0008 Clean'!A:AA, MATCH(A40 & "|" & B40, '1880 Bastrop 0008 Clean'!A:A & "|" & '1880 Bastrop 0008 Clean'!B:B, 0), 0) <> '1880 Bastrop 0008 Raw'!A40:AA40))} -> 0
A41: 40 | B41: 8 | D41: Keslus | E41: William | F41: White | G41: Male | H41: 14 | J41: Abt 1866 | K41: Son | L41: Single | V41: Y | Y41: Texas | Z41: Prussia | AA41: Bohemia | AC41: {=SUMPRODUCT(--(INDEX('1880 Bastrop 0008 Clean'!A:AA, MATCH(A41 & "|" & B41, '1880 Bastrop 0008 Clean'!A:A & "|" & '1880 Bastrop 0008 Clean'!B:B, 0), 0) <> '1880 Bastrop 0008 Raw'!A41:AA41))} -> 0
A42: 41 | B42: 8 | D42: Keslus | E42: Hugo | F42: White | G42: Male | H42: 10 | J42: Abt 1870 | K42: Son | L42: Single | V42: Y | Y42: Texas | Z42: Prussia | AA42: Bohemia | AC42: {=SUMPRODUCT(--(INDEX('1880 Bastrop 0008 Clean'!A:AA, MATCH(A42 & "|" & B42, '1880 Bastrop 0008 Clean'!A:A & "|" & '1880 Bastrop 0008 Clean'!B:B, 0), 0) <> '1880 Bastrop 0008 Raw'!A42:AA42))} -> 0
A43: 42 | B43: 8 | D43: Keslus | E43: Rudolph | F43: White | G43: Male | H43: 9 | J43: Abt 1871 | K43: Son | L43: Single | Y43: Texas | Z43: Prussia | AA43: Bohemia | AC43: {=SUMPRODUCT(--(INDEX('1880 Bastrop 0008 Clean'!A:AA, MATCH(A43 & "|" & B43, '1880 Bastrop 0008 Clean'!A:A & "|" & '1880 Bastrop 0008 Clean'!B:B, 0), 0) <> '1880 Bastrop 0008 Raw'!A43:AA43))} -> 0
A44: 43 | B44: 8 | D44: Keslus | E44: Hellena | F44: White | G44: Female | H44: 4 | J44: Abt 1876 | K44: Daughter | L44: Single | Y44: Texas | Z44: Prussia | AA44: Bohemia | AC44: {=SUMPRODUCT(--(INDEX('1880 Bastrop 0008 Clean'!A:AA, MATCH(A44 & "|" & B44, '1880 Bastrop 0008 Clean'!A:A & "|" & '1880 Bastrop 0008 Clean'!B:B, 0), 0) <> '1880 Bastrop 0008 Raw'!A44:AA44))} -> 0
A45: 44 | B45: 8 | D45: Keslus | E45: Hadee | F45: White | G45: Female | H45: 2 | J45: Abt 1878 | K45: Daughter | L45: Single | Y45: Texas | Z45: Prussia | AA45: Bohemia | AC45: {=SUMPRODUCT(--(INDEX('1880 Bastrop 0008 Clean'!A:AA, MATCH(A45 & "|" & B45, '1880 Bastrop 0008 Clean'!A:A & "|" & '1880 Bastrop 0008 Clean'!B:B, 0), 0) <> '1880 Bastrop 0008 Raw'!A45:AA45))} -> 0
A46: 45 | B46: 8 | D46: Keslus | E46: Artalia | F46: White | G46: Female | H46: 45789 | J46: Abt 1880 | K46: Daughter | L46: Single | Y46: Texas | Z46: Prussia | AA46: Bohemia | AC46: {=SUMPRODUCT(--(INDEX('1880 Bastrop 0008 Clean'!A:AA, MATCH(A46 & "|" & B46, '1880 Bastrop 0008 Clean'!A:A & "|" & '1880 Bastrop 0008 Clean'!B:B, 0), 0) <> '1880 Bastrop 0008 Raw'!A46:AA46))} -> 0
A47: 46 | B47: 9 | D47: Lea | E47: D. C. | F47: White | G47: Male | H47: 39 | J47: Abt 1841 | K47: Self (Head) | L47: Married | N47: Dentist | Y47: Mississippi | AA47: Indiana | AC47: {=SUMPRODUCT(--(INDEX('1880 Bastrop 0008 Clean'!A:AA, MATCH(A47 & "|" & B47, '1880 Bastrop 0008 Clean'!A:A & "|" & '1880 Bastrop 0008 Clean'!B:B, 0), 0) <> '1880 Bastrop 0008 Raw'!A47:AA47))} -> 0
A48: 47 | B48: 9 | D48: Lea | E48: Ortalia | F48: White | G48: Female | H48: 20 | J48: Abt 1860 | K48: Wife | L48: Married | N48: Housekeeper | Y48: Texas | Z48: Wurtemburg | AA48: Holland | AC48: {=SUMPRODUCT(--(INDEX('1880 Bastrop 0008 Clean'!A:AA, MATCH(A48 & "|" & B48, '1880 Bastrop 0008 Clean'!A:A & "|" & '1880 Bastrop 0008 Clean'!B:B, 0), 0) <> '1880 Bastrop 0008 Raw'!A48:AA48))} -> 0
A49: 48 | B49: 9 | D49: Lea | E49: Maud | F49: White | G49: Female | H49: 45881 | I49: Sep | J49: Abt 1879 | K49: Daughter | L49: Single | Y49: Texas | Z49: Mississippi | AA49: Texas | AC49: {=SUMPRODUCT(--(INDEX('1880 Bastrop 0008 Clean'!A:AA, MATCH(A49 & "|" & B49, '1880 Bastrop 0008 Clean'!A:A & "|" & '1880 Bastrop 0008 Clean'!B:B, 0), 0) <> '1880 Bastrop 0008 Raw'!A49:AA49))} -> 0
A50: 1 | B50: 10 | D50: Meller | E50: William | F50: White | G50: Male | H50: 48 | J50: Abt 1832 | K50: Self (Head) | L50: Married | N50: Barber | Y50: Bavaria | Z50: Bavaria | AA50: Bavaria | AC50: {=SUMPRODUCT(--(INDEX('1880 Bastrop 0008 Clean'!A:AA, MATCH(A50 & "|" & B50, '1880 Bastrop 0008 Clean'!A:A & "|" & '1880 Bastrop 0008 Clean'!B:B, 0), 0) <> '1880 Bastrop 0008 Raw'!A50:AA50))} -> 0
A51: 2 | B51: 10 | D51: Meller | E51: Hellena | F51: White | G51: Female | H51: 38 | J51: Abt 1842 | K51: Wife | L51: Married | N51: Housekeeper | Y51: Wurtemburg | Z51: Wurtemburg | AA51: Wurtemburg | AC51: {=SUMPRODUCT(--(INDEX('1880 Bastrop 0008 Clean'!A:AA, MATCH(A51 & "|" & B51, '1880 Bastrop 0008 Clean'!A:A & "|" & '1880 Bastrop 0008 Clean'!B:B, 0), 0) <> '1880 Bastrop 0008 Raw'!A51:AA51))} -> 0
A52: 3 | B52: 10 | D52: Meller | E52: Antonia | F52: White | G52: Female | H52: 18 | J52: Abt 1862 | K52: Daughter | L52: Single | Y52: Texas | Z52: Bavaria | AA52: Wurtemburg | AC52: {=SUMPRODUCT(--(INDEX('1880 Bastrop 0008 Clean'!A:AA, MATCH(A52 & "|" & B52, '1880 Bastrop 0008 Clean'!A:A & "|" & '1880 Bastrop 0008 Clean'!B:B, 0), 0) <> '1880 Bastrop 0008 Raw'!A52:AA52))} -> 0
A53: 4 | B53: 10 | D53: Meller | E53: Anna | F53: White | G53: Female | H53: 16 | J53: Abt 1864 | K53: Daughter | L53: Single | V53: Y | Y53: Texas | Z53: Bavaria | AA53: Wurtemburg | AC53: {=SUMPRODUCT(--(INDEX('1880 Bastrop 0008 Clean'!A:AA, MATCH(A53 & "|" & B53, '1880 Bastrop 0008 Clean'!A:A & "|" & '1880 Bastrop 0008 Clean'!B:B, 0), 0) <> '1880 Bastrop 0008 Raw'!A53:AA53))} -> 0
A54: 5 | B54: 10 | D54: Meller | E54: Julia | F54: White | G54: Female | H54: 12 | J54: Abt 1868 | K54: Daughter | L54: Single | V54: Y | Y54: Texas | Z54: Bavaria | AA54: Wurtemburg | AC54: {=SUMPRODUCT(--(INDEX('1880 Bastrop 0008 Clean'!A:AA, MATCH(A54 & "|" & B54, '1880 Bastrop 0008 Clean'!A:A & "|" & '1880 Bastrop 0008 Clean'!B:B, 0), 0) <> '1880 Bastrop 0008 Raw'!A54:AA54))} -> 0
A55: 6 | B55: 10 | D55: Meller | E55: Willie | F55: White | G55: Male | H55: 10 | J55: Abt 1870 | K55: Son | L55: Single | V55: Y | Y55: Texas | Z55: Bavaria | AA55: Wurtemburg | AC55: {=SUMPRODUCT(--(INDEX('1880 Bastrop 0008 Clean'!A:AA, MATCH(A55 & "|" & B55, '1880 Bastrop 0008 Clean'!A:A & "|" & '1880 Bastrop 0008 Clean'!B:B, 0), 0) <> '1880 Bastrop 0008 Raw'!A55:AA55))} -> 0
A56: 7 | B56: 10 | D56: Meller | E56: George | F56: White | G56: Male | H56: 8 | J56: Abt 1872 | K56: Son | L56: Single | Y56: Texas | Z56: Bavaria | AA56: Wurtemburg | AC56: {=SUMPRODUCT(--(INDEX('1880 Bastrop 0008 Clean'!A:AA, MATCH(A56 & "|" & B56, '1880 Bastrop 0008 Clean'!A:A & "|" & '1880 Bastrop 0008 Clean'!B:B, 0), 0) <> '1880 Bastrop 0008 Raw'!A56:AA56))} -> 0
A57: 8 | B57: 10 | D57: Meller | E57: Arnold | F57: White | G57: Male | H57: 3 | J57: Abt 1877 | K57: Son | L57: Single | Y57: Texas | Z57: Bavaria | AA57: Wurtemburg | AC57: {=SUMPRODUCT(--(INDEX('1880 Bastrop 0008 Clean'!A:AA, MATCH(A57 & "|" & B57, '1880 Bastrop 0008 Clean'!A:A & "|" & '1880 Bastrop 0008 Clean'!B:B, 0), 0) <> '1880 Bastrop 0008 Raw'!A57:AA57))} -> 0
A58: 9 | B58: 10 | D58: Meller | E58: Fritz | F58: White | G58: Male | H58: 45820 | I58: Oct | J58: Abt 1880 | K58: Son | L58: Single | Y58: Texas | Z58: Bavaria | AA58: Wurtemburg | AC58: {=SUMPRODUCT(--(INDEX('1880 Bastrop 0008 Clean'!A:AA, MATCH(A58 & "|" & B58, '1880 Bastrop 0008 Clean'!A:A & "|" & '1880 Bastrop 0008 Clean'!B:B, 0), 0) <> '1880 Bastrop 0008 Raw'!A58:AA58))} -> 0
A59: 10 | B59: 11 | D59: Fuest | E59: L. R. | F59: White | G59: Male | H59: 27 | J59: Abt 1853 | K59: Self (Head) | L59: Married | N59: Merchant | Y59: Texas | Z59: Wurtemburg | AA59: Holland | AC59: {=SUMPRODUCT(--(INDEX('1880 Bastrop 0008 Clean'!A:AA, MATCH(A59 & "|" & B59, '1880 Bastrop 0008 Clean'!A:A & "|" & '1880 Bastrop 0008 Clean'!B:B, 0), 0) <> '1880 Bastrop 0008 Raw'!A59:AA59))} -> 0
A60: 11 | B60: 11 | D60: Fuest | E60: Fannie | F60: White | G60: Female | H60: 21 | J60: Abt 1859 | K60: Wife | L60: Married | N60: Housekeeper | Y60: England | Z60: England | AA60: England | AC60: {=SUMPRODUCT(--(INDEX('1880 Bastrop 0008 Clean'!A:AA, MATCH(A60 & "|" & B60, '1880 Bastrop 0008 Clean'!A:A & "|" & '1880 Bastrop 0008 Clean'!B:B, 0), 0) <> '1880 Bastrop 0008 Raw'!A60:AA60))} -> 0
A61: 12 | B61: 11 | D61: Fuest | E61: Leo R. | F61: White | G61: Male | H61: 45850 | I61: Oct | J61: Abt 1879 | K61: Son | L61: Single | Y61: Texas | Z61: Texas | AA61: England | AC61: {=SUMPRODUCT(--(INDEX('1880 Bastrop 0008 Clean'!A:AA, MATCH(A61 & "|" & B61, '1880 Bastrop 0008 Clean'!A:A & "|" & '1880 Bastrop 0008 Clean'!B:B, 0), 0) <> '1880 Bastrop 0008 Raw'!A61:AA61))} -> 0
A62: 13 | B62: 12 | D62: Nettle | E62: A. | F62: White | G62: Male | H62: 56 | J62: Abt 1824 | K62: Self (Head) | L62: Married | N62: Shoemaker | Y62: Selasia | Z62: Selasia | AA62: Selasia | AC62: {=SUMPRODUCT(--(INDEX('1880 Bastrop 0008 Clean'!A:AA, MATCH(A62 & "|" & B62, '1880 Bastrop 0008 Clean'!A:A & "|" & '1880 Bastrop 0008 Clean'!B:B, 0), 0) <> '1880 Bastrop 0008 Raw'!A62:AA62))} -> 0
A63: 14 | B63: 12 | D63: Nettle | E63: Ida | F63: White | G63: Female | H63: 52 | J63: Abt 1828 | K63: Wife | L63: Married | N63: Housekeeper | Y63: Pomeme | Z63: Pomeme | AA63: Pomeme | AC63: {=SUMPRODUCT(--(INDEX('1880 Bastrop 0008 Clean'!A:AA, MATCH(A63 & "|" & B63, '1880 Bastrop 0008 Clean'!A:A & "|" & '1880 Bastrop 0008 Clean'!B:B, 0), 0) <> '1880 Bastrop 0008 Raw'!A63:AA63))} -> 0
A64: 15 | B64: 12 | D64: Nettle | E64: Alois | F64: White | G64: Male | H64: 23 | J64: Abt 1857 | K64: Son | L64: Single | N64: Shoemaker | Y64: Texas | Z64: Selasia | AA64: Pomeme | AC64: {=SUMPRODUCT(--(INDEX('1880 Bastrop 0008 Clean'!A:AA, MATCH(A64 & "|" & B64, '1880 Bastrop 0008 Clean'!A:A & "|" & '1880 Bastrop 0008 Clean'!B:B, 0), 0) <> '1880 Bastrop 0008 Raw'!A64:AA64))} -> 0
A65: 16 | B65: 12 | D65: Nettle | E65: Ida | F65: White | G65: Female | H65: 21 | J65: Abt 1859 | K65: Daughter | L65: Single | Y65: Texas | Z65: Selasia | AA65: Pomeme | AC65: {=SUMPRODUCT(--(INDEX('1880 Bastrop 0008 Clean'!A:AA, MATCH(A65 & "|" & B65, '1880 Bastrop 0008 Clean'!A:A & "|" & '1880 Bastrop 0008 Clean'!B:B, 0), 0) <> '1880 Bastrop 0008 Raw'!A65:AA65))} -> 0
A66: 17 | B66: 12 | D66: Nettle | E66: Alfred | F66: White | G66: Male | H66: 20 | J66: Abt 1860 | K66: Son | L66: Single | N66: Apprentice shoemaker | Y66: Texas | Z66: Selasia | AA66: Pomeme | AC66: {=SUMPRODUCT(--(INDEX('1880 Bastrop 0008 Clean'!A:AA, MATCH(A66 & "|" & B66, '1880 Bastrop 0008 Clean'!A:A & "|" & '1880 Bastrop 0008 Clean'!B:B, 0), 0) <> '1880 Bastrop 0008 Raw'!A66:AA66))} -> 0
A67: 18 | B67: 12 | D67: Nettle | E67: Paul | F67: White | G67: Male | H67: 18 | J67: Abt 1862 | K67: Son | L67: Single | N67: Apprentice carpenter | Y67: Texas | Z67: Selasia | AA67: Pomeme | AC67: {=SUMPRODUCT(--(INDEX('1880 Bastrop 0008 Clean'!A:AA, MATCH(A67 & "|" & B67, '1880 Bastrop 0008 Clean'!A:A & "|" & '1880 Bastrop 0008 Clean'!B:B, 0), 0) <> '1880 Bastrop 0008 Raw'!A67:AA67))} -> 0
A68: 19 | B68: 12 | D68: Nettle | E68: Joseph | F68: White | G68: Male | H68: 14 | J68: Abt 1866 | K68: Son | L68: Single | V68: Y | Y68: Texas | Z68: Selasia | AA68: Pomeme | AC68: {=SUMPRODUCT(--(INDEX('1880 Bastrop 0008 Clean'!A:AA, MATCH(A68 & "|" & B68, '1880 Bastrop 0008 Clean'!A:A & "|" & '1880 Bastrop 0008 Clean'!B:B, 0), 0) <> '1880 Bastrop 0008 Raw'!A68:AA68))} -> 0
A69: 20 | B69: 12 | D69: Nettle | E69: Anna | F69: White | G69: Female | H69: 12 | J69: Abt 1868 | K69: Daughter | L69: Single | V69: Y | Y69: Texas | Z69: Selasia | AA69: Pomeme | AC69: {=SUMPRODUCT(--(INDEX('1880 Bastrop 0008 Clean'!A:AA, MATCH(A69 & "|" & B69, '1880 Bastrop 0008 Clean'!A:A & "|" & '1880 Bastrop 0008 Clean'!B:B, 0), 0) <> '1880 Bastrop 0008 Raw'!A69:AA69))} -> 0
A70: 21 | B70: 12 | D70: Nettle | E70: Clara | F70: White | G70: Female | H70: 10 | J70: Abt 1870 | K70: Daughter | L70: Single | Y70: Texas | Z70: Selasia | AA70: Pomeme | AC70: {=SUMPRODUCT(--(INDEX('1880 Bastrop 0008 Clean'!A:AA, MATCH(A70 & "|" & B70, '1880 Bastrop 0008 Clean'!A:A & "|" & '1880 Bastrop 0008 Clean'!B:B, 0), 0) <> '1880 Bastrop 0008 Raw'!A70:AA70))} -> 1
A71: 22 | B71: 12 | D71: Nettle | E71: Martha | F71: White | G71: Female | H71: 8 | J71: Abt 1872 | K71: Daughter | L71: Single | Y71: Texas | Z71: Selasia | AA71: Pomeme | AC71: {=SUMPRODUCT(--(INDEX('1880 Bastrop 0008 Clean'!A:AA, MATCH(A71 & "|" & B71, '1880 Bastrop 0008 Clean'!A:A & "|" & '1880 Bastrop 0008 Clean'!B:B, 0), 0) <> '1880 Bastrop 0008 Raw'!A71:AA71))} -> 0
A72: 23 | B72: 13 | D72: Lewis | E72: A. S. | F72: White | G72: Male | H72: 25 | J72: Abt 1855 | K72: Self (Head) | L72: Married | N72: Merchant | Y72: Texas | Z72: Poland | AA72: Louisiana | AC72: {=SUMPRODUCT(--(INDEX('1880 Bastrop 0008 Clean'!A:AA, MATCH(A72 & "|" & B72, '1880 Bastrop 0008 Clean'!A:A & "|" & '1880 Bastrop 0008 Clean'!B:B, 0), 0) <> '1880 Bastrop 0008 Raw'!A72:AA72))} -> 0
A73: 24 | B73: 13 | D73: Lewis | E73: Bertha | F73: White | G73: Female | H73: 25 | J73: Abt 1855 | K73: Wife | L73: Married | N73: Housekeeper | Y73: Germany | AC73: {=SUMPRODUCT(--(INDEX('1880 Bastrop 0008 Clean'!A:AA, MATCH(A73 & "|" & B73, '1880 Bastrop 0008 Clean'!A:A & "|" & '1880 Bastrop 0008 Clean'!B:B, 0), 0) <> '1880 Bastrop 0008 Raw'!A73:AA73))} -> 1
A74: 25 | B74: 13 | D74: Lewis | E74: Lizzie | F74: White | G74: Female | H74: 45881 | I74: Nov | J74: Abt 1879 | K74: Daughter | L74: Single | Y74: Texas | Z74: Texas | AA74: Germany | AC74: {=SUMPRODUCT(--(INDEX('1880 Bastrop 0008 Clean'!A:AA, MATCH(A74 & "|" & B74, '1880 Bastrop 0008 Clean'!A:A & "|" & '1880 Bastrop 0008 Clean'!B:B, 0), 0) <> '1880 Bastrop 0008 Raw'!A74:AA74))} -> 0
A75: 26 | B75: 13 | D75: Lewis | E75: F. S. | F75: White | G75: Male | H75: 20 | J75: Abt 1860 | K75: Brother | L75: Single | N75: Merchant | Y75: Texas | Z75: Texas | AA75: Germany | AC75: {=SUMPRODUCT(--(INDEX('1880 Bastrop 0008 Clean'!A:AA, MATCH(A75 & "|" & B75, '1880 Bastrop 0008 Clean'!A:A & "|" & '1880 Bastrop 0008 Clean'!B:B, 0), 0) <> '1880 Bastrop 0008 Raw'!A75:AA75))} -> 0
A76: 27 | B76: 13 | D76: Mc David | E76: R. A. | F76: Black | G76: Female | H76: 24 | J76: Abt 1856 | L76: Single | N76: Servant | W76: Y | X76: Y | Y76: Texas | AC76: {=SUMPRODUCT(--(INDEX('1880 Bastrop 0008 Clean'!A:AA, MATCH(A76 & "|" & B76, '1880 Bastrop 0008 Clean'!A:A & "|" & '1880 Bastrop 0008 Clean'!B:B, 0), 0) <> '1880 Bastrop 0008 Raw'!A76:AA76))} -> 0
A77: 28 | B77: 13 | D77: Helmann | E77: H. | F77: White | G77: Female | H77: 30 | J77: Abt 1850 | L77: Married | Y77: Germany | AC77: {=SUMPRODUCT(--(INDEX('1880 Bastrop 0008 Clean'!A:AA, MATCH(A77 & "|" & B77, '1880 Bastrop 0008 Clean'!A:A & "|" & '1880 Bastrop 0008 Clean'!B:B, 0), 0) <> '1880 Bastrop 0008 Raw'!A77:AA77))} -> 1
A78: 29 | B78: 13 | D78: Helmann | E78: L. | F78: White | G78: Male | H78: 44 | J78: Abt 1836 | L78: Married | Y78: Germany | AC78: {=SUMPRODUCT(--(INDEX('1880 Bastrop 0008 Clean'!A:AA, MATCH(A78 & "|" & B78, '1880 Bastrop 0008 Clean'!A:A & "|" & '1880 Bastrop 0008 Clean'!B:B, 0), 0) <> '1880 Bastrop 0008 Raw'!A78:AA78))} -> 1
A79: 30 | B79: 14 | D79: Shafer | E79: C. W. | F79: White | G79: Male | H79: 32 | J79: Abt 1848 | K79: Self (Head) | L79: Married | N79: Tanner | Y79: Texas | Z79: Germany | AA79: Germany | AC79: {=SUMPRODUCT(--(INDEX('1880 Bastrop 0008 Clean'!A:AA, MATCH(A79 & "|" & B79, '1880 Bastrop 0008 Clean'!A:A & "|" & '1880 Bastrop 0008 Clean'!B:B, 0), 0) <> '1880 Bastrop 0008 Raw'!A79:AA79))} -> 0
A80: 31 | B80: 14 | D80: Shafer | E80: Theracia | F80: White | G80: Female | H80: 30 | J80: Abt 1850 | K80: Wife | L80: Married | N80: Housekeeper | Y80: Germany | Z80: Germany | AA80: Germany | AC80: {=SUMPRODUCT(--(INDEX('1880 Bastrop 0008 Clean'!A:AA, MATCH(A80 & "|" & B80, '1880 Bastrop 0008 Clean'!A:A & "|" & '1880 Bastrop 0008 Clean'!B:B, 0), 0) <> '1880 Bastrop 0008 Raw'!A80:AA80))} -> 0
A81: 32 | B81: 14 | D81: Shafer | E81: William | F81: White | G81: Male | H81: 6 | J81: Abt 1874 | K81: Son | L81: Single | Y81: Texas | Z81: Texas | AA81: Germany | AC81: {=SUMPRODUCT(--(INDEX('1880 Bastrop 0008 Clean'!A:AA, MATCH(A81 & "|" & B81, '1880 Bastrop 0008 Clean'!A:A & "|" & '1880 Bastrop 0008 Clean'!B:B, 0), 0) <> '1880 Bastrop 0008 Raw'!A81:AA81))} -> 0
A82: 33 | B82: 14 | D82: Shafer | E82: Sophia | F82: White | G82: Female | H82: 4 | J82: Abt 1876 | K82: Daughter | L82: Single | Y82: Texas | Z82: Texas | AA82: Germany | AC82: {=SUMPRODUCT(--(INDEX('1880 Bastrop 0008 Clean'!A:AA, MATCH(A82 & "|" & B82, '1880 Bastrop 0008 Clean'!A:A & "|" & '1880 Bastrop 0008 Clean'!B:B, 0), 0) <> '1880 Bastrop 0008 Raw'!A82:AA82))} -> 0
A83: 34 | B83: 14 | D83: Shafer | E83: Julia | F83: White | G83: Female | H83: 2 | J83: Abt 1878 | K83: Daughter | L83: Single | Y83: Texas | Z83: Texas | AA83: Germany | AC83: {=SUMPRODUCT(--(INDEX('1880 Bastrop 0008 Clean'!A:AA, MATCH(A83 & "|" & B83, '1880 Bastrop 0008 Clean'!A:A & "|" & '1880 Bastrop 0008 Clean'!B:B, 0), 0) <> '1880 Bastrop 0008 Raw'!A83:AA83))} -> 0
A84: 35 | B84: 15 | D84: Birch | E84: Nelson | F84: White | G84: Male | H84: 75 | J84: Abt 1805 | K84: Self (Head) | L84: Married | N84: Merchant | Y84: New York | Z84: Massachusetts | AA84: Massachusetts | AC84: {=SUMPRODUCT(--(INDEX('1880 Bastrop 0008 Clean'!A:AA, MATCH(A84 & "|" & B84, '1880 Bastrop 0008 Clean'!A:A & "|" & '1880 Bastrop 0008 Clean'!B:B, 0), 0) <> '1880 Bastrop 0008 Raw'!A84:AA84))} -> 0
A85: 36 | B85: 15 | D85: Birch | E85: E. D. | F85: White | G85: Female | H85: 54 | J85: Abt 1826 | K85: Wife | L85: Married | N85: Housekeeper | Y85: New York | Z85: Massachusetts | AA85: Massachusetts | AC85: {=SUMPRODUCT(--(INDEX('1880 Bastrop 0008 Clean'!A:AA, MATCH(A85 & "|" & B85, '1880 Bastrop 0008 Clean'!A:A & "|" & '1880 Bastrop 0008 Clean'!B:B, 0), 0) <> '1880 Bastrop 0008 Raw'!A85:AA85))} -> 0
A86: 37 | B86: 15 | D86: Demauda | E86: R. M. | F86: White | G86: Female | H86: 56 | J86: Abt 1824 | K86: Sister-in-law | L86: Single | Y86: New York | Z86: Massachusetts | AA86: Massachusetts | AC86: {=SUMPRODUCT(--(INDEX('1880 Bastrop 0008 Clean'!A:AA, MATCH(A86 & "|" & B86, '1880 Bastrop 0008 Clean'!A:A & "|" & '1880 Bastrop 0008 Clean'!B:B, 0), 0) <> '1880 Bastrop 0008 Raw'!A86:AA86))} -> 0
A87: 38 | B87: 16 | D87: Martin | E87: William | F87: Mulatto | G87: Male | H87: 34 | J87: Abt 1846 | K87: Self (Head) | L87: Married | N87: Blacksmith | Y87: Tennessee | AA87: Tennessee | AC87: {=SUMPRODUCT(--(INDEX('1880 Bastrop 0008 Clean'!A:AA, MATCH(A87 & "|" & B87, '1880 Bastrop 0008 Clean'!A:A & "|" & '1880 Bastrop 0008 Clean'!B:B, 0), 0) <> '1880 Bastrop 0008 Raw'!A87:AA87))} -> 0
A88: 39 | B88: 16 | D88: Martin | E88: Elvira | F88: Mulatto | G88: Female | H88: 32 | J88: Abt 1848 | K88: Wife | L88: Married | N88: Housekeeper | Y88: Texas | Z88: Louisiana | AA88: Louisiana | AC88: {=SUMPRODUCT(--(INDEX('1880 Bastrop 0008 Clean'!A:AA, MATCH(A88 & "|" & B88, '1880 Bastrop 0008 Clean'!A:A & "|" & '1880 Bastrop 0008 Clean'!B:B, 0), 0) <> '1880 Bastrop 0008 Raw'!A88:AA88))} -> 0
A89: 40 | B89: 16 | D89: Black | E89: Laura | F89: Black | G89: Female | H89: 14 | J89: Abt 1866 | L89: Single | X89: Y | Y89: Texas | AC89: {=SUMPRODUCT(--(INDEX('1880 Bastrop 0008 Clean'!A:AA, MATCH(A89 & "|" & B89, '1880 Bastrop 0008 Clean'!A:A & "|" & '1880 Bastrop 0008 Clean'!B:B, 0), 0) <> '1880 Bastrop 0008 Raw'!A89:AA89))} -> 1
A90: 41 | B90: 16 | D90: Holady | E90: Blanch | F90: Black | G90: Female | H90: 11 | J90: Abt 1869 | L90: Single | X90: Y | Y90: Texas | Z90: Alabama | AA90: Texas | AC90: {=SUMPRODUCT(--(INDEX('1880 Bastrop 0008 Clean'!A:AA, MATCH(A90 & "|" & B90, '1880 Bastrop 0008 Clean'!A:A & "|" & '1880 Bastrop 0008 Clean'!B:B, 0), 0) <> '1880 Bastrop 0008 Raw'!A90:AA90))} -> 1
A91: 42 | B91: 17 | D91: Hancock | E91: Booker | F91: Mulatto | G91: Male | H91: 39 | J91: Abt 1841 | K91: Self (Head) | L91: Married | N91: Blacksmith | Y91: Texas | AA91: Virginia | AC91: {=SUMPRODUCT(--(INDEX('1880 Bastrop 0008 Clean'!A:AA, MATCH(A91 & "|" & B91, '1880 Bastrop 0008 Clean'!A:A & "|" & '1880 Bastrop 0008 Clean'!B:B, 0), 0) <> '1880 Bastrop 0008 Raw'!A91:AA91))} -> 0
A92: 43 | B92: 17 | D92: Hancock | E92: Hanale | F92: Black | G92: Female | H92: 34 | J92: Abt 1846 | K92: Wife | L92: Married | N92: Housekeeper | Y92: Alabama | Z92: North Carolina | AA92: Alabama | AC92: {=SUMPRODUCT(--(INDEX('1880 Bastrop 0008 Clean'!A:AA, MATCH(A92 & "|" & B92, '1880 Bastrop 0008 Clean'!A:A & "|" & '1880 Bastrop 0008 Clean'!B:B, 0), 0) <> '1880 Bastrop 0008 Raw'!A92:AA92))} -> 0
A93: 44 | B93: 17 | D93: Hancock | E93: Louis | F93: Mulatto | G93: Male | H93: 13 | J93: Abt 1867 | K93: Son | L93: Single | V93: Y | Y93: Texas | Z93: Texas | AA93: Alabama | AC93: {=SUMPRODUCT(--(INDEX('1880 Bastrop 0008 Clean'!A:AA, MATCH(A93 & "|" & B93, '1880 Bastrop 0008 Clean'!A:A & "|" & '1880 Bastrop 0008 Clean'!B:B, 0), 0) <> '1880 Bastrop 0008 Raw'!A93:AA93))} -> 0
A94: 45 | B94: 17 | D94: Hancock | E94: Louisa | F94: Mulatto | G94: Female | H94: 11 | J94: Abt 1869 | K94: Daughter | L94: Single | V94: Y | Y94: Texas | Z94: Texas | AA94: Alabama | AC94: {=SUMPRODUCT(--(INDEX('1880 Bastrop 0008 Clean'!A:AA, MATCH(A94 & "|" & B94, '1880 Bastrop 0008 Clean'!A:A & "|" & '1880 Bastrop 0008 Clean'!B:B, 0), 0) <> '1880 Bastrop 0008 Raw'!A94:AA94))} -> 0
A95: 46 | B95: 17 | D95: Hancock | E95: Estellar | F95: Mulatto | G95: Male | H95: 8 | J95: Abt 1872 | K95: Son | L95: Single | Y95: Texas | Z95: Texas | AA95: Alabama | AC95: {=SUMPRODUCT(--(INDEX('1880 Bastrop 0008 Clean'!A:AA, MATCH(A95 & "|" & B95, '1880 Bastrop 0008 Clean'!A:A & "|" & '1880 Bastrop 0008 Clean'!B:B, 0), 0) <> '1880 Bastrop 0008 Raw'!A95:AA95))} -> 0
A96: 47 | B96: 17 | D96: Hancock | E96: Clarance | F96: Mulatto | G96: Male | H96: 6 | J96: Abt 1874 | K96: Son | L96: Single | Y96: Texas | Z96: Texas | AA96: Alabama | AC96: {=SUMPRODUCT(--(INDEX('1880 Bastrop 0008 Clean'!A:AA, MATCH(A96 & "|" & B96, '1880 Bastrop 0008 Clean'!A:A & "|" & '1880 Bastrop 0008 Clean'!B:B, 0), 0) <> '1880 Bastrop 0008 Raw'!A96:AA96))} -> 0
A97: 48 | B97: 17 | D97: Hancock | E97: Ferdenand | F97: Mulatto | G97: Male | H97: 2 | J97: Abt 1878 | K97: Son | L97: Single | Y97: Texas | Z97: Texas | AA97: Alabama | AC97: {=SUMPRODUCT(--(INDEX('1880 Bastrop 0008 Clean'!A:AA, MATCH(A97 & "|" & B97, '1880 Bastrop 0008 Clean'!A:A & "|" & '1880 Bastrop 0008 Clean'!B:B, 0), 0) <> '1880 Bastrop 0008 Raw'!A97:AA97))} -> 0
A98: 1 | B98: 18 | D98: Shaffer | E98: Charles | F98: White | G98: Male | H98: 48 | J98: Abt 1832 | K98: Self (Head) | L98: Married | N98: Confectioner | Y98: France | Z98: France | AA98: France | AC98: {=SUMPRODUCT(--(INDEX('1880 Bastrop 0008 Clean'!A:AA, MATCH(A98 & "|" & B98, '1880 Bastrop 0008 Clean'!A:A & "|" & '1880 Bastrop 0008 Clean'!B:B, 0), 0) <> '1880 Bastrop 0008 Raw'!A98:AA98))} -> 0
A99: 2 | B99: 18 | D99: Shaffer | E99: Anna | F99: White | G99: Female | H99: 59 | J99: Abt 1821 | K99: Wife | L99: Married | N99: Housekeeper | Y99: Prussia | Z99: Prussia | AA99: Prussia | AC99: {=SUMPRODUCT(--(INDEX('1880 Bastrop 0008 Clean'!A:AA, MATCH(A99 & "|" & B99, '1880 Bastrop 0008 Clean'!A:A & "|" & '1880 Bastrop 0008 Clean'!B:B, 0), 0) <> '1880 Bastrop 0008 Raw'!A99:AA99))} -> 0
A100: 3 | B100: 18 | D100: Beacher | E100: Richard | F100: White | G100: Male | H100: 31 | J100: Abt 1849 | L100: Single | N100: Clerk in shop | Y100: Prussia | Z100: Prussia | AA100: Prussia | AC100: {=SUMPRODUCT(--(INDEX('1880 Bastrop 0008 Clean'!A:AA, MATCH(A100 & "|" & B100, '1880 Bastrop 0008 Clean'!A:A & "|" & '1880 Bastrop 0008 Clean'!B:B, 0), 0) <> '1880 Bastrop 0008 Raw'!A100:AA100))} -> 1
...

Sheet 1900 Bastrop 0001 Clean
A1: Line Number | B1: Family Number | C1: Street | D1: House Number | E1: Number of Dwelling in Order of Visitation | F1: Surname | G1: Given Name | H1: Relationship | I1: Race | J1: Gender | K1: Birth Month | L1: Birth Year | M1: Age | N1: Marital Status | O1: Years Married | P1: Number of Children Born | Q1: Number of Children Living | R1: Birthplace | S1: Father's Birthplace | T1: Mother's Birthplace | U1: Immigration Year | V1: Years in US | W1: Naturalization | X1: Occupation | Y1: Months Not Employed | Z1: Attended School | AA1: Can Read | AB1: Can Write | AC1: Can Speak English | AD1: House Owned or Rented | AE1: House Owned Free or Mortgaged | AF1: Farm or House
A2: 1 | B2: 1 | E2: 1 | F2: Garner | G2: Earl A | H2: Head | I2: White | J2: Male | K2: Jan | L2: 1850 | M2: 50 | N2: Married | O2: 13 | R2: Germany | S2: Germany | T2: Germany | U2: 1878 | V2: 21 | W2: Naturalized | X2: Farmer | Y2: 0 | AA2: Y | AB2: Y | AC2: Y | AD2: Own | AE2: F | AF2: F
A3: 2 | B3: 1 | E3: 1 | F3: Garner | G3: Anna | H3: Wife | I3: White | J3: Female | K3: Oct | L3: 1862 | M3: 37 | N3: Married | O3: 13 | P3: 4 | Q3: 4 | R3: Germany | S3: Germany | T3: Germany | U3: 1883 | V3: 17 | AA3: N | AB3: N | AC3: Y
A4: 3 | B4: 1 | E4: 1 | F4: Garner | G4: Julia | H4: Daughter | I4: White | J4: Female | K4: Aug | L4: 1888 | M4: 11 | N4: Single | R4: Texas, USA | S4: Germany | T4: Germany | Z4: 0 | AA4: Y | AB4: Y | AC4: Y
A5: 4 | B5: 1 | E5: 1 | F5: Garner | G5: Karl | H5: Son | I5: White | J5: Male | K5: Jan | L5: 1890 | M5: 10 | N5: Single | R5: Texas, USA | S5: Germany | T5: Germany | X5: Farmer Labor | Y5: 0 | Z5: 0 | AA5: Y | AB5: Y | AC5: Y
A6: 5 | B6: 1 | E6: 1 | F6: Garner | G6: Adolph | H6: Son | I6: White | J6: Male | K6: Dec | L6: 1891 | M6: 8 | N6: Single | R6: Texas, USA | S6: Germany | T6: Germany | Z6: 0 | AA6: Y | AB6: Y | AC6: Y
A7: 6 | B7: 2 | E7: 2 | F7: Hogan | G7: James T | H7: Head | I7: Black | J7: Male | K7: Nov | L7: 1851 | M7: 48 | N7: Married | O7: 28 | R7: Georgia, USA | S7: Georgia, USA | T7: Georgia, USA | X7: Farmer | Y7: 0 | AA7: Y | AB7: Y | AC7: Y | AD7: Rent | AF7: F
A8: 7 | B8: 2 | E8: 2 | F8: Hogan | G8: Amey | H8: Wife | I8: Black | J8: Female | K8: May | L8: 1854 | M8: 46 | N8: Married | O8: 28 | P8: 12 | Q8: 11 | R8: Alabama, USA | S8: Mississippi, USA | T8: Mississippi, USA | AA8: N | AB8: N | AC8: Y
A9: 8 | B9: 2 | E9: 2 | F9: Hogan | G9: Ella J | H9: Daughter | I9: Black | J9: Female | K9: Oct | L9: 1882 | M9: 17 | N9: Single | R9: Texas, USA | S9: Georgia, USA | T9: Alabama, USA | X9: Farm Laborer | Y9: 0 | Z9: 0 | AA9: Y | AB9: Y | AC9: Y
A10: 9 | B10: 2 | E10: 2 | F10: Hogan | G10: Moses | H10: Son | I10: Black | J10: Male | K10: Feb | L10: 1885 | M10: 15 | N10: Single | R10: Texas, USA | S10: Georgia, USA | T10: Alabama, USA | X10: Farm Laborer | Y10: 0 | Z10: 0 | AA10: Y | AB10: N | AC10: Y
A11: 10 | B11: 2 | E11: 2 | F11: Hogan | G11: Webster | H11: Son | I11: Black | J11: Male | K11: Apr | L11: 1887 | M11: 13 | N11: Single | R11: Texas, USA | S11: Georgia, USA | T11: Alabama, USA | X11: Farm Laborer | Y11: 0 | Z11: 0 | AA11: N | AB11: N | AC11: Y
A12: 11 | B12: 2 | E12: 2 | F12: Hogan | G12: Thomas K | H12: Son | I12: Black | J12: Male | K12: Aug | L12: 1889 | M12: 10 | N12: Single | R12: Texas, USA | S12: Georgia, USA | T12: Alabama, USA | X12: At Sch | Z12: 8 | AA12: Y | AB12: Y | AC12: Y
A13: 12 | B13: 2 | E13: 2 | F13: Hogan | G13: Willie B | H13: Son | I13: Black | J13: Male | K13: Jul | L13: 1892 | M13: 7 | N13: Single | R13: Texas, USA | S13: Georgia, USA | T13: Alabama, USA
A14: 13 | B14: 2 | E14: 2 | F14: Hogan | G14: Robert | H14: Son | I14: Black | J14: Male | K14: Nov | L14: 1894 | M14: 5 | N14: Single | R14: Texas, USA | S14: Georgia, USA | T14: Alabama, USA
A15: 14 | B15: 2 | E15: 2 | F15: Hogan | G15: Sallie | H15: Daughter | I15: Black | J15: Female | K15: May | L15: 1897 | M15: 3 | N15: Single | R15: Texas, USA | S15: Georgia, USA | T15: Alabama, USA
A16: 15 | B16: 2 | E16: 2 | F16: Hogan | G16: May B | H16: Daughter | I16: Black | J16: Female | K16: Oct | L16: 1899 | M16: 45850 | N16: Single | R16: Texas, USA | S16: Georgia, USA | T16: Alabama, USA
A17: 16 | B17: 2 | E17: 2 | F17: Mathews | G17: William | H17: Son-in-law | I17: Black | J17: Male | K17: Jan | L17: 1868 | M17: 32 | N17: Married | O17: 12 | R17: Texas, USA | S17: Texas, USA | T17: Texas, USA | X17: Farm Laborer | Y17: 0 | AA17: Y | AB17: Y | AC17: Y
A18: 17 | B18: 2 | E18: 2 | F18: Mathews | G18: Ida | H18: Wife | I18: Black | J18: Female | K18: Oct | L18: 1872 | M18: 27 | N18: Married | O18: 12 | P18: 7 | Q18: 5 | R18: Texas, USA | S18: Georgia, USA | T18: Alabama, USA | AA18: Y | AB18: Y | AC18: Y
A19: 18 | B19: 2 | E19: 2 | F19: Mathews | G19: Dave | H19: Son | I19: Black | J19: Male | K19: Mar | L19: 1888 | M19: 12 | N19: Single | R19: Texas, USA | S19: Texas, USA | T19: Texas, USA | X19: Farm Laborer | Y19: 0 | Z19: 0 | AA19: Y | AB19: Y | AC19: Y
A20: 19 | B20: 2 | E20: 2 | F20: Mathews | G20: Birdie A | H20: Daughter | I20: Black | J20: Female | K20: Dec | L20: 1890 | M20: 9 | N20: Single | R20: Texas, USA | S20: Texas, USA | T20: Texas, USA | Z20: 0
A21: 20 | B21: 2 | E21: 2 | F21: Mathews | G21: Mayjor | H21: Son | I21: Black | J21: Male | K21: Aug | L21: 1894 | M21: 5 | N21: Single | R21: Texas, USA | S21: Texas, USA | T21: Texas, USA
A22: 21 | B22: 2 | E22: 2 | F22: Mathews | G22: Minnie | H22: Daughter | I22: Black | J22: Female | K22: Sep | L22: 1893 | M22: 6 | N22: Single | R22: Texas, USA | S22: Texas, USA | T22: Texas, USA
A23: 22 | B23: 2 | E23: 2 | F23: Mathews | G23: Walter | H23: Son | I23: Black | J23: Male | K23: Jul | L23: 1898 | M23: 1 | N23: Single | R23: Texas, USA | S23: Texas, USA | T23: Texas, USA
A24: 23 | B24: 3 | E24: 3 | F24: Manuel | G24: Alemann | H24: Head | I24: White | J24: Male | K24: May | L24: 1852 | M24: 48 | N24: Married | O24: 13 | R24: Mexico | S24: Mexico | T24: Mexico | U24: 1864 | V24: 36 | W24: Naturalized | X24: Farmer | Y24: 0 | AA24: N | AB24: N | AC24: Y | AD24: Rent | AF24: F
A25: 24 | B25: 3 | E25: 3 | F25: Manuel | G25: Domingo | H25: Wife | I25: White | J25: Female | K25: Sep | L25: 1873 | M25: 26 | N25: Married | O25: 13 | P25: 4 | Q25: 4 | R25: Texas, USA | S25: Texas, USA | T25: Texas, USA | AA25: N | AB25: N | AC25: Y
A26: 25 | B26: 3 | E26: 3 | F26: Manuel | G26: Rafel | H26: Son | I26: White | J26: Male | K26: Jun | L26: 1888 | M26: 11 | N26: Single | R26: Texas, USA | S26: Mexico | T26: Texas, USA | X26: Farm Laborer | Y26: 0 | Z26: 0 | AA26: N | AB26: N | AC26: Y
A27: 26 | B27: 3 | E27: 3 | F27: Manuel | G27: Lupie | H27: Daughter | I27: White | J27: Female | K27: Apr | L27: 1891 | M27: 9 | N27: Single | R27: Texas, USA | S27: Mexico | T27: Texas, USA | Z27: 0
A28: 27 | B28: 3 | E28: 3 | F28: Manuel | G28: John | H28: Son | I28: White | J28: Male | K28: Sep | L28: 1893 | M28: 6 | N28: Single | R28: Texas, USA | S28: Mexico | T28: Texas, USA
A29: 28 | B29: 3 | E29: 3 | F29: Manuel | G29: Severa | H29: Daughter | I29: White | J29: Female | K29: Sep | L29: 1896 | M29: 3 | N29: Single | R29: Texas, USA | S29: Mexico | T29: Texas, USA
A30: 29 | B30: 4 | E30: 4 | F30: Enicia | G30: Gonzales | H30: Head | I30: White | J30: Male | K30: Jun | L30: 1866 | M30: 33 | N30: Married | O30: 13 | R30: Mexico | S30: Mexico | T30: Mexico | U30: 1896 | V30: 4 | W30: Alien | X30: Farm Laborer | Y30: 0 | AA30: N | AB30: N | AC30: N | AD30: Rent | AF30: H
A31: 30 | B31: 4 | E31: 4 | F31: Enicia | G31: Marie | H31: Wife | I31: White | J31: Female | K31: May | L31: 1870 | M31: 30 | N31: Married | O31: 13 | P31: 6 | Q31: 5 | R31: Mexico | S31: Mexico | T31: Mexico | U31: 1896 | V31: 4 | AA31: N | AB31: N | AC31: N
A32: 31 | B32: 4 | E32: 4 | F32: Enicia | G32: Eladia | H32: Daughter | I32: White | J32: Female | K32: Jan | L32: 1889 | M32: 11 | N32: Single | R32: Mexico | S32: Mexico | T32: Mexico | U32: 1896 | V32: 4 | X32: Farm Laborer | Z32: 0 | AA32: N | AB32: N | AC32: N
A33: 32 | B33: 4 | E33: 4 | F33: Enicia | G33: Manuel | H33: Daughter | I33: White | J33: Female | K33: Mar | L33: 1892 | M33: 8 | N33: Single | R33: Mexico | S33: Mexico | T33: Mexico | U33: 1896 | V33: 4 | Z33: 0
A34: 33 | B34: 4 | E34: 4 | F34: Enicia | G34: John | H34: Son | I34: White | J34: Male | K34: Jun | L34: 1893 | M34: 6 | N34: Single | R34: Mexico | S34: Mexico | T34: Mexico | U34: 1896 | V34: 4
A35: 34 | B35: 4 | E35: 4 | F35: Enicia | G35: Lenora | H35: Daughter | I35: White | J35: Female | K35: Dec | L35: 1895 | M35: 4 | N35: Single | R35: Mexico | S35: Mexico | T35: Mexico | U35: 1896 | V35: 4
A36: 35 | B36: 4 | E36: 4 | F36: Enicia | G36: Elerico | H36: Son | I36: White | J36: Male | K36: Jan | L36: 1900 | M36: 45759 | N36: Single | R36: Texas, USA | S36: Mexico | T36: Mexico
A37: 36 | B37: 5 | E37: 4 | F37: Albrecht | G37: Charles E | H37: Head | I37: White | J37: Male | K37: Oct | L37: 1870 | M37: 29 | N37: Married | O37: 10 | R37: Texas, USA | S37: Germany | T37: Germany | X37: Farmer | Y37: 0 | AA37: Y | AB37: Y | AC37: Y | AD37: Rent | AF37: F
A38: 37 | B38: 5 | E38: 4 | F38: Albrecht | G38: Annie B | H38: Wife | I38: White | J38: Female | K38: Nov | L38: 1865 | M38: 34 | N38: Married | O38: 10 | P38: 4 | Q38: 3 | R38: Texas, USA | S38: Texas, USA | T38: Texas, USA | AA38: Y | AB38: Y | AC38: Y
A39: 38 | B39: 5 | E39: 4 | F39: Albrecht | G39: Thomas O | H39: Son | I39: White | J39: Male | K39: Apr | L39: 1895 | M39: 5 | N39: Single | R39: Texas, USA | S39: Texas, USA | T39: Texas, USA
A40: 39 | B40: 5 | E40: 4 | F40: Albrecht | G40: Golda | H40: Daughter | I40: White | J40: Female | K40: Aug | L40: 1897 | M40: 2 | N40: Single | R40: Texas, USA | S40: Texas, USA | T40: Texas, USA
A41: 40 | B41: 5 | E41: 4 | F41: Albrecht | G41: Frank | H41: Son | I41: White | J41: Male | K41: Dec | L41: 1899 | M41: 45789 | N41: Single | R41: Texas, USA | S41: Texas, USA | T41: Texas, USA
A42: 41 | B42: 6 | E42: 5 | F42: Stricklind | G42: Tate J | H42: Head | I42: White | J42: Male | K42: Sep | L42: 1862 | M42: 37 | N42: Single | R42: Texas, USA | S42: Texas, USA | T42: Texas, USA | X42: Farmer | Y42: 0 | AA42: Y | AB42: Y | AC42: Y | AD42: Rent | AF42: F
A43: 42 | B43: 7 | E43: 6 | F43: Are | G43: John | H43: Head | I43: White | J43: Male | K43: Jun | L43: 1853 | M43: 46 | N43: Married | O43: 23 | R43: Texas, USA | S43: Mexico | T43: Mexico | X43: Farmer | Y43: 0 | AA43: N | AB43: N | AC43: Y | AD43: Rent | AF43: F
A44: 43 | B44: 7 | E44: 6 | F44: Are | G44: Tanis | H44: Wife | I44: White | J44: Female | K44: May | L44: 1853 | M44: 47 | N44: Married | O44: 23 | P44: 16 | Q44: 5 | R44: Mexico | S44: Mexico | T44: Mexico | U44: 1885 | V44: 15 | AA44: N | AB44: N | AC44: N
A45: 44 | B45: 7 | E45: 6 | F45: Are | G45: Fidelia | H45: Daughter | I45: White | J45: Female | K45: Nov | L45: 1886 | M45: 18 | N45: Single | R45: Texas, USA | S45: Texas, USA | T45: Mexico | X45: Farm Laborer | Y45: 0 | Z45: 0 | AA45: N | AB45: N | AC45: Y
A46: 45 | B46: 7 | E46: 6 | F46: Are | G46: L | H46: Daughter | I46: White | J46: Female | K46: Dec | L46: 1891 | M46: 8 | N46: Single | R46: Texas, USA | S46: Texas, USA | T46: Mexico | Z46: 0
A47: 46 | B47: 7 | E47: 6 | F47: Are | G47: Walukie | H47: Son | I47: White | J47: Male | K47: Dec | L47: 1896 | M47: 3 | N47: Single | R47: Texas, USA | S47: Texas, USA | T47: Mexico
A48: 47 | B48: 7 | E48: 6 | F48: Marcos | G48: Gi??nes | H48: Boarder | I48: White | J48: Male | K48: Apr | L48: 1851 | M48: 59 | N48: Widowed | R48: Mexico | S48: Mexico | T48: Mexico | U48: 1860 | V48: 40 | W48: Naturalized | X48: Farm Laborer | Y48: 0 | AA48: Y | AB48: Y | AC48: Y
A49: 48 | B49: 7 | E49: 6 | F49: Marcos | G49: Pablo | H49: Boarder | I49: White | J49: Male | K49: May | L49: 1861 | M49: 34 | N49: Widowed | R49: Mexico | S49: Mexico | T49: Mexico | U49: 1887 | W49: Alien | X49: Farm Laborer | Y49: 0 | AA49: Y | AB49: Y | AC49: N
A50: 49 | B50: 8 | E50: 6 | F50: Oyes | H50: Head | I50: White | J50: Male | L50: 1875 | M50: 25 | N50: Married | O50: 9 | R50: Mexico | S50: Mexico | T50: Mexico | U50: 1867 | X50: Farmer | Y50: 0 | AA50: N | AB50: N | AC50: Y | AD50: Rent | AF50: F
A51: 50
A52: 1 | B52: 8 | E52: 6 | F52: Oyes | G52: Josephine | H52: Daughter | I52: White | J52: Female | K52: Aug | L52: 1883 | M52: 16 | N52: Single | R52: Texas, USA | S52: Mexico | T52: Texas, USA | X52: Farm Laborer | Y52: 0 | Z52: 0 | AA52: Y | AB52: N | AC52: Y
A53: 2 | B53: 8 | E53: 6 | F53: Oyes | G53: Linie | H53: Daughter | I53: White | J53: Female | K53: Jul | L53: 1887 | M53: 12 | N53: Single | R53: Texas, USA | S53: Mexico | T53: Texas, USA | X53: Farm Laborer | Y53: 0 | Z53: 0 | AA53: N | AB53: N | AC53: Y
A54: 3 | B54: 8 | E54: 6 | F54: Oyes | G54: Mary | H54: Daughter | I54: White | J54: Female | K54: Apr | L54: 1891 | M54: 9 | N54: Single | R54: Texas, USA | S54: Mexico | T54: Texas, USA | Z54: 0
A55: 4 | B55: 8 | E55: 6 | F55: Oyes | G55: Rose | H55: Daughter | I55: White | J55: Female | K55: Apr | L55: 1894 | M55: 6 | N55: Single | R55: Texas, USA | S55: Mexico | T55: Texas, USA
A56: 5 | B56: 8 | E56: 6 | F56: Oyes | G56: Bartolia | H56: Daughter | I56: White | J56: Female | K56: Aug | L56: 1898 | M56: 1 | N56: Single | R56: Texas, USA | S56: Mexico | T56: Texas, USA
A57: 6 | B57: 8 | E57: 6 | F57: Oyes | G57: Jesus | H57: Father | I57: White | J57: Male | K57: May | L57: 1845 | M57: 55 | N57: Widowed | R57: Mexico | S57: Mexico | T57: Mexico | U57: 1867 | V57: 33 | W57: Naturalized | X57: Farm Laborer | Y57: 0 | AA57: Y | AB57: Y | AC57: Y | AF57: H
A58: 7 | B58: 9 | E58: 8 | F58: Roomel | G58: Franco | H58: Head | I58: White | J58: Male | K58: Aug | L58: 1865 | M58: 34 | N58: Married | O58: 2 | R58: Mexico | S58: Mexico | T58: Mexico | U58: 1896 | V58: 4 | W58: Alien | X58: Farmer | Y58: 0 | AA58: N | AB58: N | AC58: N | AD58: Rent | AF58: F
A59: 8 | B59: 9 | E59: 8 | F59: Roomel | G59: Telisfora | H59: Wife | I59: White | J59: Female | K59: Jan | L59: 1860 | M59: 40 | N59: Married | O59: 2 | P59: 0 | Q59: 0 | R59: Mexico | S59: Mexico | T59: Mexico | U59: 1896 | V59: 4 | AA59: Y | AB59: Y | AC59: N
A60: 9 | B60: 10 | E60: 9 | F60: Gibberto | G60: Aleags | H60: Head | I60: White | J60: Male | K60: Dec | L60: 1856 | M60: 43 | N60: Married | O60: 12 | R60: Mexico | S60: Mexico | T60: Mexico | U60: 1893 | V60: 7 | W60: Alien | X60: Farmer | Y60: 0 | AA60: Y | AB60: Y | AC60: N | AD60: Rent | AF60: F
A61: 10 | B61: 10 | E61: 9 | F61: Gibberto | G61: Romany | H61: Wife | I61: White | J61: Female | K61: Feb | L61: 1874 | M61: 26 | N61: Married | O61: 12 | P61: 3 | Q61: 3 | R61: Mexico | S61: Mexico | T61: Mexico | U61: 1893 | V61: 7 | AA61: N | AB61: N | AC61: N
A62: 11 | B62: 10 | E62: 9 | F62: Gibberto | G62: Feuloso | H62: Son | I62: White | J62: Male | K62: Feb | L62: 1893 | M62: 7 | N62: Single | R62: Mexico | S62: Mexico | T62: Mexico | U62: 1893 | V62: 7
A63: 12 | B63: 10 | E63: 9 | F63: Gibberto | G63: Mercid | H63: Daughter | I63: White | J63: Female | K63: Mar | L63: 1894 | M63: 6 | N63: Single | R63: Texas, USA | S63: Mexico | T63: Mexico
A64: 13 | B64: 10 | E64: 9 | F64: Gibberto | G64: Joseph | H64: Son | I64: White | J64: Male | K64: Jan | L64: 1896 | M64: 4 | N64: Single | R64: Texas, USA | S64: Mexico | T64: Mexico
A65: 14 | B65: 11 | E65: 10 | F65: Whats | G65: Beto | H65: Head | I65: White | J65: Male | K65: May | L65: 1852 | M65: 48 | N65: Widowed | R65: Mexico | S65: Mexico | T65: Mexico | U65: 1882 | V65: 18 | W65: Alien | X65: Farmer | Y65: 0 | AA65: N | AB65: N | AC65: Y | AD65: Rent | AF65: F
A66: 15 | B66: 11 | E66: 10 | F66: Whats | G66: Mack | H66: Son | I66: White | J66: Male | K66: Jan | L66: 1893 | M66: 7 | N66: Single | R66: Texas, USA | S66: Mexico | T66: Texas, USA
A67: 16 | B67: 11 | E67: 10 | F67: Whats | G67: Peter | H67: Son | I67: White | J67: Male | K67: Sep | L67: 1894 | M67: 5 | N67: Single | R67: Texas, USA | S67: Mexico | T67: Texas, USA
A68: 17 | B68: 11 | E68: 10 | F68: Whats | G68: Everline | H68: Daughter | I68: White | J68: Female | K68: Dec | L68: 1896 | M68: 3 | N68: Single | R68: Texas, USA | S68: Mexico | T68: Texas, USA
A69: 18 | B69: 11 | E69: 10 | F69: Sam??ria | G69: Louis | H69: Boarder | I69: White | J69: Male | K69: Jan | L69: 1855 | M69: 45 | N69: Single | R69: Mexico | S69: Mexico | T69: Mexico | U69: 1882 | V69: 18 | W69: Alien | X69: Farm Laborer | Y69: 0 | AA69: Y | AB69: Y | AC69: N
A70: 19 | B70: 12 | E70: 11 | F70: Schae??ke | G70: Otto A | H70: Head | I70: White | J70: Male | K70: Sep | L70: 1870 | M70: 29 | N70: Married | O70: 4 | R70: Texas, USA | S70: Germany | T70: Germany | X70: Farmer | Y70: 0 | AA70: Y | AB70: Y | AC70: Y | AD70: Rent | AF70: F
A71: 20 | B71: 12 | E71: 11 | F71: Schae??ke | G71: Carry | H71: Wife | I71: White | J71: Female | K71: Jun | L71: 1876 | M71: 23 | N71: Married | O71: 4 | P71: 2 | Q71: 2 | R71: Texas, USA | S71: Germany | T71: Arkansas, USA | AA71: Y | AB71: Y | AC71: Y
A72: 21 | B72: 12 | E72: 11 | F72: Schae??ke | G72: Auther | H72: Son | I72: White | J72: Male | K72: Dec | L72: 1896 | M72: 3 | N72: Single | R72: Texas, USA | S72: Texas, USA | T72: Texas, USA
A73: 22 | B73: 12 | E73: 11 | F73: Schae??ke | G73: Earl | H73: Son | I73: White | J73: Male | K73: May | L73: 1898 | M73: 2 | N73: Single | R73: Texas, USA | S73: Texas, USA | T73: Texas, USA
A74: 23 | B74: 12 | E74: 11 | F74: Hall | G74: John | H74: Boarder | I74: Black | J74: Male | K74: Apr | L74: 1882 | M74: 18 | N74: Single | R74: Texas, USA | S74: Texas, USA | T74: Texas, USA | X74: Farm Laborer | Y74: 0 | Z74: 0 | AA74: N | AB74: N | AC74: Y
A75: 24 | B75: 13 | E75: 12 | F75: Voss | G75: John | H75: Head | I75: White | J75: Male | K75: May | L75: 1845 | M75: 55 | N75: Married | O75: 28 | R75: Germany | S75: Germany | T75: Germany | U75: 1860 | V75: 40 | W75: Naturalized | X75: Farmer | Y75: 0 | AA75: Y | AB75: Y | AC75: Y | AD75: Rent | AF75: F
A76: 25 | B76: 13 | E76: 12 | F76: Voss | G76: Salie A | H76: Wife | I76: White | J76: Female | K76: Aug | L76: 1853 | M76: 46 | N76: Married | O76: 28 | P76: 10 | Q76: 10 | R76: Alabama, USA | S76: South Carolina, USA | T76: South Carolina, USA | AA76: Y | AB76: Y | AC76: Y
A77: 26 | B77: 13 | E77: 12 | F77: Voss | G77: Josephien | H77: Daughter | I77: White | J77: Female | K77: Oct | L77: 1878 | M77: 21 | N77: Single | R77: Texas, USA | S77: Germany | T77: Alabama, USA | AA77: Y | AB77: Y | AC77: Y
A78: 27 | B78: 13 | E78: 12 | F78: Voss | G78: Bula | H78: Daughter | I78: White | J78: Female | K78: Jul | L78: 1881 | M78: 18 | N78: Single | R78: Texas, USA | S78: Germany | T78: Alabama, USA | X78: At Sch | Z78: 6 | AA78: Y | AB78: Y | AC78: Y
A79: 28 | B79: 13 | E79: 12 | F79: Voss | G79: Salie | H79: Daughter | I79: White | J79: Female | K79: Nov | L79: 1883 | M79: 16 | N79: Single | R79: Texas, USA | S79: Germany | T79: Alabama, USA | X79: At Sch | Z79: 6 | AA79: Y | AB79: Y | AC79: Y
A80: 29 | B80: 13 | E80: 12 | F80: Voss | G80: Willie | H80: Daughter | I80: White | J80: Female | K80: Feb | L80: 1886 | M80: 14 | N80: Single | R80: Texas, USA | S80: Germany | T80: Alabama, USA | X80: At Sch | Z80: 6 | AA80: Y | AB80: Y | AC80: Y
A81: 30 | B81: 13 | E81: 12 | F81: Voss | G81: Sophy | H81: Daughter | I81: White | J81: Female | K81: Apr | L81: 1890 | M81: 10 | N81: Single | R81: Texas, USA | S81: Germany | T81: Alabama, USA | X81: At Sch | Z81: 6 | AA81: Y | AB81: Y | AC81: Y
A82: 31 | B82: 13 | E82: 12 | F82: Voss | G82: John | H82: Son | I82: White | J82: Male | K82: Nov | L82: 1892 | M82: 7 | N82: Single | R82: Texas, USA | S82: Germany | T82: Alabama, USA
A83: 32 | B83: 13 | E83: 12 | F83: Voss | G83: Walter | H83: Son | I83: White | J83: Male | K83: Jun | L83: 1895 | M83: 4 | N83: Single | R83: Texas, USA | S83: Germany | T83: Alabama, USA
A84: 33 | B84: 14 | E84: 13 | F84: Looner | G84: Gadulupe | H84: Head | I84: White | J84: Male | K84: Dec | L84: 1842 | M84: 57 | N84: Widowed | R84: Mexico | S84: Mexico | T84: Mexico | U84: 1842 | V84: 51 | W84: Naturalized | X84: Farmer | Y84: 0 | AA84: N | AB84: N | AC84: Y | AD84: Rent | AF84: F
A85: 34 | B85: 14 | E85: 13 | F85: Looner | G85: Domingo | H85: Son | I85: White | J85: Male | K85: Feb | L85: 1884 | M85: 16 | N85: Single | R85: Texas, USA | S85: Mexico | T85: Mexico | X85: Farm Laborer | Y85: 0 | Z85: 0 | AA85: N | AB85: N | AC85: Y
A86: 35 | B86: 14 | E86: 13 | F86: Looner | G86: Joe W | H86: Son | I86: White | J86: Male | K86: Sep | L86: 1869 | M86: 30 | N86: Married | O86: 9 | R86: Texas, USA | S86: Mexico | T86: Mexico | X86: Farm Laborer | Y86: 0 | AA86: N | AB86: N | AC86: Y
A87: 36 | B87: 14 | E87: 13 | F87: Looner | G87: Fannie | H87: Daughter-in-law | I87: White | J87: Female | K87: May | L87: 1875 | M87: 25 | N87: Married | O87: 9 | P87: 4 | Q87: 1 | R87: Texas, USA | S87: Mexico | T87: Mexico | AA87: N | AB87: N | AC87: Y
A88: 37 | B88: 14 | E88: 13 | F88: Looner | G88: Francis | H88: Daughter | I88: White | J88: Female | K88: Mar | L88: 1893 | M88: 7 | N88: Single | R88: Texas, USA | S88: Texas, USA | T88: Texas, USA | AF88: H
A89: 38 | B89: 14 | E89: 13 | F89: Baker | G89: Deedora | H89: Boarder | I89: White | J89: Male | K89: Apr | L89: 1859 | M89: 41 | N89: Single | R89: Mexico | S89: Mexico | T89: Mexico | U89: 1897 | V89: 3 | W89: Alien | X89: Farm Laborer | Y89: 0 | AA89: N | AB89: N | AC89: N
A90: 39 | B90: 14 | E90: 13 | F90: Mandoria | G90: John | H90: Boarder | I90: White | J90: Male | K90: Mar | L90: 1871 | M90: 29 | N90: Single | R90: Mexico | S90: Mexico | T90: Mexico | U90: 1886 | V90: 14 | W90: Alien | X90: Farm Laborer | Y90: 0 | AA90: Y | AB90: Y | AC90: N
A91: 40 | B91: 15 | E91: 14 | F91: Vara | G91: Jesus | H91: Head | I91: White | J91: Male | K91: Jan | L91: 1840 | M91: 60 | N91: Married | O91: 26 | R91: Mexico | S91: Mexico | T91: Mexico | U91: 1841 | V91: 59 | W91: Naturalized | X91: Farmer | Y91: 0 | AA91: N | AB91: N | AC91: Y | AD91: Rent | AF91: F
A92: 41 | B92: 15 | E92: 14 | F92: Vara | G92: Rosie | H92: Wife | I92: White | J92: Female | K92: Aug | L92: 1844 | M92: 53 | N92: Married | O92: 26 | P92: 0 | Q92: 0 | R92: Mexico | S92: Mexico | T92: Mexico | U92: 1870 | V92: 30 | AA92: N | AB92: N | AC92: Y
A93: 42 | B93: 15 | E93: 14 | F93: Vara | G93: Ninsencis | H93: Adopted Son | I93: White | J93: Male | K93: Jul | L93: 1894 | M93: 5 | N93: Single | R93: Texas, USA | S93: Mexico | T93: Texas, USA
A94: 43 | B94: 16 | E94: 15 | F94: Isabel | G94: Gonsalas | H94: Head | I94: White | J94: Male | K94: May | L94: 1875 | M94: 25 | N94: Married | O94: 1 | R94: Texas, USA | S94: Mexico | T94: Mexico | X94: Farm Laborer | Y94: 0 | AA94: N | AB94: N | AC94: Y | AD94: Rent | AF94: H
A95: 44 | B95: 16 | E95: 15 | F95: Isabel | G95: Mary | H95: Wife | I95: White | J95: Female | K95: Feb | L95: 1880 | M95: 20 | N95: Married | O95: 1 | P95: 3 | Q95: 3 | R95: Texas, USA | S95: Mexico | T95: Mexico | AA95: N | AB95: N | AC95: Y | AF95: H
A96: 45 | B96: 16 | E96: 15 | F96: Paulino | G96: Rosie | H96: Daughter | I96: White | J96: Female | K96: Jan | L96: 1893 | M96: 7 | N96: Single | R96: Texas, USA | S96: Texas, USA | T96: Texas, USA
A97: 46 | B97: 16 | E97: 15 | F97: Paulino | G97: Bisenta | H97: Daughter | I97: White | J97: Female | K97: May | L97: 1894 | M97: 6 | N97: Single | R97: Texas, USA | S97: Texas, USA | T97: Texas, USA | Z97: 1
A98: 47 | B98: 16 | E98: 15 | F98: Paulino | G98: Mary | H98: Daughter | I98: White | J98: Female | K98: Aug | L98: 1897 | M98: 2 | N98: Single | R98: Texas, USA | S98: Texas, USA | T98: Texas, USA
